{"name": "SOL AI반도체소부장", "ticker": "455850.KS", "ohlcv": [{"date": "2025-08-28", "open": 12270.3769, "high": 12510.2865, "low": 12175.4127, "close": 12415.3223, "volume": 339794, "vwap_1d": 12367.0071, "vwap_3d": null, "vwap_5d": null, "vwap_10d": null, "vwap_20d": null, "vwap_40d": null, "vwap_60d": null, "vwap_100d": null, "vwap_200d": null}, {"date": "2025-08-29", "open": 12405.3263, "high": 12560.2679, "low": 12405.3263, "close": 12465.3037, "volume": 262008, "vwap_1d": 12476.966, "vwap_3d": null, "vwap_5d": null, "vwap_10d": null, "vwap_20d": null, "vwap_40d": null, "vwap_60d": null, "vwap_100d": null, "vwap_200d": null}, {"date": "2025-09-01", "open": 12165.4164, "high": 12230.3919, "low": 11990.4823, "close": 12000.4785, "volume": 348677, "vwap_1d": 12073.7842, "vwap_3d": 12289.7514, "vwap_5d": null, "vwap_10d": null, "vwap_20d": null, "vwap_40d": null, "vwap_60d": null, "vwap_100d": null, "vwap_200d": null}, {"date": "2025-09-02", "open": 12115.4348, "high": 12115.4348, "low": 11965.4913, "close": 12030.4668, "volume": 208375, "vwap_1d": 12037.131, "vwap_3d": 12193.4326, "vwap_5d": null, "vwap_10d": null, "vwap_20d": null, "vwap_40d": null, "vwap_60d": null, "vwap_100d": null, "vwap_200d": null}, {"date": "2025-09-03", "open": 11965.4912, "high": 12175.4121, "low": 11915.51, "close": 12175.4121, "volume": 177197, "vwap_1d": 12088.7781, "vwap_3d": 12067.0008, "vwap_5d": 12223.6973, "vwap_10d": null, "vwap_20d": null, "vwap_40d": null, "vwap_60d": null, "vwap_100d": null, "vwap_200d": null}, {"date": "2025-09-04", "open": 12190.4066, "high": 12355.3444, "low": 12160.4179, "close": 12235.3896, "volume": 221764, "vwap_1d": 12250.384, "vwap_3d": 12130.0673, "vwap_5d": 12188.5766, "vwap_10d": null, "vwap_20d": null, "vwap_40d": null, "vwap_60d": null, "vwap_100d": null, "vwap_200d": null}, {"date": "2025-09-05", "open": 12410.3243, "high": 12525.281, "low": 12310.362, "close": 12335.3525, "volume": 437018, "vwap_1d": 12390.3318, "vwap_3d": 12289.2888, "vwap_5d": 12197.6291, "vwap_10d": null, "vwap_20d": null, "vwap_40d": null, "vwap_60d": null, "vwap_100d": null, "vwap_200d": null}, {"date": "2025-09-08", "open": 12365.341, "high": 12635.2393, "low": 12365.341, "close": 12635.2393, "volume": 714278, "vwap_1d": 12545.2732, "vwap_3d": 12448.3306, "vwap_5d": 12363.3808, "vwap_10d": null, "vwap_20d": null, "vwap_40d": null, "vwap_60d": null, "vwap_100d": null, "vwap_200d": null}, {"date": "2025-09-09", "open": 12685.2207, "high": 12955.119, "low": 12655.232, "close": 12895.1416, "volume": 1466698, "vwap_1d": 12835.1642, "vwap_3d": 12681.8168, "vwap_5d": 12615.2726, "vwap_10d": null, "vwap_20d": null, "vwap_40d": null, "vwap_60d": null, "vwap_100d": null, "vwap_200d": null}, {"date": "2025-09-10", "open": 13010.0977, "high": 13269.9997, "low": 13010.0977, "close": 13220.0186, "volume": 1949038, "vwap_1d": 13166.7053, "vwap_3d": 12941.4891, "vwap_5d": 12859.187, "vwap_10d": 12720.5637, "vwap_20d": null, "vwap_40d": null, "vwap_60d": null, "vwap_100d": null, "vwap_200d": null}, {"date": "2025-09-11", "open": 13374.9607, "high": 13379.9588, "low": 13090.068, "close": 13324.9795, "volume": 1449306, "vwap_1d": 13265.0021, "vwap_3d": 13096.0361, "vwap_5d": 12979.3865, "vwap_10d": 12846.2409, "vwap_20d": null, "vwap_40d": null, "vwap_60d": null, "vwap_100d": null, "vwap_200d": null}, {"date": "2025-09-12", "open": 13414.9459, "high": 13719.8311, "low": 13404.9497, "close": 13509.9102, "volume": 1350628, "vwap_1d": 13544.897, "vwap_3d": 13304.2632, "vwap_5d": 13126.7501, "vwap_10d": 12971.2415, "vwap_20d": null, "vwap_40d": null, "vwap_60d": null, "vwap_100d": null, "vwap_200d": null}, {"date": "2025-09-15", "open": 13784.8062, "high": 14024.7158, "low": 13629.8646, "close": 14024.7158, "volume": 1437571, "vwap_1d": 13893.0987, "vwap_3d": 13567.2949, "vwap_5d": 13324.969, "vwap_10d": 13145.2938, "vwap_20d": null, "vwap_40d": null, "vwap_60d": null, "vwap_100d": null, "vwap_200d": null}, {"date": "2025-09-16", "open": 14114.6819, "high": 14239.6348, "low": 13994.7271, "close": 14234.6367, "volume": 1359837, "vwap_1d": 14156.3329, "vwap_3d": 13866.0171, "vwap_5d": 13569.9758, "vwap_10d": 13297.3066, "vwap_20d": null, "vwap_40d": null, "vwap_60d": null, "vwap_100d": null, "vwap_200d": null}, {"date": "2025-09-17", "open": 13994.7274, "high": 14169.6615, "low": 13924.7538, "close": 14074.6973, "volume": 951063, "vwap_1d": 14056.3708, "vwap_3d": 14030.0179, "vwap_5d": 13760.6455, "vwap_10d": 13379.8724, "vwap_20d": null, "vwap_40d": null, "vwap_60d": null, "vwap_100d": null, "vwap_200d": null}, {"date": "2025-09-18", "open": 14124.6779, "high": 14674.4707, "low": 13999.7249, "close": 14534.5234, "volume": 1520249, "vwap_1d": 14402.9064, "vwap_3d": 14229.3613, "vwap_5d": 14016.673, "vwap_10d": 13522.7809, "vwap_20d": null, "vwap_40d": null, "vwap_60d": null, "vwap_100d": null, "vwap_200d": null}, {"date": "2025-09-19", "open": 14834.4102, "high": 14844.4064, "low": 14439.5589, "close": 14624.4893, "volume": 1618256, "vwap_1d": 14636.1515, "vwap_3d": 14414.6126, "vwap_5d": 14254.7555, "vwap_10d": 13688.9987, "vwap_20d": null, "vwap_40d": null, "vwap_60d": null, "vwap_100d": null, "vwap_200d": null}, {"date": "2025-09-22", "open": 14734.4487, "high": 14974.3583, "low": 14644.4826, "close": 14844.4072, "volume": 1410920, "vwap_1d": 14821.0827, "vwap_3d": 14615.5626, "vwap_5d": 14447.0131, "vwap_10d": 13855.3409, "vwap_20d": null, "vwap_40d": null, "vwap_60d": null, "vwap_100d": null, "vwap_200d": null}, {"date": "2025-09-23", "open": 15074.3202, "high": 15139.2957, "low": 14699.4614, "close": 14874.3955, "volume": 1481135, "vwap_1d": 14904.3842, "vwap_3d": 14782.0864, "vwap_5d": 14600.6602, "vwap_10d": 14065.2848, "vwap_20d": null, "vwap_40d": null, "vwap_60d": null, "vwap_100d": null, "vwap_200d": null}, {"date": "2025-09-24", "open": 14684.4667, "high": 14969.3594, "low": 14474.5458, "close": 14969.3594, "volume": 1384195, "vwap_1d": 14804.4215, "vwap_3d": 14844.5421, "vwap_5d": 14708.5126, "vwap_10d": 14263.9844, "vwap_20d": 13793.3944, "vwap_40d": null, "vwap_60d": null, "vwap_100d": null, "vwap_200d": null}, {"date": "2025-09-25", "open": 14719.4535, "high": 14949.3669, "low": 14599.4987, "close": 14689.4648, "volume": 1843301, "vwap_1d": 14746.1102, "vwap_3d": 14813.0382, "vwap_5d": 14777.5116, "vwap_10d": 14426.728, "vwap_20d": 13897.1768, "vwap_40d": null, "vwap_60d": null, "vwap_100d": null, "vwap_200d": null}, {"date": "2025-09-26", "open": 14469.5484, "high": 14509.5334, "low": 14119.6802, "close": 14289.6162, "volume": 3167056, "vwap_1d": 14306.2766, "vwap_3d": 14540.8943, "vwap_5d": 14641.4371, "vwap_10d": 14476.7818, "vwap_20d": 13965.2578, "vwap_40d": null, "vwap_60d": null, "vwap_100d": null, "vwap_200d": null}, {"date": "2025-09-29", "open": 14379.5817, "high": 14574.5083, "low": 14219.642, "close": 14539.5215, "volume": 977056, "vwap_1d": 14444.5573, "vwap_3d": 14464.2503, "vwap_5d": 14591.0766, "vwap_10d": 14528.1785, "vwap_20d": 14010.146, "vwap_40d": null, "vwap_60d": null, "vwap_100d": null, "vwap_200d": null}, {"date": "2025-09-30", "open": 14619.4916, "high": 14884.3917, "low": 14519.5292, "close": 14594.501, "volume": 620148, "vwap_1d": 14666.1407, "vwap_3d": 14381.4776, "vwap_5d": 14538.8353, "vwap_10d": 14567.6623, "vwap_20d": 14042.176, "vwap_40d": null, "vwap_60d": null, "vwap_100d": null, "vwap_200d": null}, {"date": "2025-10-01", "open": 14664.4743, "high": 14869.397, "low": 14639.4837, "close": 14829.4121, "volume": 985436, "vwap_1d": 14779.4309, "vwap_3d": 14625.5392, "vwap_5d": 14521.6442, "vwap_10d": 14613.9687, "vwap_20d": 14082.8918, "vwap_40d": null, "vwap_60d": null, "vwap_100d": null, "vwap_200d": null}, {"date": "2025-10-02", "open": 15144.2944, "high": 15384.204, "low": 15139.2962, "close": 15324.2266, "volume": 2529752, "vwap_1d": 15282.5756, "vwap_3d": 15070.2355, "vwap_5d": 14704.1696, "vwap_10d": 14739.6006, "vwap_20d": 14202.9942, "vwap_40d": null, "vwap_60d": null, "vwap_100d": null, "vwap_200d": null}, {"date": "2025-10-10", "open": 15689.0882, "high": 16058.9489, "low": 15414.1918, "close": 15943.9922, "volume": 2280752, "vwap_1d": 15805.711, "vwap_3d": 15402.8883, "vwap_5d": 15214.4386, "vwap_10d": 14895.4147, "vwap_20d": 14348.8319, "vwap_40d": null, "vwap_60d": null, "vwap_100d": null, "vwap_200d": null}, {"date": "2025-10-13", "open": 15244.2564, "high": 16183.9023, "low": 15234.2601, "close": 16183.9023, "volume": 2503258, "vwap_1d": 15867.3549, "vwap_3d": 15645.8627, "vwap_5d": 15482.0182, "vwap_10d": 15038.2169, "vwap_20d": 14506.4715, "vwap_40d": null, "vwap_60d": null, "vwap_100d": null, "vwap_200d": null}, {"date": "2025-10-14", "open": 16558.7608, "high": 16673.7174, "low": 15399.1977, "close": 15789.0508, "volume": 4988445, "vwap_1d": 15953.9886, "vwap_3d": 15897.1911, "vwap_5d": 15697.2831, "vwap_10d": 15262.2129, "vwap_20d": 14776.5878, "vwap_40d": null, "vwap_60d": null, "vwap_100d": null, "vwap_200d": null}, {"date": "2025-10-15", "open": 15804.0444, "high": 16403.8184, "low": 15764.0594, "close": 16403.8184, "volume": 2023811, "vwap_1d": 16190.5654, "vwap_3d": 15981.5142, "vwap_5d": 15830.104, "vwap_10d": 15376.8386, "vwap_20d": 14943.7835, "vwap_40d": null, "vwap_60d": null, "vwap_100d": null, "vwap_200d": null}, {"date": "2025-10-16", "open": 16363.8341, "high": 16653.7249, "low": 16233.8831, "close": 16633.7324, "volume": 2896874, "vwap_1d": 16507.1135, "vwap_3d": 16164.009, "vwap_5d": 16057.8513, "vwap_10d": 15569.9769, "vwap_20d": 15130.2792, "vwap_40d": null, "vwap_60d": null, "vwap_100d": null, "vwap_200d": null}, {"date": "2025-10-17", "open": 16428.8103, "high": 16813.6653, "low": 16368.8329, "close": 16448.8027, "volume": 1856832, "vwap_1d": 16543.767, "vwap_3d": 16422.6321, "vwap_5d": 16161.3842, "vwap_10d": 15838.2013, "vwap_20d": 15256.2407, "vwap_40d": null, "vwap_60d": null, "vwap_100d": null, "vwap_200d": null}, {"date": "2025-10-20", "open": 16733.6946, "high": 16908.6287, "low": 16418.8133, "close": 16643.7285, "volume": 1416331, "vwap_1d": 16657.0568, "vwap_3d": 16552.5636, "vwap_5d": 16270.475, "vwap_10d": 15952.2851, "vwap_20d": 15360.529, "vwap_40d": null, "vwap_60d": null, "vwap_100d": null, "vwap_200d": null}, {"date": "2025-10-21", "open": 16843.654, "high": 16973.6051, "low": 16298.8593, "close": 16443.8047, "volume": 1944804, "vwap_1d": 16572.0897, "vwap_3d": 16585.0739, "vwap_5d": 16484.0494, "vwap_10d": 16037.7872, "vwap_20d": 15464.534, "vwap_40d": null, "vwap_60d": null, "vwap_100d": null, "vwap_200d": null}, {"date": "2025-10-22", "open": 16343.8416, "high": 16638.7305, "low": 16003.9696, "close": 16638.7305, "volume": 2039283, "vwap_1d": 16427.1435, "vwap_3d": 16539.6395, "vwap_5d": 16531.1149, "vwap_10d": 16120.8765, "vwap_20d": 15548.1618, "vwap_40d": null, "vwap_60d": null, "vwap_100d": null, "vwap_200d": null}, {"date": "2025-10-23", "open": 16308.856, "high": 16683.7148, "low": 16163.9106, "close": 16548.7656, "volume": 897393, "vwap_1d": 16465.4637, "vwap_3d": 16491.9354, "vwap_5d": 16532.4165, "vwap_10d": 16227.2292, "vwap_20d": 15614.1402, "vwap_40d": null, "vwap_60d": null, "vwap_100d": null, "vwap_200d": null}, {"date": "2025-10-24", "open": 16898.6328, "high": 17053.5744, "low": 16808.6667, "close": 17038.5801, "volume": 1816391, "vwap_1d": 16966.9404, "vwap_3d": 16640.6626, "vwap_5d": 16627.0887, "vwap_10d": 16330.2065, "vwap_20d": 15717.5586, "vwap_40d": null, "vwap_60d": null, "vwap_100d": null, "vwap_200d": null}, {"date": "2025-10-27", "open": 17138.543, "high": 17268.4941, "low": 16898.6334, "close": 17133.5449, "volume": 1940590, "vwap_1d": 17100.2241, "vwap_3d": 16925.8237, "vwap_5d": 16728.4629, "vwap_10d": 16451.7845, "vwap_20d": 15817.2747, "vwap_40d": null, "vwap_60d": null, "vwap_100d": null, "vwap_200d": null}, {"date": "2025-10-28", "open": 17043.5777, "high": 17338.4666, "low": 16903.6304, "close": 17073.5664, "volume": 1546264, "vwap_1d": 17105.2211, "vwap_3d": 17056.0307, "vwap_5d": 16836.0711, "vwap_10d": 16641.8762, "vwap_20d": 15901.5861, "vwap_40d": null, "vwap_60d": null, "vwap_100d": null, "vwap_200d": null}, {"date": "2025-10-29", "open": 17328.4709, "high": 17453.4238, "low": 16988.599, "close": 17453.4238, "volume": 1696003, "vwap_1d": 17298.4822, "vwap_3d": 17166.5916, "vwap_5d": 17040.9898, "vwap_10d": 16754.1691, "vwap_20d": 15998.8553, "vwap_40d": 15261.1772, "vwap_60d": null, "vwap_100d": null, "vwap_200d": null}, {"date": "2025-10-30", "open": 17458.4215, "high": 17658.3462, "low": 17163.5326, "close": 17483.4121, "volume": 2447622, "vwap_1d": 17435.097, "vwap_3d": 17304.7299, "vwap_5d": 17197.7718, "vwap_10d": 16889.5179, "vwap_20d": 16142.409, "vwap_40d": 15362.5895, "vwap_60d": null, "vwap_100d": null, "vwap_200d": null}, {"date": "2025-10-31", "open": 17383.4507, "high": 17753.3114, "low": 17358.4601, "close": 17693.334, "volume": 1396188, "vwap_1d": 17601.7018, "vwap_3d": 17435.2617, "vwap_5d": 17306.6982, "vwap_10d": 16984.9824, "vwap_20d": 16344.7783, "vwap_40d": 15423.9211, "vwap_60d": null, "vwap_100d": null, "vwap_200d": null}, {"date": "2025-11-03", "open": 17703.3305, "high": 17813.2891, "low": 17403.4435, "close": 17813.2891, "volume": 1643349, "vwap_1d": 17676.6739, "vwap_3d": 17549.8388, "vwap_5d": 17422.2476, "vwap_10d": 17077.1721, "vwap_20d": 16447.2723, "vwap_40d": 15499.3172, "vwap_60d": null, "vwap_100d": null, "vwap_200d": null}, {"date": "2025-11-04", "open": 17928.2455, "high": 18268.1174, "low": 17843.2775, "close": 18113.1758, "volume": 3194452, "vwap_1d": 18074.8569, "vwap_3d": 17863.9218, "vwap_5d": 17670.3717, "vwap_10d": 17301.1192, "vwap_20d": 16597.2065, "vwap_40d": 15631.7351, "vwap_60d": null, "vwap_100d": null, "vwap_200d": null}, {"date": "2025-11-05", "open": 17473.4164, "high": 17638.3543, "low": 16348.8402, "close": 17163.5332, "volume": 2748188, "vwap_1d": 17050.2426, "vwap_3d": 17617.4101, "vwap_5d": 17576.45, "vwap_10d": 17357.6649, "vwap_20d": 16666.5186, "vwap_40d": 15696.2544, "vwap_60d": null, "vwap_100d": null, "vwap_200d": null}, {"date": "2025-11-06", "open": 17593.3718, "high": 17778.3021, "low": 16903.6317, "close": 17403.4434, "volume": 1538909, "vwap_1d": 17361.7924, "vwap_3d": 17551.8136, "vwap_5d": 17577.9366, "vwap_10d": 17398.08, "vwap_20d": 16773.2784, "vwap_40d": 15742.8102, "vwap_60d": null, "vwap_100d": null, "vwap_200d": null}, {"date": "2025-11-07", "open": 16768.6816, "high": 17188.5234, "low": 16353.8379, "close": 16633.7324, "volume": 1496075, "vwap_1d": 16725.3646, "vwap_3d": 17049.1022, "vwap_5d": 17454.7188, "vwap_10d": 17386.7141, "vwap_20d": 16824.0765, "vwap_40d": 15783.2784, "vwap_60d": null, "vwap_100d": null, "vwap_200d": null}, {"date": "2025-11-10", "open": 16713.7026, "high": 17318.4747, "low": 16328.8476, "close": 17308.4785, "volume": 998512, "vwap_1d": 16985.267, "vwap_3d": 17032.5225, "vwap_5d": 17371.1692, "vwap_10d": 17395.0062, "vwap_20d": 16887.1434, "vwap_40d": 15831.5264, "vwap_60d": null, "vwap_100d": null, "vwap_200d": null}, {"date": "2025-11-11", "open": 17598.3698, "high": 17778.302, "low": 17113.5524, "close": 17413.4395, "volume": 1901382, "vwap_1d": 17435.098, "vwap_3d": 17091.3794, "vwap_5d": 17126.2852, "vwap_10d": 17422.5138, "vwap_20d": 17039.3062, "vwap_40d": 15933.1524, "vwap_60d": null, "vwap_100d": null, "vwap_200d": null}, {"date": "2025-11-12", "open": 17413.4386, "high": 17568.3802, "low": 17098.5573, "close": 17473.416, "volume": 969104, "vwap_1d": 17380.1178, "vwap_3d": 17305.2341, "vwap_5d": 17192.1848, "vwap_10d": 17431.7466, "vwap_20d": 17095.5931, "vwap_40d": 16027.1676, "vwap_60d": null, "vwap_100d": null, "vwap_200d": null}, {"date": "2025-11-13", "open": 17398.4452, "high": 17553.3869, "low": 17203.5187, "close": 17543.3906, "volume": 728966, "vwap_1d": 17433.4321, "vwap_3d": 17419.9579, "vwap_5d": 17178.2122, "vwap_10d": 17431.327, "vwap_20d": 17152.6129, "vwap_40d": 16097.4485, "vwap_60d": null, "vwap_100d": null, "vwap_200d": null}, {"date": "2025-11-14", "open": 16898.6338, "high": 17003.5943, "low": 16633.7336, "close": 16688.7129, "volume": 1163331, "vwap_1d": 16775.3469, "vwap_3d": 17147.8245, "vwap_5d": 17214.459, "vwap_10d": 17370.2245, "vwap_20d": 17173.2446, "vwap_40d": 16156.8126, "vwap_60d": null, "vwap_100d": null, "vwap_200d": null}, {"date": "2025-11-17", "open": 17073.5678, "high": 17673.3418, "low": 17058.5734, "close": 17673.3418, "volume": 1117788, "vwap_1d": 17468.419, "vwap_3d": 17192.0891, "vwap_5d": 17301.6485, "vwap_10d": 17345.3869, "vwap_20d": 17205.1798, "vwap_40d": 16223.2595, "vwap_60d": null, "vwap_100d": null, "vwap_200d": null}, {"date": "2025-11-18", "open": 17193.5213, "high": 17378.4516, "low": 16663.7209, "close": 16788.6738, "volume": 998716, "vwap_1d": 16943.6154, "vwap_3d": 17062.7882, "vwap_5d": 17178.8435, "vwap_10d": 17145.4369, "vwap_20d": 17235.231, "vwap_40d": 16273.2059, "vwap_60d": null, "vwap_100d": null, "vwap_200d": null}, {"date": "2025-11-19", "open": 16693.7102, "high": 16938.618, "low": 16063.9475, "close": 16743.6914, "volume": 1462290, "vwap_1d": 16582.0856, "vwap_3d": 16959.8102, "vwap_5d": 16983.6925, "vwap_10d": 17100.0092, "vwap_20d": 17257.0859, "vwap_40d": 16309.1666, "vwap_60d": null, "vwap_100d": null, "vwap_200d": null}, {"date": "2025-11-20", "open": 17393.4467, "high": 17433.4316, "low": 16858.6482, "close": 17018.5879, "volume": 790262, "vwap_1d": 17103.5559, "vwap_3d": 16819.8894, "vwap_5d": 16941.5549, "vwap_10d": 17065.5998, "vwap_20d": 17275.7305, "vwap_40d": 16359.2062, "vwap_60d": null, "vwap_100d": null, "vwap_200d": null}, {"date": "2025-11-21", "open": 16038.9565, "high": 16193.8982, "low": 15784.0526, "close": 15933.9961, "volume": 1008859, "vwap_1d": 15970.6489, "vwap_3d": 16519.3044, "vwap_5d": 16795.3733, "vwap_10d": 17012.128, "vwap_20d": 17251.1824, "vwap_40d": 16393.5132, "vwap_60d": null, "vwap_100d": null, "vwap_200d": null}, {"date": "2025-11-24", "open": 16043.9549, "high": 16273.8683, "low": 15899.0096, "close": 16053.9512, "volume": 579470, "vwap_1d": 16075.6097, "vwap_3d": 16372.6159, "vwap_5d": 16553.7409, "vwap_10d": 16964.0072, "vwap_20d": 17237.9878, "vwap_40d": 16422.9887, "vwap_60d": null, "vwap_100d": null, "vwap_200d": null}, {"date": "2025-11-25", "open": 16918.6258, "high": 17063.5712, "low": 16603.7445, "close": 16858.6484, "volume": 961881, "vwap_1d": 16841.988, "vwap_3d": 16323.1478, "vwap_5d": 16530.3971, "vwap_10d": 16860.4262, "vwap_20d": 17231.8989, "vwap_40d": 16461.7086, "vwap_60d": null, "vwap_100d": null, "vwap_200d": null}, {"date": "2025-11-26", "open": 17078.5653, "high": 17163.5333, "low": 16633.7329, "close": 17158.5352, "volume": 1305586, "vwap_1d": 16985.2671, "vwap_3d": 16751.705, "vwap_5d": 16641.9515, "vwap_10d": 16826.7562, "vwap_20d": 17216.6121, "vwap_40d": 16505.227, "vwap_60d": 15889.7474, "vwap_100d": null, "vwap_200d": null}, {"date": "2025-11-27", "open": 17263.4961, "high": 17428.434, "low": 17128.5469, "close": 17263.4961, "volume": 842885, "vwap_1d": 17273.4923, "vwap_3d": 17019.065, "vwap_5d": 16677.6058, "vwap_10d": 16820.3347, "vwap_20d": 17198.4782, "vwap_40d": 16562.9269, "vwap_60d": 15916.2983, "vwap_100d": null, "vwap_200d": null}, {"date": "2025-11-28", "open": 17263.4956, "high": 17473.4165, "low": 16993.5973, "close": 17438.4297, "volume": 546322, "vwap_1d": 17301.8145, "vwap_3d": 17139.5934, "vwap_5d": 16926.4733, "vwap_10d": 16853.1386, "vwap_20d": 17178.9939, "vwap_40d": 16679.4494, "vwap_60d": 15934.8665, "vwap_100d": null, "vwap_200d": null}, {"date": "2025-12-01", "open": 17728.3203, "high": 17823.2845, "low": 17318.4747, "close": 17448.4258, "volume": 1071586, "vwap_1d": 17530.0617, "vwap_3d": 17391.5068, "vwap_5d": 17167.5444, "vwap_10d": 16857.0713, "vwap_20d": 17161.6224, "vwap_40d": 16727.1443, "vwap_60d": 15968.8111, "vwap_100d": null, "vwap_200d": null}, {"date": "2025-12-02", "open": 17548.389, "high": 17653.3494, "low": 17243.5038, "close": 17388.4492, "volume": 758357, "vwap_1d": 17428.4342, "vwap_3d": 17445.1526, "vwap_5d": 17280.4778, "vwap_10d": 16894.2586, "vwap_20d": 17043.5221, "vwap_40d": 16754.976, "vwap_60d": 15990.0786, "vwap_100d": null, "vwap_200d": null}, {"date": "2025-12-03", "open": 17588.3731, "high": 17693.3336, "low": 17353.4616, "close": 17583.375, "volume": 1094857, "vwap_1d": 17543.3901, "vwap_3d": 17508.7005, "vwap_5d": 17436.5449, "vwap_10d": 17024.5248, "vwap_20d": 17068.3082, "vwap_40d": 16798.1123, "vwap_60d": 16016.224, "vwap_100d": null, "vwap_200d": null}, {"date": "2025-12-04", "open": 17278.489, "high": 17443.4269, "low": 16843.6529, "close": 17083.5625, "volume": 725422, "vwap_1d": 17123.5474, "vwap_3d": 17391.4723, "vwap_5d": 17415.189, "vwap_10d": 17025.579, "vwap_20d": 17048.2526, "vwap_40d": 16862.3715, "vwap_60d": 16034.0346, "vwap_100d": null, "vwap_200d": null}, {"date": "2025-12-05", "open": 16963.6087, "high": 17153.5371, "low": 16793.6727, "close": 17153.5371, "volume": 574537, "vwap_1d": 17033.5823, "vwap_3d": 17293.9068, "vwap_5d": 17377.9542, "vwap_10d": 17151.91, "vwap_20d": 17072.4686, "vwap_40d": 16903.0708, "vwap_60d": 16057.5524, "vwap_100d": null, "vwap_200d": null}, {"date": "2025-12-08", "open": 17203.5181, "high": 17353.4616, "low": 16993.5972, "close": 17308.4785, "volume": 600684, "vwap_1d": 17218.5124, "vwap_3d": 17126.3652, "vwap_5d": 17309.0197, "vwap_10d": 17230.1559, "vwap_20d": 17081.5716, "vwap_40d": 16949.6506, "vwap_60d": 16092.396, "vwap_100d": null, "vwap_200d": null}, {"date": "2025-12-09", "open": 17333.4699, "high": 17418.4379, "low": 17178.5282, "close": 17393.4473, "volume": 322869, "vwap_1d": 17330.1378, "vwap_3d": 17171.6469, "vwap_5d": 17283.7843, "vwap_10d": 17281.8768, "vwap_20d": 17047.9843, "vwap_40d": 17042.0838, "vwap_60d": 16149.3673, "vwap_100d": null, "vwap_200d": null}, {"date": "2025-12-10", "open": 17398.4441, "high": 17618.3612, "low": 17318.4742, "close": 17348.4629, "volume": 408225, "vwap_1d": 17428.4328, "vwap_3d": 17309.9204, "vwap_5d": 17198.2202, "vwap_10d": 17346.2438, "vwap_20d": 17038.2226, "vwap_40d": 17077.2778, "vwap_60d": 16220.2897, "vwap_100d": null, "vwap_200d": null}, {"date": "2025-12-11", "open": 17488.4102, "high": 17748.3123, "low": 17193.5213, "close": 17203.5176, "volume": 718622, "vwap_1d": 17381.7837, "vwap_3d": 17383.4175, "vwap_5d": 17269.1103, "vwap_10d": 17358.9773, "vwap_20d": 17035.8063, "vwap_40d": 17113.7621, "vwap_60d": 16278.0533, "vwap_100d": null, "vwap_200d": null}, {"date": "2025-12-12", "open": 17208.5163, "high": 17278.49, "low": 16740.6926, "close": 16878.6406, "volume": 858995, "vwap_1d": 16965.9411, "vwap_3d": 17211.4965, "vwap_5d": 17226.1112, "vwap_10d": 17316.0308, "vwap_20d": 17050.3145, "vwap_40d": 17132.2897, "vwap_60d": 16326.6573, "vwap_100d": null, "vwap_200d": null}, {"date": "2025-12-15", "open": 16378.8285, "high": 16543.7664, "low": 16213.8907, "close": 16488.7871, "volume": 589100, "vwap_1d": 16415.4814, "vwap_3d": 16954.1988, "vwap_5d": 17062.8923, "vwap_10d": 17201.7939, "vwap_20d": 16998.4429, "vwap_40d": 17137.3624, "vwap_60d": 16367.3493, "vwap_100d": null, "vwap_200d": null}, {"date": "2025-12-16", "open": 16378.8285, "high": 16383.8266, "low": 15899.0093, "close": 15933.9961, "volume": 497722, "vwap_1d": 16072.2773, "vwap_3d": 16570.6974, "vwap_5d": 16874.3471, "vwap_10d": 17086.9361, "vwap_20d": 16972.5998, "vwap_40d": 17149.222, "vwap_60d": 16400.4496, "vwap_100d": null, "vwap_200d": null}, {"date": "2025-12-17", "open": 16008.9688, "high": 16463.7974, "low": 15819.0403, "close": 16423.8125, "volume": 554975, "vwap_1d": 16235.5501, "vwap_3d": 16250.6147, "vwap_5d": 16693.9702, "vwap_10d": 16920.7723, "vwap_20d": 16983.5375, "vwap_40d": 17169.9789, "vwap_60d": 16425.3082, "vwap_100d": null, "vwap_200d": null}, {"date": "2025-12-18", "open": 16053.9507, "high": 16298.8584, "low": 15864.0223, "close": 15948.9902, "volume": 491716, "vwap_1d": 16037.2903, "vwap_3d": 16119.8091, "vwap_5d": 16420.8955, "vwap_10d": 16817.252, "vwap_20d": 16944.9415, "vwap_40d": 17171.6113, "vwap_60d": 16459.2459, "vwap_100d": null, "vwap_200d": null}, {"date": "2025-12-19", "open": 16263.8722, "high": 16263.8722, "low": 15764.0605, "close": 15909.0059, "volume": 398341, "vwap_1d": 15978.9795, "vwap_3d": 16097.3593, "vwap_5d": 16166.4478, "vwap_10d": 16733.0419, "vwap_20d": 16987.9666, "vwap_40d": 17169.2995, "vwap_60d": 16492.1874, "vwap_100d": null, "vwap_200d": null}, {"date": "2025-12-22", "open": 16373.8305, "high": 16628.7344, "low": 16323.8493, "close": 16623.7363, "volume": 622599, "vwap_1d": 16525.44, "vwap_3d": 16222.8539, "vwap_5d": 16196.3861, "vwap_10d": 16656.0046, "vwap_20d": 17005.228, "vwap_40d": 17163.1475, "vwap_60d": 16520.8565, "vwap_100d": null, "vwap_200d": null}, {"date": "2025-12-23", "open": 16698.7088, "high": 16773.6805, "low": 16468.7954, "close": 16573.7559, "volume": 700581, "vwap_1d": 16605.4106, "vwap_3d": 16431.5395, "vwap_5d": 16322.217, "vwap_10d": 16612.6718, "vwap_20d": 16996.233, "vwap_40d": 17156.0653, "vwap_60d": 16550.7099, "vwap_100d": null, "vwap_200d": null}, {"date": "2025-12-24", "open": 16678.7158, "high": 16678.7158, "low": 16263.8721, "close": 16333.8457, "volume": 429426, "vwap_1d": 16425.4778, "vwap_3d": 16532.9143, "vwap_5d": 16357.1972, "vwap_10d": 16542.1507, "vwap_20d": 16978.2143, "vwap_40d": 17142.607, "vwap_60d": 16579.8059, "vwap_100d": null, "vwap_200d": null}, {"date": "2025-12-26", "open": 16368.8326, "high": 16833.6575, "low": 16333.8458, "close": 16743.6914, "volume": 1039601, "vwap_1d": 16637.0649, "vwap_3d": 16584.9645, "vwap_5d": 16497.6916, "vwap_10d": 16460.5234, "vwap_20d": 16931.804, "vwap_40d": 17111.4541, "vwap_60d": 16622.5736, "vwap_100d": null, "vwap_200d": null}, {"date": "2025-12-29", "open": 16993.5963, "high": 17013.5888, "low": 16688.7112, "close": 16808.666, "volume": 418188, "vwap_1d": 16836.9887, "vwap_3d": 16633.2205, "vwap_5d": 16606.2496, "vwap_10d": 16412.3336, "vwap_20d": 16913.0258, "vwap_40d": 17090.8932, "vwap_60d": 16718.1695, "vwap_100d": null, "vwap_200d": null}, {"date": "2025-12-30", "open": 16748.6897, "high": 16888.637, "low": 16618.7387, "close": 16728.6973, "volume": 466016, "vwap_1d": 16745.3577, "vwap_3d": 16706.7559, "vwap_5d": 16643.9529, "vwap_10d": 16439.6224, "vwap_20d": 16852.7738, "vwap_40d": 17061.0841, "vwap_60d": 16747.122, "vwap_100d": null, "vwap_200d": null}, {"date": "2026-01-02", "open": 16813.6656, "high": 17958.2344, "low": 16738.6938, "close": 17958.2344, "volume": 2076513, "vwap_1d": 17551.7209, "vwap_3d": 17323.8468, "vwap_5d": 17075.5792, "vwap_10d": 16785.8488, "vwap_20d": 16927.4531, "vwap_40d": 17000.401, "vwap_60d": 16784.7871, "vwap_100d": null, "vwap_200d": null}, {"date": "2026-01-05", "open": 18582.9974, "high": 18917.8712, "low": 18258.1198, "close": 18627.9805, "volume": 4052041, "vwap_1d": 18601.3238, "vwap_3d": 18139.6676, "vwap_5d": 17878.0211, "vwap_10d": 17502.2364, "vwap_20d": 17296.6158, "vwap_40d": 17168.0306, "vwap_60d": 16899.0859, "vwap_100d": null, "vwap_200d": null}, {"date": "2026-01-06", "open": 18518.0232, "high": 19092.8066, "low": 18203.1418, "close": 19092.8066, "volume": 2297924, "vwap_1d": 18796.2517, "vwap_3d": 18395.8305, "vwap_5d": 18243.2063, "vwap_10d": 17797.7183, "vwap_20d": 17493.7382, "vwap_40d": 17257.1434, "vwap_60d": 17002.8095, "vwap_100d": null, "vwap_200d": null}, {"date": "2026-01-07", "open": 19322.7191, "high": 19402.689, "low": 18268.1165, "close": 18597.9922, "volume": 2931420, "vwap_1d": 18756.2659, "vwap_3d": 18698.5216, "vwap_5d": 18420.1406, "vwap_10d": 18032.8061, "vwap_20d": 17687.4021, "vwap_40d": 17386.6519, "vwap_60d": 17098.6652, "vwap_100d": null, "vwap_200d": null}, {"date": "2026-01-08", "open": 18403.0658, "high": 19177.7739, "low": 18338.0903, "close": 18443.0508, "volume": 2021707, "vwap_1d": 18652.9717, "vwap_3d": 18740.1377, "vwap_5d": 18513.6555, "vwap_10d": 18166.2098, "vwap_20d": 17789.4159, "vwap_40d": 17458.6956, "vwap_60d": 17174.9241, "vwap_100d": null, "vwap_200d": null}, {"date": "2026-01-09", "open": 18248.1238, "high": 18358.0824, "low": 17818.2858, "close": 18053.1973, "volume": 1926448, "vwap_1d": 18076.5218, "vwap_3d": 18535.5659, "vwap_5d": 18600.9869, "vwap_10d": 18218.3459, "vwap_20d": 17819.2617, "vwap_40d": 17488.7287, "vwap_60d": 17274.5566, "vwap_100d": null, "vwap_200d": null}, {"date": "2026-01-12", "open": 18248.1249, "high": 18298.106, "low": 17703.3301, "close": 17978.2266, "volume": 1312349, "vwap_1d": 17993.2209, "vwap_3d": 18277.2807, "vwap_5d": 18524.8212, "vwap_10d": 18243.9341, "vwap_20d": 17835.154, "vwap_40d": 17507.2331, "vwap_60d": 17314.8503, "vwap_100d": null, "vwap_200d": null}, {"date": "2026-01-13", "open": 18243.1261, "high": 18518.0225, "low": 18143.1638, "close": 18443.0508, "volume": 1193498, "vwap_1d": 18368.079, "vwap_3d": 18130.3659, "vwap_5d": 18438.4321, "vwap_10d": 18341.2094, "vwap_20d": 17873.8148, "vwap_40d": 17533.0182, "vwap_60d": 17362.0862, "vwap_100d": null, "vwap_200d": null}, {"date": "2026-01-14", "open": 18573.002, "high": 18892.8815, "low": 18453.0472, "close": 18707.9512, "volume": 1309659, "vwap_1d": 18684.6266, "vwap_3d": 18347.7999, "vwap_5d": 18359.9546, "vwap_10d": 18396.2855, "vwap_20d": 17946.5253, "vwap_40d": 17589.8088, "vwap_60d": 17405.0956, "vwap_100d": null, "vwap_200d": null}, {"date": "2026-01-15", "open": 18428.0569, "high": 18862.8931, "low": 18373.0776, "close": 18827.9062, "volume": 1077387, "vwap_1d": 18687.959, "vwap_3d": 18580.1149, "vwap_5d": 18324.9061, "vwap_10d": 18449.9321, "vwap_20d": 18012.3996, "vwap_40d": 17621.1812, "vwap_60d": 17437.5369, "vwap_100d": null, "vwap_200d": null}, {"date": "2026-01-16", "open": 19177.7746, "high": 19227.7557, "low": 18677.9629, "close": 18817.9102, "volume": 1347095, "vwap_1d": 18907.8763, "vwap_3d": 18766.1256, "vwap_5d": 18527.4411, "vwap_10d": 18577.4155, "vwap_20d": 18093.8446, "vwap_40d": 17678.0395, "vwap_60d": 17486.6073, "vwap_100d": null, "vwap_200d": null}, {"date": "2026-01-19", "open": 18672.9637, "high": 18814.9102, "low": 18573.0014, "close": 18752.9336, "volume": 1507289, "vwap_1d": 18713.6151, "vwap_3d": 18773.1421, "vwap_5d": 18679.9993, "vwap_10d": 18583.8211, "vwap_20d": 18165.0066, "vwap_40d": 17752.5962, "vwap_60d": 17540.6996, "vwap_100d": null, "vwap_200d": null}, {"date": "2026-01-20", "open": 18657.9709, "high": 18687.9596, "low": 18028.2081, "close": 18368.0801, "volume": 1081382, "vwap_1d": 18361.4159, "vwap_3d": 18683.3354, "vwap_5d": 18684.3907, "vwap_10d": 18537.4344, "vwap_20d": 18209.6238, "vwap_40d": 17780.0124, "vwap_60d": 17565.6257, "vwap_100d": null, "vwap_200d": null}, {"date": "2026-01-21", "open": 17833.2799, "high": 18233.1293, "low": 17678.3383, "close": 18208.1387, "volume": 1787352, "vwap_1d": 18039.8687, "vwap_3d": 18351.3949, "vwap_5d": 18514.9479, "vwap_10d": 18432.3262, "vwap_20d": 18229.3932, "vwap_40d": 17832.6518, "vwap_60d": 17591.6743, "vwap_100d": null, "vwap_200d": null}, {"date": "2026-01-22", "open": 18592.9936, "high": 18602.9898, "low": 18138.165, "close": 18493.0312, "volume": 941895, "vwap_1d": 18411.3953, "vwap_3d": 18222.9499, "vwap_5d": 18472.347, "vwap_10d": 18397.7829, "vwap_20d": 18270.583, "vwap_40d": 17868.2915, "vwap_60d": 17615.2221, "vwap_100d": null, "vwap_200d": null}, {"date": "2026-01-23", "open": 18493.0324, "high": 18742.9382, "low": 18333.0926, "close": 18692.957, "volume": 1019516, "vwap_1d": 18589.6626, "vwap_3d": 18282.7389, "vwap_5d": 18398.643, "vwap_10d": 18462.5431, "vwap_20d": 18319.9235, "vwap_40d": 17907.5129, "vwap_60d": 17639.7137, "vwap_100d": null, "vwap_200d": null}, {"date": "2026-01-26", "open": 18912.874, "high": 19542.6367, "low": 18722.9456, "close": 19542.6367, "volume": 3941814, "vwap_1d": 19269.4063, "vwap_3d": 19015.1104, "vwap_5d": 18735.8121, "vwap_10d": 18712.1944, "vwap_20d": 18454.9259, "vwap_40d": 18048.6821, "vwap_60d": 17733.0729, "vwap_100d": 16633.9289, "vwap_200d": null}, {"date": "2026-01-27", "open": 19547.6344, "high": 20412.3086, "low": 19422.6815, "close": 20412.3086, "volume": 5481541, "vwap_1d": 20082.4329, "vwap_3d": 19629.8081, "vwap_5d": 19326.9412, "vwap_10d": 19118.5421, "vwap_20d": 18738.0053, "vwap_40d": 18279.1998, "vwap_60d": 17907.434, "vwap_100d": 16779.0923, "vwap_200d": null}, {"date": "2026-01-28", "open": 20847.1445, "high": 21986.7151, "low": 20767.1747, "close": 21966.7227, "volume": 6968373, "vwap_1d": 21573.5375, "vwap_3d": 20520.8109, "vwap_5d": 20305.2792, "vwap_10d": 19821.2476, "vwap_20d": 19197.4034, "vwap_40d": 18686.89, "vwap_60d": 18218.0716, "vwap_100d": 17014.1736, "vwap_200d": null}, {"date": "2026-01-29", "open": 23376.1931, "high": 23766.0462, "low": 21082.0574, "close": 22561.5, "volume": 13983320, "vwap_1d": 22469.8679, "vwap_3d": 21738.486, "vwap_5d": 21326.2195, "vwap_10d": 20826.4478, "vwap_20d": 20002.4806, "vwap_40d": 19454.4886, "vwap_60d": 18846.9561, "vwap_100d": 17500.079, "vwap_200d": null}, {"date": "2026-01-30", "open": 22556.5017, "high": 24540.7542, "low": 22386.5658, "close": 23686.0762, "volume": 12898450, "vwap_1d": 23537.7987, "vwap_3d": 22692.2802, "vwap_5d": 22049.8935, "vwap_10d": 21583.473, "vwap_20d": 20736.2505, "vwap_40d": 20110.1702, "vwap_60d": 19442.9458, "vwap_100d": 17956.1877, "vwap_200d": null}, {"date": "2026-02-02", "open": 22826.3994, "high": 23251.2393, "low": 21431.9248, "close": 21641.8457, "volume": 8525949, "vwap_1d": 22108.3366, "vwap_3d": 22771.8431, "vwap_5d": 22289.3213, "vwap_10d": 21738.8805, "vwap_20d": 21012.9049, "vwap_40d": 20330.4411, "vwap_60d": 19705.883, "vwap_100d": 18156.8664, "vwap_200d": null}, {"date": "2026-02-03", "open": 22746.4297, "high": 23166.2715, "low": 22361.5747, "close": 23166.2715, "volume": 5191661, "vwap_1d": 22898.0392, "vwap_3d": 22955.1078, "vwap_5d": 22610.0723, "vwap_10d": 21898.0888, "vwap_20d": 21207.5557, "vwap_40d": 20496.0008, "vwap_60d": 19881.2259, "vwap_100d": 18295.8287, "vwap_200d": null}, {"date": "2026-02-04", "open": 22731.4354, "high": 23486.151, "low": 22486.5277, "close": 23161.2734, "volume": 4141035, "vwap_1d": 23044.6507, "vwap_3d": 22555.021, "vwap_5d": 22811.7371, "vwap_10d": 22082.6393, "vwap_20d": 21398.0484, "vwap_40d": 20623.8202, "vwap_60d": 20032.5955, "vwap_100d": 18412.7514, "vwap_200d": null}, {"date": "2026-02-05", "open": 22356.5759, "high": 22991.3367, "low": 22046.6927, "close": 22236.6211, "volume": 3588009, "vwap_1d": 22424.8835, "vwap_3d": 22813.6349, "vwap_5d": 22910.512, "vwap_10d": 22153.919, "vwap_20d": 21514.6044, "vwap_40d": 20707.9548, "vwap_60d": 20129.2217, "vwap_100d": 18508.9877, "vwap_200d": null}, {"date": "2026-02-06", "open": 21491.902, "high": 22556.5009, "low": 20937.1111, "close": 22351.5781, "volume": 3052752, "vwap_1d": 21948.3967, "vwap_3d": 22528.0093, "vwap_5d": 22460.3735, "vwap_10d": 22198.279, "vwap_20d": 21613.5156, "vwap_40d": 20754.92, "vwap_60d": 20217.109, "vwap_100d": 18605.6463, "vwap_200d": null}, {"date": "2026-02-09", "open": 23381.1896, "high": 23381.1896, "low": 22691.4495, "close": 23231.2461, "volume": 2831932, "vwap_1d": 23101.2951, "vwap_3d": 22473.545, "vwap_5d": 22716.4966, "vwap_10d": 22409.8258, "vwap_20d": 21723.0111, "vwap_40d": 20830.2227, "vwap_60d": 20305.6238, "vwap_100d": 18724.9286, "vwap_200d": null}, {"date": "2026-02-10", "open": 23211.2544, "high": 23241.2431, "low": 22236.6216, "close": 22341.582, "volume": 2546626, "vwap_1d": 22606.4822, "vwap_3d": 22534.4062, "vwap_5d": 22640.8378, "vwap_10d": 22617.8739, "vwap_20d": 21798.1582, "vwap_40d": 20894.9909, "vwap_60d": 20369.1704, "vwap_100d": 18815.4109, "vwap_200d": null}, {"date": "2026-02-11", "open": 22156.6508, "high": 22276.6056, "low": 21746.8052, "close": 21986.7148, "volume": 1886445, "vwap_1d": 22003.3752, "vwap_3d": 22642.7586, "vwap_5d": 22434.1075, "vwap_10d": 22722.1963, "vwap_20d": 21851.4375, "vwap_40d": 20945.0776, "vwap_60d": 20426.8743, "vwap_100d": 18881.9929, "vwap_200d": null}, {"date": "2026-02-12", "open": 22386.5642, "high": 22836.3947, "low": 22211.6301, "close": 22826.3984, "volume": 2074137, "vwap_1d": 22624.8077, "vwap_3d": 22437.4822, "vwap_5d": 22468.6974, "vwap_10d": 22793.3688, "vwap_20d": 21910.548, "vwap_40d": 21000.6975, "vwap_60d": 20488.8902, "vwap_100d": 18957.4704, "vwap_200d": null}, {"date": "2026-02-13", "open": 22446.5424, "high": 22596.4859, "low": 22101.6724, "close": 22346.5801, "volume": 2080627, "vwap_1d": 22348.2461, "vwap_3d": 22335.5081, "vwap_5d": 22585.8395, "vwap_10d": 22500.2628, "vwap_20d": 21968.4875, "vwap_40d": 21047.5499, "vwap_60d": 20546.8137, "vwap_100d": 19025.8696, "vwap_200d": null}, {"date": "2026-02-19", "open": 22721.4383, "high": 23276.2292, "low": 22346.5795, "close": 23226.248, "volume": 2580601, "vwap_1d": 22949.6856, "vwap_3d": 22663.8492, "vwap_5d": 22539.2086, "vwap_10d": 22650.438, "vwap_20d": 22054.3746, "vwap_40d": 21113.9041, "vwap_60d": 20639.8, "vwap_100d": 19100.0472, "vwap_200d": null}, {"date": "2026-02-20", "open": 23191.2622, "high": 23221.2509, "low": 22791.4129, "close": 23156.2754, "volume": 1874828, "vwap_1d": 23056.3131, "vwap_3d": 22788.8144, "vwap_5d": 22615.2483, "vwap_10d": 22630.7615, "vwap_20d": 22121.5619, "vwap_40d": 21166.9975, "vwap_60d": 20696.0955, "vwap_100d": 19172.628, "vwap_200d": null}, {"date": "2026-02-23", "open": 23246.2419, "high": 23251.24, "low": 22571.4961, "close": 22851.3906, "volume": 1629545, "vwap_1d": 22891.3756, "vwap_3d": 22966.923, "vwap_5d": 22771.9151, "vwap_10d": 22577.3666, "vwap_20d": 22219.5669, "vwap_40d": 21208.7354, "vwap_60d": 20759.9217, "vwap_100d": 19239.4362, "vwap_200d": null}, {"date": "2026-02-24", "open": 22791.4129, "high": 23356.2001, "low": 22441.5447, "close": 23296.2227, "volume": 1740461, "vwap_1d": 23031.3225, "vwap_3d": 22996.7748, "vwap_5d": 22848.2935, "vwap_10d": 22637.3363, "vwap_20d": 22276.3577, "vwap_40d": 21260.3478, "vwap_60d": 20810.4726, "vwap_100d": 19303.3105, "vwap_200d": null}, {"date": "2026-02-25", "open": 23511.1421, "high": 23726.0611, "low": 23156.2758, "close": 23266.2344, "volume": 2622264, "vwap_1d": 23382.8571, "vwap_3d": 23147.0994, "vwap_5d": 23082.0463, "vwap_10d": 22822.914, "vwap_20d": 22350.6566, "vwap_40d": 21333.9811, "vwap_60d": 20889.5576, "vwap_100d": 19388.4982, "vwap_200d": null}, {"date": "2026-02-26", "open": 24185.8866, "high": 25940.2256, "low": 23841.0166, "close": 25730.3047, "volume": 7875414, "vwap_1d": 25170.5156, "vwap_3d": 24483.2465, "vwap_5d": 24148.5299, "vwap_10d": 23480.6381, "vwap_20d": 22717.7809, "vwap_40d": 21587.8403, "vwap_60d": 21166.5252, "vwap_100d": 19637.2665, "vwap_200d": null}, {"date": "2026-02-27", "open": 24790.6585, "high": 27399.6754, "low": 24690.6962, "close": 27004.8242, "volume": 7762841, "vwap_1d": 26365.0653, "vwap_3d": 25421.6249, "vwap_5d": 25038.6761, "vwap_10d": 24246.8899, "vwap_20d": 23163.8602, "vwap_40d": 21902.8932, "vwap_60d": 21463.2716, "vwap_100d": 19922.8187, "vwap_200d": null}, {"date": "2026-03-03", "open": 26564.9917, "high": 28224.3665, "low": 25465.406, "close": 25625.3457, "volume": 7899806, "vwap_1d": 26438.3727, "vwap_3d": 25989.9937, "vwap_5d": 25560.3982, "vwap_10d": 24811.763, "vwap_20d": 23545.6273, "vwap_40d": 22171.0233, "vwap_60d": 21732.5376, "vwap_100d": 20238.7781, "vwap_200d": null}, {"date": "2026-03-04", "open": 25040.5642, "high": 26420.0443, "low": 22676.455, "close": 22821.4004, "volume": 10460350, "vwap_1d": 23972.6332, "vwap_3d": 25429.24, "vwap_5d": 25227.0668, "vwap_10d": 24720.5994, "vwap_20d": 23754.8117, "vwap_40d": 22312.0846, "vwap_60d": 21903.0912, "vwap_100d": 20434.3234, "vwap_200d": null}, {"date": "2026-03-05", "open": 25570.3653, "high": 28239.3597, "low": 25245.4877, "close": 27659.5781, "volume": 8123321, "vwap_1d": 27048.1418, "vwap_3d": 25651.4992, "vwap_5d": 25693.0776, "vwap_10d": 25174.1588, "vwap_20d": 24088.7746, "vwap_40d": 22618.9816, "vwap_60d": 22167.1061, "vwap_100d": 20676.9383, "vwap_200d": null}, {"date": "2026-03-06", "open": 27749.5435, "high": 28549.2422, "low": 26445.0351, "close": 28549.2422, "volume": 9278468, "vwap_1d": 27847.8398, "vwap_3d": 26159.8064, "vwap_5d": 26246.9754, "vwap_10d": 25689.5887, "vwap_20d": 24668.8152, "vwap_40d": 23016.9994, "vwap_60d": 22489.2333, "vwap_100d": 20972.8545, "vwap_200d": null}, {"date": "2026-03-09", "open": 26535.0011, "high": 27044.809, "low": 25390.4324, "close": 26315.084, "volume": 6366807, "vwap_1d": 26250.1085, "vwap_3d": 27146.551, "vwap_5d": 26225.6891, "vwap_10d": 25822.9914, "vwap_20d": 24881.8417, "vwap_40d": 23198.4853, "vwap_60d": 22639.7181, "vwap_100d": 21166.13, "vwap_200d": null}, {"date": "2026-03-10", "open": 27989.4547, "high": 28069.4246, "low": 26350.0724, "close": 27179.7598, "volume": 5553073, "vwap_1d": 27199.7522, "vwap_3d": 27198.1984, "vwap_5d": 26319.422, "vwap_10d": 26006.5307, "vwap_20d": 25104.8601, "vwap_40d": 23406.416, "vwap_60d": 22789.9756, "vwap_100d": 21347.8957, "vwap_200d": null}, {"date": "2026-03-11", "open": 27504.6373, "high": 27504.6373, "low": 25660.3321, "close": 26210.125, "volume": 4228372, "vwap_1d": 26458.3648, "vwap_3d": 26631.204, "vwap_5d": 27068.6233, "vwap_10d": 26107.5523, "vwap_20d": 25270.7422, "vwap_40d": 23537.5505, "vwap_60d": 22887.388, "vwap_100d": 21487.3575, "vwap_200d": null}, {"date": "2026-03-12", "open": 25760.293, "high": 26315.084, "low": 25470.4023, "close": 26315.084, "volume": 2589128, "vwap_1d": 26033.5234, "vwap_3d": 26702.2508, "vwap_5d": 26978.9017, "vwap_10d": 26206.6889, "vwap_20d": 25402.4441, "vwap_40d": 23636.0841, "vwap_60d": 22938.1397, "vwap_100d": 21644.275, "vwap_200d": null}, {"date": "2026-03-13", "open": 25315.4613, "high": 25910.2372, "low": 25155.5216, "close": 25845.2617, "volume": 2371811, "vwap_1d": 25637.0069, "vwap_3d": 26126.667, "vwap_5d": 26446.1889, "vwap_10d": 26312.0377, "vwap_20d": 25479.7071, "vwap_40d": 23706.1543, "vwap_60d": 22981.8686, "vwap_100d": 21725.8906, "vwap_200d": null}, {"date": "2026-03-16", "open": 25760.2946, "high": 26085.1722, "low": 25025.5714, "close": 25925.2324, "volume": 2089686, "vwap_1d": 25678.6587, "vwap_3d": 25794.9604, "vwap_5d": 26425.069, "vwap_10d": 26282.6079, "vwap_20d": 25564.6005, "vwap_40d": 23766.3507, "vwap_60d": 23030.3639, "vwap_100d": 21819.2319, "vwap_200d": null}, {"date": "2026-03-17", "open": 26589.9818, "high": 26609.9743, "low": 25655.334, "close": 25655.334, "volume": 1662326, "vwap_1d": 25973.5474, "vwap_3d": 25742.5748, "vwap_5d": 26034.657, "vwap_10d": 26249.5244, "vwap_20d": 25646.0175, "vwap_40d": 23825.4609, "vwap_60d": 23080.8747, "vwap_100d": 21885.9671, "vwap_200d": null}, {"date": "2026-03-18", "open": 26335.0766, "high": 27044.8092, "low": 26320.0822, "close": 27004.8242, "volume": 2637934, "vwap_1d": 26789.9052, "vwap_3d": 26214.1243, "vwap_5d": 26052.3385, "vwap_10d": 26811.7081, "vwap_20d": 25747.5612, "vwap_40d": 23901.2455, "vwap_60d": 23148.7356, "vwap_100d": 21966.8547, "vwap_200d": null}, {"date": "2026-03-19", "open": 26165.1419, "high": 27484.6448, "low": 26145.1494, "close": 27189.7559, "volume": 2909956, "vwap_1d": 26939.85, "vwap_3d": 26662.2086, "vwap_5d": 26277.7839, "vwap_10d": 26772.71, "vwap_20d": 25861.8313, "vwap_40d": 23988.8151, "vwap_60d": 23219.9205, "vwap_100d": 22065.7368, "vwap_200d": null}, {"date": "2026-03-20", "open": 27449.6583, "high": 27534.6263, "low": 27129.7788, "close": 27444.6602, "volume": 2626779, "vwap_1d": 27369.6884, "vwap_3d": 27029.584, "vwap_5d": 26645.6979, "vwap_10d": 26518.2161, "vwap_20d": 25986.1595, "vwap_40d": 24082.8981, "vwap_60d": 23291.4691, "vwap_100d": 22166.239, "vwap_200d": null}, {"date": "2026-03-23", "open": 26475.0245, "high": 26939.8494, "low": 25795.2806, "close": 25980.2109, "volume": 2642412, "vwap_1d": 26238.447, "vwap_3d": 26851.2949, "vwap_5d": 26721.3973, "vwap_10d": 26551.2313, "vwap_20d": 26052.3415, "vwap_40d": 24148.7434, "vwap_60d": 23345.8791, "vwap_100d": 22228.5517, "vwap_200d": null}, {"date": "2026-03-24", "open": 27069.7996, "high": 27329.7017, "low": 25820.2704, "close": 26455.0312, "volume": 2169756, "vwap_1d": 26535.0011, "vwap_3d": 26724.399, "vwap_5d": 26785.9809, "vwap_10d": 26410.9784, "vwap_20d": 26118.5537, "vwap_40d": 24237.7471, "vwap_60d": 23392.7037, "vwap_100d": 22302.6337, "vwap_200d": null}, {"date": "2026-03-25", "open": 27029.8148, "high": 27404.6735, "low": 26859.8788, "close": 27144.7715, "volume": 2090681, "vwap_1d": 27136.4413, "vwap_3d": 26603.6396, "vwap_5d": 26844.0495, "vwap_10d": 26466.3091, "vwap_20d": 26198.3876, "vwap_40d": 24301.1983, "vwap_60d": 23449.8135, "vwap_100d": 22381.7668, "vwap_200d": null}, {"date": "2026-03-26", "open": 26679.9465, "high": 26919.8561, "low": 25445.4117, "close": 25615.3477, "volume": 2132509, "vwap_1d": 25993.5385, "vwap_3d": 26551.0728, "vwap_5d": 26664.6228, "vwap_10d": 26471.124, "vwap_20d": 26272.7014, "vwap_40d": 24352.7075, "vwap_60d": 23497.7143, "vwap_100d": 22443.7546, "vwap_200d": null}, {"date": "2026-03-27", "open": 24750.6735, "high": 25600.3534, "low": 24225.8713, "close": 25330.4551, "volume": 2355397, "vwap_1d": 25052.2266, "vwap_3d": 26019.7268, "vwap_5d": 26168.6167, "vwap_10d": 26412.6399, "vwap_20d": 26338.7091, "vwap_40d": 24472.1678, "vwap_60d": 23528.8304, "vwap_100d": 22501.7213, "vwap_200d": null}, {"date": "2026-03-30", "open": 23965.9705, "high": 24175.8914, "low": 23526.1362, "close": 23980.9648, "volume": 2034589, "vwap_1d": 23894.3308, "vwap_3d": 24998.7983, "vwap_5d": 25722.3784, "vwap_10d": 26258.3161, "vwap_20d": 26275.7353, "vwap_40d": 24600.6889, "vwap_60d": 23565.3974, "vwap_100d": 22561.2034, "vwap_200d": null}, {"date": "2026-03-31", "open": 23191.2614, "high": 23890.9977, "low": 22701.4459, "close": 22936.3574, "volume": 2041355, "vwap_1d": 23176.267, "vwap_3d": 24090.4767, "vwap_5d": 25069.0685, "vwap_10d": 26012.2145, "vwap_20d": 26176.0568, "vwap_40d": 24705.7217, "vwap_60d": 23574.6652, "vwap_100d": 22593.0612, "vwap_200d": null}, {"date": "2026-04-01", "open": 24400.8063, "high": 25260.4824, "low": 24125.9099, "close": 25260.4824, "volume": 1594805, "vwap_1d": 24882.2916, "vwap_3d": 23913.6901, "vwap_5d": 24614.2751, "vwap_10d": 25841.6922, "vwap_20d": 26486.9537, "vwap_40d": 24901.9502, "vwap_60d": 23598.7175, "vwap_100d": 22638.7544, "vwap_200d": null}, {"date": "2026-04-02", "open": 25400.4289, "high": 25545.3742, "low": 23256.2368, "close": 23641.0918, "volume": 2244535, "vwap_1d": 24147.5676, "vwap_3d": 24009.654, "vwap_5d": 24225.9042, "vwap_10d": 25522.6218, "vwap_20d": 26327.7605, "vwap_40d": 25007.8879, "vwap_60d": 23661.6247, "vwap_100d": 22708.997, "vwap_200d": null}, {"date": "2026-04-03", "open": 24185.8869, "high": 24310.8399, "low": 23366.1958, "close": 23890.998, "volume": 1823305, "vwap_1d": 23856.0112, "vwap_3d": 24260.6147, "vwap_5d": 23956.7949, "vwap_10d": 25149.1802, "vwap_20d": 25984.168, "vwap_40d": 25165.6299, "vwap_60d": 23757.7664, "vwap_100d": 22778.2269, "vwap_200d": null}, {"date": "2026-04-06", "open": 23995.9589, "high": 24545.7517, "low": 23536.1321, "close": 23726.0605, "volume": 1230970, "vwap_1d": 23935.9815, "vwap_3d": 23998.0902, "vwap_5d": 23968.1512, "vwap_10d": 24927.4679, "vwap_20d": 25898.2104, "vwap_40d": 25239.199, "vwap_60d": 23811.5917, "vwap_100d": 22816.5736, "vwap_200d": null}, {"date": "2026-04-07", "open": 24485.7732, "high": 24550.7487, "low": 23691.0727, "close": 24080.9258, "volume": 1677415, "vwap_1d": 24107.5824, "vwap_3d": 23965.9995, "vwap_5d": 24184.0413, "vwap_10d": 24674.5107, "vwap_20d": 25671.6248, "vwap_40d": 25291.6841, "vwap_60d": 23882.9475, "vwap_100d": 22860.8523, "vwap_200d": null}, {"date": "2026-04-08", "open": 25735.3036, "high": 26290.0946, "low": 25245.4882, "close": 26230.1172, "volume": 2196534, "vwap_1d": 25921.9, "vwap_3d": 24846.8644, "vwap_5d": 24478.7937, "vwap_10d": 24549.9891, "vwap_20d": 25607.2285, "vwap_40d": 25377.755, "vwap_60d": 23953.0177, "vwap_100d": 22910.0507, "vwap_200d": null}, {"date": "2026-04-09", "open": 25890.2444, "high": 26220.1201, "low": 25360.444, "close": 25735.3027, "volume": 1499360, "vwap_1d": 25771.9556, "vwap_3d": 25313.6744, "vwap_5d": 24797.0775, "vwap_10d": 24483.3405, "vwap_20d": 25586.8453, "vwap_40d": 25460.2696, "vwap_60d": 24018.544, "vwap_100d": 22967.5863, "vwap_200d": null}, {"date": "2026-04-10", "open": 26415.048, "high": 26649.9595, "low": 26100.1666, "close": 26195.1309, "volume": 1650553, "vwap_1d": 26315.0857, "vwap_3d": 26001.2336, "vwap_5d": 25308.4633, "vwap_10d": 24576.8991, "vwap_20d": 25613.0618, "vwap_40d": 25521.1731, "vwap_60d": 24073.0223, "vwap_100d": 23010.2888, "vwap_200d": null}, {"date": "2026-04-13", "open": 25560.3697, "high": 26310.0873, "low": 25450.4112, "close": 26075.1758, "volume": 990927, "vwap_1d": 25945.2247, "vwap_3d": 26029.9134, "vwap_5d": 25597.9866, "vwap_10d": 24738.8281, "vwap_20d": 25617.8383, "vwap_40d": 25580.9052, "vwap_60d": 24113.4098, "vwap_100d": 23037.4813, "vwap_200d": null}, {"date": "2026-04-14", "open": 26654.9577, "high": 26689.9445, "low": 26230.1177, "close": 26330.0801, "volume": 1492469, "vwap_1d": 26416.7141, "vwap_3d": 26263.1189, "vwap_5d": 26073.3412, "vwap_10d": 25086.0007, "vwap_20d": 25632.8473, "vwap_40d": 25641.9889, "vwap_60d": 24162.535, "vwap_100d": 23085.4918, "vwap_200d": null}, {"date": "2026-04-15", "open": 27009.8228, "high": 27149.7701, "low": 26639.9622, "close": 27109.7852, "volume": 1679384, "vwap_1d": 26966.5058, "vwap_3d": 26526.2803, "vwap_5d": 26323.9482, "vwap_10d": 25297.2759, "vwap_20d": 25612.0581, "vwap_40d": 25706.9826, "vwap_60d": 24211.8001, "vwap_100d": 23135.2164, "vwap_200d": null}, {"date": "2026-04-16", "open": 27109.786, "high": 27469.6504, "low": 26599.9781, "close": 27469.6504, "volume": 1945267, "vwap_1d": 27179.7596, "vwap_3d": 26887.2207, "vwap_5d": 26645.194, "vwap_10d": 25682.9439, "vwap_20d": 25590.6982, "vwap_40d": 25782.5581, "vwap_60d": 24271.6334, "vwap_100d": 23189.6175, "vwap_200d": null}, {"date": "2026-04-17", "open": 27469.6507, "high": 27469.6507, "low": 26974.8371, "close": 27309.7109, "volume": 1046932, "vwap_1d": 27251.3996, "vwap_3d": 27119.1521, "vwap_5d": 26810.0466, "vwap_10d": 26005.6683, "vwap_20d": 25510.3906, "vwap_40d": 25851.2334, "vwap_60d": 24324.9979, "vwap_100d": 23243.5756, "vwap_200d": null}, {"date": "2026-04-20", "open": 27299.7132, "high": 28104.4099, "low": 27144.7715, "close": 27979.457, "volume": 2441278, "vwap_1d": 27742.8795, "vwap_3d": 27446.5748, "vwap_5d": 27174.272, "vwap_10d": 26414.1334, "vwap_20d": 25607.4322, "vwap_40d": 25927.4108, "vwap_60d": 24393.2291, "vwap_100d": 23304.5952, "vwap_200d": null}, {"date": "2026-04-21", "open": 28184.3814, "high": 28704.1855, "low": 28144.3965, "close": 28704.1855, "volume": 2447793, "vwap_1d": 28517.5892, "vwap_3d": 27975.6595, "vwap_5d": 27636.4574, "vwap_10d": 26932.6848, "vwap_20d": 25747.012, "vwap_40d": 26014.087, "vwap_60d": 24491.871, "vwap_100d": 23381.8435, "vwap_200d": null}, {"date": "2026-04-22", "open": 28784.1549, "high": 29718.8027, "low": 28309.3338, "close": 29718.8027, "volume": 3538648, "vwap_1d": 29248.9798, "vwap_3d": 28600.2749, "vwap_5d": 28234.6451, "vwap_10d": 27488.7619, "vwap_20d": 25996.2599, "vwap_40d": 26140.1124, "vwap_60d": 24594.3913, "vwap_100d": 23476.5499, "vwap_200d": null}, {"date": "2026-04-23", "open": 29763.7858, "high": 29763.7858, "low": 28399.2999, "close": 29298.9609, "volume": 4231273, "vwap_1d": 29154.0155, "vwap_3d": 29034.4394, "vwap_5d": 28668.1906, "vwap_10d": 27936.9551, "vwap_20d": 26329.0837, "vwap_40d": 26289.6467, "vwap_60d": 24708.2194, "vwap_100d": 23590.3415, "vwap_200d": null}, {"date": "2026-04-24", "open": 29343.9431, "high": 30198.6211, "low": 29119.0279, "close": 30198.6211, "volume": 2941029, "vwap_1d": 29838.7567, "vwap_3d": 29373.4068, "vwap_5d": 28983.9564, "vwap_10d": 28300.402, "vwap_20d": 26656.202, "vwap_40d": 26439.2324, "vwap_60d": 24872.5566, "vwap_100d": 23690.7774, "vwap_200d": null}, {"date": "2026-04-27", "open": 30393.5488, "high": 31788.0234, "low": 30108.6562, "close": 31788.0234, "volume": 3765977, "vwap_1d": 31228.2343, "vwap_3d": 30052.2651, "vwap_5d": 29662.3553, "vwap_10d": 28823.7053, "vwap_20d": 27193.809, "vwap_40d": 26588.4752, "vwap_60d": 25100.1273, "vwap_100d": 23815.136, "vwap_200d": null}, {"date": "2026-04-28", "open": 31768.0301, "high": 31942.9642, "low": 31088.2863, "close": 31848.0, "volume": 2972888, "vwap_1d": 31626.4168, "vwap_3d": 30928.361, "vwap_5d": 30157.5517, "vwap_10d": 29265.1825, "vwap_20d": 27686.2811, "vwap_40d": 26723.4188, "vwap_60d": 25303.1932, "vwap_100d": 23912.8105, "vwap_200d": null}, {"date": "2026-04-29", "open": 31125.0, "high": 31335.0, "low": 30585.0, "close": 31335.0, "volume": 3875589, "vwap_1d": 31085.0, "vwap_3d": 31287.4587, "vwap_5d": 30540.3942, "vwap_10d": 29638.8377, "vwap_20d": 28072.4276, "vwap_40d": 27126.9647, "vwap_60d": 25603.6325, "vwap_100d": 24037.8577, "vwap_200d": null}, {"date": "2026-04-30", "open": 31470.0, "high": 31870.0, "low": 30935.0, "close": 31200.0, "volume": 3095525, "vwap_1d": 31335.0, "vwap_3d": 31324.6875, "vwap_5d": 31040.4161, "vwap_10d": 29969.3743, "vwap_20d": 28478.693, "vwap_40d": 27253.314, "vwap_60d": 25829.3492, "vwap_100d": 24136.6714, "vwap_200d": null}, {"date": "2026-05-04", "open": 31755.0, "high": 31800.0, "low": 31330.0, "close": 31800.0, "volume": 2240207, "vwap_1d": 31643.3333, "vwap_3d": 31304.8016, "vwap_5d": 31346.6679, "vwap_10d": 30178.4236, "vwap_20d": 28809.1445, "vwap_40d": 27296.0161, "vwap_60d": 26064.4206, "vwap_100d": 24222.3684, "vwap_200d": null}, {"date": "2026-05-06", "open": 32615.0, "high": 32880.0, "low": 31810.0, "close": 32880.0, "volume": 3556858, "vwap_1d": 32523.3333, "vwap_3d": 31887.9844, "vwap_5d": 31640.8824, "vwap_10d": 30615.7727, "vwap_20d": 29198.9022, "vwap_40d": 27552.8624, "vwap_60d": 26273.2474, "vwap_100d": 24344.7659, "vwap_200d": null}, {"date": "2026-05-07", "open": 33180.0, "high": 33205.0, "low": 31590.0, "close": 32740.0, "volume": 2610930, "vwap_1d": 32511.6667, "vwap_3d": 32285.2453, "vwap_5d": 31791.5128, "vwap_10d": 30923.0007, "vwap_20d": 29541.1931, "vwap_40d": 27709.1741, "vwap_60d": 26431.6747, "vwap_100d": 24434.2178, "vwap_200d": null}, {"date": "2026-05-08", "open": 32025.0, "high": 32660.0, "low": 31830.0, "close": 32660.0, "volume": 2334464, "vwap_1d": 32383.3333, "vwap_3d": 32481.3108, "vwap_5d": 32089.225, "vwap_10d": 31218.1135, "vwap_20d": 29830.8187, "vwap_40d": 27882.4805, "vwap_60d": 26583.7083, "vwap_100d": 24513.9594, "vwap_200d": null}, {"date": "2026-05-11", "open": 33040.0, "high": 33650.0, "low": 32865.0, "close": 33450.0, "volume": 4258623, "vwap_1d": 33321.6667, "vwap_3d": 32853.8971, "vwap_5d": 32594.737, "vwap_10d": 31777.0656, "vwap_20d": 30225.2697, "vwap_40d": 28176.2377, "vwap_60d": 26812.637, "vwap_100d": 24650.8238, "vwap_200d": null}, {"date": "2026-05-12", "open": 33430.0, "high": 33975.0, "low": 30090.0, "close": 31395.0, "volume": 5063415, "vwap_1d": 31820.0, "vwap_3d": 32481.4432, "vwap_5d": 32494.2296, "vwap_10d": 31952.2872, "vwap_20d": 30482.2816, "vwap_40d": 28426.3642, "vwap_60d": 27002.0109, "vwap_100d": 24783.5741, "vwap_200d": null}, {"date": "2026-05-13", "open": 30705.0, "high": 33100.0, "low": 30570.0, "close": 33100.0, "volume": 3117066, "vwap_1d": 32256.6667, "vwap_3d": 32443.5297, "vwap_5d": 32445.6796, "vwap_10d": 32063.2449, "vwap_20d": 30653.2246, "vwap_40d": 28605.2006, "vwap_60d": 27147.1652, "vwap_100d": 24879.5729, "vwap_200d": null}, {"date": "2026-05-14", "open": 32810.0, "high": 33230.0, "low": 31850.0, "close": 33230.0, "volume": 1883339, "vwap_1d": 32770.0, "vwap_3d": 32133.0313, "vwap_5d": 32472.0061, "vwap_10d": 32145.3306, "vwap_20d": 30827.8237, "vwap_40d": 28728.5082, "vwap_60d": 27253.9981, "vwap_100d": 24951.9882, "vwap_200d": null}, {"date": "2026-05-15", "open": 33280.0, "high": 33300.0, "low": 29940.0, "close": 30550.0, "volume": 2463196, "vwap_1d": 31263.3333, "vwap_3d": 32058.3718, "vwap_5d": 32306.9725, "vwap_10d": 32208.5783, "vwap_20d": 30954.1373, "vwap_40d": 28843.332, "vwap_60d": 27356.3264, "vwap_100d": 25020.3534, "vwap_200d": null}, {"date": "2026-05-18", "open": 29700.0, "high": 30680.0, "low": 28145.0, "close": 30110.0, "volume": 3561093, "vwap_1d": 29645.0, "vwap_3d": 30893.3777, "vwap_5d": 31449.1506, "vwap_10d": 32001.9162, "vwap_20d": 30997.7562, "vwap_40d": 28927.6372, "vwap_60d": 27453.1355, "vwap_100d": 25089.1728, "vwap_200d": null}, {"date": "2026-05-19", "open": 29895.0, "high": 29965.0, "low": 27990.0, "close": 28490.0, "volume": 2645770, "vwap_1d": 28815.0, "vwap_3d": 29851.4903, "vwap_5d": 30801.9801, "vwap_10d": 31759.6998, "vwap_20d": 30968.3663, "vwap_40d": 28965.7395, "vwap_60d": 27532.4779, "vwap_100d": 25137.4273, "vwap_200d": null}, {"date": "2026-05-20", "open": 28795.0, "high": 29440.0, "low": 27900.0, "close": 28340.0, "volume": 3129340, "vwap_1d": 28560.0, "vwap_3d": 29046.1138, "vwap_5d": 29957.8309, "vwap_10d": 31349.9728, "vwap_20d": 30973.6651, "vwap_40d": 29025.0666, "vwap_60d": 27592.5763, "vwap_100d": 25186.6101, "vwap_200d": null}, {"date": "2026-05-21", "open": 29300.0, "high": 31350.0, "low": 29245.0, "close": 31285.0, "volume": 1749197, "vwap_1d": 30626.6667, "vwap_3d": 29130.1094, "vwap_5d": 29653.2723, "vwap_10d": 31207.6707, "vwap_20d": 31059.4119, "vwap_40d": 29107.3979, "vwap_60d": 27659.6773, "vwap_100d": 25229.1239, "vwap_200d": null}, {"date": "2026-05-22", "open": 31310.0, "high": 32250.0, "low": 31010.0, "close": 32005.0, "volume": 1516616, "vwap_1d": 31755.0, "vwap_3d": 29882.97, "vwap_5d": 29591.5058, "vwap_10d": 31142.5259, "vwap_20d": 31181.7054, "vwap_40d": 29189.5167, "vwap_60d": 27733.5826, "vwap_100d": 25278.3731, "vwap_200d": null}, {"date": "2026-05-26", "open": 33015.0, "high": 33730.0, "low": 32900.0, "close": 33130.0, "volume": 3131409, "vwap_1d": 33253.3333, "vwap_3d": 32179.9059, "vwap_5d": 30517.8839, "vwap_10d": 31048.0356, "vwap_20d": 31433.1858, "vwap_40d": 29384.7789, "vwap_60d": 27881.8328, "vwap_100d": 25377.437, "vwap_200d": null}, {"date": "2026-05-27", "open": 34255.0, "high": 34455.0, "low": 31000.0, "close": 31450.0, "volume": 3613984, "vwap_1d": 32301.6667, "vwap_3d": 32562.0118, "vwap_5d": 31351.3349, "vwap_10d": 31071.2285, "vwap_20d": 31562.3906, "vwap_40d": 29589.5126, "vwap_60d": 28079.0269, "vwap_100d": 25468.6167, "vwap_200d": null}, {"date": "2026-05-28", "open": 31160.0, "high": 31160.0, "low": 28600.0, "close": 29735.0, "volume": 2922585, "vwap_1d": 29831.6667, "vwap_3d": 31863.2371, "vwap_5d": 31683.3085, "vwap_10d": 30796.2936, "vwap_20d": 31498.7878, "vwap_40d": 29709.7908, "vwap_60d": 28178.9345, "vwap_100d": 25537.4809, "vwap_200d": null}, {"date": "2026-05-29", "open": 30135.0, "high": 30300.0, "low": 28330.0, "close": 28900.0, "volume": 3224995, "vwap_1d": 29176.6667, "vwap_3d": 30529.7278, "vwap_5d": 31250.5666, "vwap_10d": 30476.5144, "vwap_20d": 31367.6376, "vwap_40d": 29822.1438, "vwap_60d": 28273.3204, "vwap_100d": 25585.3331, "vwap_200d": null}, {"date": "2026-06-01", "open": 29200.0, "high": 29620.0, "low": 28580.0, "close": 28855.0, "volume": 2477911, "vwap_1d": 29018.3333, "vwap_3d": 29353.1154, "vwap_5d": 30840.941, "vwap_10d": 30278.0604, "vwap_20d": 31286.9847, "vwap_40d": 29878.5864, "vwap_60d": 28545.9402, "vwap_100d": 25624.3861, "vwap_200d": null}, {"date": "2026-06-02", "open": 28855.0, "high": 28970.0, "low": 27500.0, "close": 27950.0, "volume": 2498014, "vwap_1d": 28140.0, "vwap_3d": 28813.0558, "vwap_5d": 29870.5467, "vwap_10d": 30163.3619, "vwap_20d": 31148.8815, "vwap_40d": 29960.0891, "vwap_60d": 28613.0616, "vwap_100d": 25695.5779, "vwap_200d": null}, {"date": "2026-06-04", "open": 28580.0, "high": 31935.0, "low": 28580.0, "close": 31085.0, "volume": 7048273, "vwap_1d": 30533.3333, "vwap_3d": 29723.9142, "vwap_5d": 29644.1227, "vwap_10d": 30360.5722, "vwap_20d": 31062.168, "vwap_40d": 30098.2906, "vwap_60d": 28738.9348, "vwap_100d": 25887.9216, "vwap_200d": null}, {"date": "2026-06-05", "open": 29000.0, "high": 30455.0, "low": 28575.0, "close": 29440.0, "volume": 3272681, "vwap_1d": 29490.0, "vwap_3d": 29800.585, "vwap_5d": 29587.2975, "vwap_10d": 30449.1254, "vwap_20d": 30896.7508, "vwap_40d": 30148.3303, "vwap_60d": 28852.7378, "vwap_100d": 25973.623, "vwap_200d": null}, {"date": "2026-06-08", "open": 26640.0, "high": 27860.0, "low": 25685.0, "close": 25900.0, "volume": 3553607, "vwap_1d": 26481.6667, "vwap_3d": 29249.5069, "vwap_5d": 29072.0902, "vwap_10d": 30015.8929, "vwap_20d": 30583.1019, "vwap_40d": 30122.8472, "vwap_60d": 28857.4803, "vwap_100d": 26043.5613, "vwap_200d": null}, {"date": "2026-06-09", "open": 27295.0, "high": 28950.0, "low": 27150.0, "close": 28615.0, "volume": 2878477, "vwap_1d": 28238.3333, "vwap_3d": 28017.1845, "vwap_5d": 28954.3436, "vwap_10d": 29791.9244, "vwap_20d": 30412.0035, "vwap_40d": 30156.0998, "vwap_60d": 28910.5771, "vwap_100d": 26108.1434, "vwap_200d": null}, {"date": "2026-06-10", "open": 27820.0, "high": 30415.0, "low": 27320.0, "close": 28150.0, "volume": 3856366, "vwap_1d": 28628.3333, "vwap_3d": 27777.7664, "vwap_5d": 28992.0462, "vwap_10d": 29358.3271, "vwap_20d": 30109.0567, "vwap_40d": 30161.9408, "vwap_60d": 28950.6425, "vwap_100d": 26184.2243, "vwap_200d": null}, {"date": "2026-06-11", "open": 27610.0, "high": 31520.0, "low": 26980.0, "close": 31520.0, "volume": 7079726, "vwap_1d": 30006.6667, "vwap_3d": 29253.4427, "vwap_5d": 28813.7504, "vwap_10d": 29202.5243, "vwap_20d": 29965.9968, "vwap_40d": 30204.9208, "vwap_60d": 29044.4594, "vwap_100d": 26296.4644, "vwap_200d": null}, {"date": "2026-06-12", "open": 33405.0, "high": 35185.0, "low": 31885.0, "close": 34200.0, "volume": 11917160, "vwap_1d": 33756.6667, "vwap_3d": 31729.5721, "vwap_5d": 30749.6126, "vwap_10d": 30299.2986, "vwap_20d": 30477.0414, "vwap_40d": 30554.6953, "vwap_60d": 29409.1029, "vwap_100d": 26579.4513, "vwap_200d": null}, {"date": "2026-06-15", "open": 34900.0, "high": 35110.0, "low": 33610.0, "close": 33885.0, "volume": 5210377, "vwap_1d": 34201.6667, "vwap_3d": 32755.7127, "vwap_5d": 31821.0686, "vwap_10d": 30780.36, "vwap_20d": 30671.101, "vwap_40d": 30738.748, "vwap_60d": 29582.6053, "vwap_100d": 26721.8515, "vwap_200d": null}, {"date": "2026-06-16", "open": 34295.0, "high": 34305.0, "low": 32100.0, "close": 32460.0, "volume": 4061110, "vwap_1d": 32955.0, "vwap_3d": 33712.443, "vwap_5d": 32285.441, "vwap_10d": 31037.2436, "vwap_20d": 30769.6077, "vwap_40d": 30848.9334, "vwap_60d": 29700.7602, "vwap_100d": 26817.6777, "vwap_200d": null}, {"date": "2026-06-17", "open": 32000.0, "high": 33530.0, "low": 31830.0, "close": 32375.0, "volume": 3900994, "vwap_1d": 32578.3333, "vwap_3d": 33336.5704, "vwap_5d": 32759.3613, "vwap_10d": 31288.2751, "vwap_20d": 30908.4063, "vwap_40d": 30947.3068, "vwap_60d": 29808.2031, "vwap_100d": 26910.4613, "vwap_200d": null}, {"date": "2026-06-18", "open": 32390.0, "high": 32725.0, "low": 31200.0, "close": 31785.0, "volume": 3681718, "vwap_1d": 31903.3333, "vwap_3d": 32496.2748, "vwap_5d": 33327.1715, "vwap_10d": 31441.7899, "vwap_20d": 31022.3953, "vwap_40d": 30998.7028, "vwap_60d": 29886.5083, "vwap_100d": 26996.0294, "vwap_200d": null}, {"date": "2026-06-19", "open": 33000.0, "high": 33005.0, "low": 29070.0, "close": 29900.0, "volume": 5358171, "vwap_1d": 30658.3333, "vwap_3d": 31591.3182, "vwap_5d": 32452.9534, "vwap_10d": 31484.3101, "vwap_20d": 31091.7712, "vwap_40d": 31040.4559, "vwap_60d": 29961.7729, "vwap_100d": 27075.7025, "vwap_200d": null}, {"date": "2026-06-22", "open": 29350.0, "high": 31710.0, "low": 29305.0, "close": 31365.0, "volume": 4758272, "vwap_1d": 30793.3333, "vwap_3d": 31037.0871, "vwap_5d": 31671.3279, "vwap_10d": 31759.2422, "vwap_20d": 31084.7159, "vwap_40d": 31074.0108, "vwap_60d": 30023.1482, "vwap_100d": 27168.044, "vwap_200d": null}, {"date": "2026-06-23", "open": 31150.0, "high": 31150.0, "low": 27935.0, "close": 28080.0, "volume": 3968249, "vwap_1d": 29055.0, "vwap_3d": 30252.2145, "vwap_5d": 30951.5659, "vwap_10d": 31748.1579, "vwap_20d": 30982.1194, "vwap_40d": 31063.6124, "vwap_60d": 30034.8465, "vwap_100d": 27210.6318, "vwap_200d": null}, {"date": "2026-06-24", "open": 28085.0, "high": 28890.0, "low": 27110.0, "close": 28100.0, "volume": 3116844, "vwap_1d": 28033.3333, "vwap_3d": 29484.5306, "vwap_5d": 30212.1368, "vwap_10d": 31756.6901, "vwap_20d": 30797.6952, "vwap_40d": 31054.4097, "vwap_60d": 30047.4727, "vwap_100d": 27241.1858, "vwap_200d": null}, {"date": "2026-06-25", "open": 29465.0, "high": 29580.0, "low": 27765.0, "close": 28170.0, "volume": 2187169, "vwap_1d": 28505.0, "vwap_3d": 28581.8341, "vwap_5d": 29698.4199, "vwap_10d": 31866.2765, "vwap_20d": 30677.5444, "vwap_40d": 31040.8508, "vwap_60d": 30092.0391, "vwap_100d": 27333.6263, "vwap_200d": 24471.3403}], "volume_profile": {"3d": {"buckets": [{"price": 27211.0, "volume": 139886.0}, {"price": 27413.0, "volume": 289033.92}, {"price": 27615.0, "volume": 507269.79}, {"price": 27817.0, "volume": 756977.1}, {"price": 28019.0, "volume": 969180.7}, {"price": 28221.0, "volume": 1080717.12}, {"price": 28423.0, "volume": 1069982.17}, {"price": 28625.0, "volume": 962025.98}, {"price": 28827.0, "volume": 806311.39}, {"price": 29029.0, "volume": 649177.14}, {"price": 29231.0, "volume": 516680.39}, {"price": 29433.0, "volume": 412692.64}, {"price": 29635.0, "volume": 328807.46}, {"price": 29837.0, "volume": 256271.79}, {"price": 30039.0, "volume": 191660.49}, {"price": 30241.0, "volume": 135849.81}, {"price": 30443.0, "volume": 90710.68}, {"price": 30645.0, "volume": 56923.86}, {"price": 30847.0, "volume": 33544.7}, {"price": 31049.0, "volume": 18558.86}], "vwap": 28591.8051}, "5d": {"buckets": [{"price": 27257.375, "volume": 245792.87}, {"price": 27552.125, "volume": 635848.65}, {"price": 27846.875, "volume": 1165697.39}, {"price": 28141.625, "volume": 1556521.2}, {"price": 28436.375, "volume": 1602751.13}, {"price": 28731.125, "volume": 1382869.11}, {"price": 29025.875, "volume": 1123132.47}, {"price": 29320.625, "volume": 981976.8}, {"price": 29615.375, "volume": 993422.26}, {"price": 29910.125, "volume": 1137040.3}, {"price": 30204.875, "volume": 1368057.91}, {"price": 30499.625, "volume": 1579938.71}, {"price": 30794.375, "volume": 1626728.44}, {"price": 31089.125, "volume": 1435271.59}, {"price": 31383.875, "volume": 1075455.12}, {"price": 31678.625, "volume": 694866.63}, {"price": 31973.375, "volume": 400771.03}, {"price": 32268.125, "volume": 215477.44}, {"price": 32562.875, "volume": 111437.87}, {"price": 32857.625, "volume": 55648.09}], "vwap": 29699.0337}, "10d": {"buckets": [{"price": 27311.875, "volume": 411440.97}, {"price": 27715.625, "volume": 1269342.82}, {"price": 28119.375, "volume": 2104829.89}, {"price": 28523.125, "volume": 2129652.96}, {"price": 28926.875, "volume": 1644659.38}, {"price": 29330.625, "volume": 1339101.71}, {"price": 29734.375, "volume": 1415770.26}, {"price": 30138.125, "volume": 1791396.24}, {"price": 30541.875, "volume": 2188008.85}, {"price": 30945.625, "volume": 2201745.42}, {"price": 31349.375, "volume": 2145662.87}, {"price": 31753.125, "volume": 2732712.7}, {"price": 32156.875, "volume": 3309845.62}, {"price": 32560.625, "volume": 3747780.77}, {"price": 32964.375, "volume": 3793892.18}, {"price": 33368.125, "volume": 3539331.7}, {"price": 33771.875, "volume": 4017877.04}, {"price": 34175.625, "volume": 4475027.42}, {"price": 34579.375, "volume": 2841746.01}, {"price": 34983.125, "volume": 1060239.18}], "vwap": 31849.982}, "20d": {"buckets": [{"price": 25922.5, "volume": 784988.27}, {"price": 26397.5, "volume": 1336965.72}, {"price": 26872.5, "volume": 1206333.06}, {"price": 27347.5, "volume": 1530017.08}, {"price": 27822.5, "volume": 4307475.91}, {"price": 28297.5, "volume": 6656498.58}, {"price": 28772.5, "volume": 7480664.09}, {"price": 29247.5, "volume": 8024160.87}, {"price": 29722.5, "volume": 6886908.13}, {"price": 30197.5, "volume": 6245479.2}, {"price": 30672.5, "volume": 5665953.63}, {"price": 31147.5, "volume": 4536116.35}, {"price": 31622.5, "volume": 4065291.31}, {"price": 32097.5, "volume": 4313657.22}, {"price": 32572.5, "volume": 4595484.3}, {"price": 33047.5, "volume": 4441297.57}, {"price": 33522.5, "volume": 4246526.08}, {"price": 33997.5, "volume": 5253348.85}, {"price": 34472.5, "volume": 4022476.52}, {"price": 34947.5, "volume": 1373056.25}], "vwap": 30670.3202}, "40d": {"buckets": [{"price": 25922.5, "volume": 784988.36}, {"price": 26397.5, "volume": 1336974.57}, {"price": 26872.5, "volume": 1206956.37}, {"price": 27347.5, "volume": 1554612.08}, {"price": 27822.5, "volume": 4705426.82}, {"price": 28297.5, "volume": 8577185.75}, {"price": 28772.5, "volume": 10243239.12}, {"price": 29247.5, "volume": 9986138.23}, {"price": 29722.5, "volume": 8502919.77}, {"price": 30197.5, "volume": 8067929.26}, {"price": 30672.5, "volume": 8764154.92}, {"price": 31147.5, "volume": 14185607.82}, {"price": 31622.5, "volume": 14899987.97}, {"price": 32097.5, "volume": 10675145.39}, {"price": 32572.5, "volume": 13149179.72}, {"price": 33047.5, "volume": 11032038.83}, {"price": 33522.5, "volume": 8924896.86}, {"price": 33997.5, "volume": 5492466.02}, {"price": 34472.5, "volume": 4082322.68}, {"price": 34947.5, "volume": 1386014.48}], "vwap": 31037.3914}, "60d": {"buckets": [{"price": 23013.5348, "volume": 1655009.86}, {"price": 23637.7125, "volume": 4970340.46}, {"price": 24261.8902, "volume": 4060719.79}, {"price": 24886.0679, "volume": 1807762.69}, {"price": 25510.2456, "volume": 2284486.86}, {"price": 26134.4233, "volume": 7064045.79}, {"price": 26758.601, "volume": 3933369.56}, {"price": 27382.7787, "volume": 5727161.44}, {"price": 28006.9564, "volume": 10023715.24}, {"price": 28631.1341, "volume": 16819859.06}, {"price": 29255.3118, "volume": 18834946.25}, {"price": 29879.4895, "volume": 14272632.98}, {"price": 30503.6672, "volume": 10967557.2}, {"price": 31127.8449, "volume": 17785750.32}, {"price": 31752.0226, "volume": 17488324.47}, {"price": 32376.2003, "volume": 17080576.0}, {"price": 33000.378, "volume": 14703845.01}, {"price": 33624.5557, "volume": 9771426.34}, {"price": 34248.7334, "volume": 6834060.29}, {"price": 34872.9111, "volume": 2221016.4}], "vwap": 30087.2097}, "100d": {"buckets": [{"price": 19816.7395, "volume": 4603302.6}, {"price": 20604.8554, "volume": 1104307.16}, {"price": 21392.9713, "volume": 10473380.55}, {"price": 22181.0872, "volume": 24235685.8}, {"price": 22969.2032, "volume": 38527090.58}, {"price": 23757.3191, "volume": 20830996.88}, {"price": 24545.435, "volume": 10176866.53}, {"price": 25333.5509, "volume": 15799872.7}, {"price": 26121.6669, "volume": 35696515.62}, {"price": 26909.7828, "volume": 31339992.77}, {"price": 27697.8987, "volume": 22540094.78}, {"price": 28486.0146, "volume": 22157196.03}, {"price": 29274.1306, "volume": 23755730.89}, {"price": 30062.2465, "volume": 16323366.0}, {"price": 30850.3624, "volume": 18644009.67}, {"price": 31638.4783, "volume": 22432553.38}, {"price": 32426.5943, "volume": 20956348.47}, {"price": 33214.7102, "volume": 17681227.22}, {"price": 34002.8261, "volume": 9087862.92}, {"price": 34790.942, "volume": 3465588.45}], "vwap": 27321.1598}, "200d": {"buckets": [{"price": 12497.2473, "volume": 4175809.0}, {"price": 13660.7218, "volume": 8500867.48}, {"price": 14824.1963, "volume": 17543575.67}, {"price": 15987.6708, "volume": 26067629.19}, {"price": 17151.1453, "volume": 45634907.89}, {"price": 18314.6198, "volume": 27754154.03}, {"price": 19478.0943, "volume": 7550145.78}, {"price": 20641.5688, "volume": 3717792.11}, {"price": 21805.0433, "volume": 28178699.53}, {"price": 22968.5178, "volume": 50430486.86}, {"price": 24131.9923, "volume": 21572290.98}, {"price": 25295.4668, "volume": 24113361.04}, {"price": 26458.9413, "volume": 51800693.55}, {"price": 27622.4158, "volume": 36412106.57}, {"price": 28785.8903, "volume": 35821287.17}, {"price": 29949.3648, "volume": 24528896.2}, {"price": 31112.8393, "volume": 32766227.4}, {"price": 32276.3138, "volume": 29444185.26}, {"price": 33439.7883, "volume": 20412298.14}, {"price": 34603.2628, "volume": 8472207.15}], "vwap": 24462.2686}}, "strategy_signal": {"available": true, "strategy": "VWAP 5/20", "rules": {"buy": "VWAP5 > VWAP20", "sell": "VWAP5 < VWAP20", "execution": "next_day_vwap_1d_proxy", "valuation": "vwap_1d_proxy", "buy_hold_return": "last_vwap_1d_proxy / first_vwap_1d_proxy - 1", "fee_one_way_pct": 0.03}, "latest": {"date": "2026-06-25", "vwap5": 29698.4199, "vwap20": 30677.5444, "vwap200": 24471.3403, "vwap_5_20_return_pct": -3.19, "vwap_5_200_return_pct": 21.36, "vwap_5_20_momentum_pct": -3.19, "alignment": "5 < 20", "in_position": false, "action": "매도", "last_signal": "SELL", "last_signal_date": "2026-06-23", "holding_days": null, "entry_date": null, "entry_price": null, "current_trade_return_pct": null}, "backtest": {"period": "recent_200_trading_days", "start_date": "2025-08-28", "end_date": "2026-06-25", "strategy_return_pct": 15.76, "buy_hold_return_pct": 130.49, "max_drawdown_pct": -30.23, "trades": 6, "win_rate_pct": 50.0, "exposure_pct": 66.0, "avg_holding_days": 23.0, "max_holding_days": 57, "rolling_200d": {"window_days": 200, "strategy_return_pct": 15.76, "buy_hold_return_pct": 130.49, "strategy_mdd_pct": -30.23, "buy_hold_mdd_pct": -20.53}}, "signals": [{"date": "2025-09-24", "execution_date": "2025-09-25", "type": "BUY", "price": 14746.1102, "vwap_5_20_return_pct": 6.63, "vwap_5_200_return_pct": null}, {"date": "2025-11-18", "execution_date": "2025-11-19", "type": "SELL", "price": 16582.0856, "vwap_5_20_return_pct": -0.33, "vwap_5_200_return_pct": null}, {"date": "2025-12-01", "execution_date": "2025-12-02", "type": "BUY", "price": 17428.4342, "vwap_5_20_return_pct": 0.03, "vwap_5_200_return_pct": null}, {"date": "2025-12-16", "execution_date": "2025-12-17", "type": "SELL", "price": 16235.5501, "vwap_5_20_return_pct": -0.58, "vwap_5_200_return_pct": null}, {"date": "2026-01-02", "execution_date": "2026-01-05", "type": "BUY", "price": 18601.3238, "vwap_5_20_return_pct": 0.88, "vwap_5_200_return_pct": null}, {"date": "2026-03-27", "execution_date": "2026-03-30", "type": "SELL", "price": 23894.3308, "vwap_5_20_return_pct": -0.65, "vwap_5_200_return_pct": null}, {"date": "2026-04-14", "execution_date": "2026-04-15", "type": "BUY", "price": 26966.5058, "vwap_5_20_return_pct": 1.72, "vwap_5_200_return_pct": null}, {"date": "2026-05-19", "execution_date": "2026-05-20", "type": "SELL", "price": 28560.0, "vwap_5_20_return_pct": -0.54, "vwap_5_200_return_pct": null}, {"date": "2026-05-28", "execution_date": "2026-05-29", "type": "BUY", "price": 29176.6667, "vwap_5_20_return_pct": 0.59, "vwap_5_200_return_pct": null}, {"date": "2026-05-29", "execution_date": "2026-06-01", "type": "SELL", "price": 29018.3333, "vwap_5_20_return_pct": -0.37, "vwap_5_200_return_pct": null}, {"date": "2026-06-12", "execution_date": "2026-06-15", "type": "BUY", "price": 34201.6667, "vwap_5_20_return_pct": 0.89, "vwap_5_200_return_pct": null}, {"date": "2026-06-23", "execution_date": "2026-06-24", "type": "SELL", "price": 28033.3333, "vwap_5_20_return_pct": -0.1, "vwap_5_200_return_pct": null}]}, "lookback_trading_days": 200, "latest_price": 28170.0, "_meta": {"updated_at": "2026-06-26 08:19"}}