{"name": "팔란티어", "ticker": "PLTR", "ohlcv": [{"date": "2025-07-08", "open": 138.775, "high": 139.855, "low": 135.79, "close": 139.71, "volume": 59834800, "vwap_10d": null}, {"date": "2025-07-09", "open": 139.655, "high": 143.17, "low": 137.39, "close": 143.13, "volume": 68494800, "vwap_10d": null}, {"date": "2025-07-10", "open": 143.31, "high": 145.16, "low": 139.53, "close": 142.5, "volume": 64383900, "vwap_10d": null}, {"date": "2025-07-11", "open": 142.11, "high": 144.58, "low": 141.47, "close": 142.1, "volume": 52134800, "vwap_10d": null}, {"date": "2025-07-14", "open": 142.72, "high": 149.575, "low": 142.22, "close": 149.15, "volume": 81774400, "vwap_10d": null}, {"date": "2025-07-15", "open": 148.93, "high": 150.62, "low": 147.36, "close": 148.58, "volume": 59126200, "vwap_10d": null}, {"date": "2025-07-16", "open": 149.3, "high": 151.51, "low": 147.674, "close": 150.91, "volume": 57550300, "vwap_10d": null}, {"date": "2025-07-17", "open": 151.56, "high": 155.68, "low": 150.82, "close": 153.99, "volume": 60165500, "vwap_10d": null}, {"date": "2025-07-18", "open": 154.86, "high": 154.92, "low": 151.9, "close": 153.52, "volume": 45771600, "vwap_10d": null}, {"date": "2025-07-21", "open": 153.88, "high": 155.44, "low": 151.36, "close": 151.79, "volume": 45072800, "vwap_10d": 146.6652}, {"date": "2025-07-22", "open": 150.85, "high": 151.79, "low": 145.062, "close": 149.07, "volume": 49880800, "vwap_10d": 147.6754}, {"date": "2025-07-23", "open": 149.74, "high": 155.0, "low": 148.287, "close": 154.63, "volume": 48062000, "vwap_10d": 148.8759}, {"date": "2025-07-24", "open": 153.98, "high": 155.63, "low": 152.575, "close": 154.86, "volume": 38925700, "vwap_10d": 150.0429}, {"date": "2025-07-25", "open": 155.63, "high": 160.39, "low": 155.58, "close": 158.8, "volume": 57972300, "vwap_10d": 151.6313}, {"date": "2025-07-28", "open": 159.88, "high": 160.28, "low": 153.04, "close": 157.88, "volume": 63886900, "vwap_10d": 152.9993}, {"date": "2025-07-29", "open": 158.715, "high": 160.14, "low": 154.91, "close": 156.24, "volume": 42427200, "vwap_10d": 153.8196}, {"date": "2025-07-30", "open": 157.365, "high": 159.38, "low": 156.56, "close": 158.61, "volume": 40261700, "vwap_10d": 154.619}, {"date": "2025-07-31", "open": 159.99, "high": 160.89, "low": 156.73, "close": 158.35, "volume": 45342600, "vwap_10d": 155.1563}, {"date": "2025-08-01", "open": 155.05, "high": 158.19, "low": 151.058, "close": 154.27, "volume": 61287000, "vwap_10d": 155.2341}, {"date": "2025-08-04", "open": 158.53, "high": 161.4, "low": 157.93, "close": 160.66, "volume": 82993600, "vwap_10d": 156.1755}, {"date": "2025-08-05", "open": 171.81, "high": 176.33, "low": 169.22, "close": 173.27, "volume": 130917500, "vwap_10d": 160.3688}, {"date": "2025-08-06", "open": 171.175, "high": 180.581, "low": 171.01, "close": 179.54, "volume": 82924800, "vwap_10d": 163.0653}, {"date": "2025-08-07", "open": 181.01, "high": 184.48, "low": 178.17, "close": 182.2, "volume": 77829200, "vwap_10d": 165.7019}, {"date": "2025-08-08", "open": 184.735, "high": 187.99, "low": 184.41, "close": 186.96, "volume": 62657900, "vwap_10d": 168.1983}, {"date": "2025-08-11", "open": 186.47, "high": 187.18, "low": 181.92, "close": 182.68, "volume": 56125600, "vwap_10d": 170.5324}, {"date": "2025-08-12", "open": 184.7, "high": 190.0, "low": 182.1, "close": 186.97, "volume": 54819000, "vwap_10d": 172.5939}, {"date": "2025-08-13", "open": 189.0, "high": 189.46, "low": 183.59, "close": 184.37, "volume": 53610000, "vwap_10d": 174.4228}, {"date": "2025-08-14", "open": 182.41, "high": 185.33, "low": 179.2, "close": 181.02, "volume": 53472900, "vwap_10d": 175.9754}, {"date": "2025-08-15", "open": 179.725, "high": 180.0, "low": 173.38, "close": 177.17, "volume": 60288700, "vwap_10d": 177.8806}, {"date": "2025-08-18", "open": 175.27, "high": 177.9, "low": 171.39, "close": 174.03, "volume": 62656600, "vwap_10d": 179.7178}, {"date": "2025-08-19", "open": 171.36, "high": 172.3, "low": 156.9, "close": 157.75, "volume": 137922700, "vwap_10d": 177.6689}, {"date": "2025-08-20", "open": 152.3, "high": 156.46, "low": 142.34, "close": 156.01, "volume": 220336400, "vwap_10d": 170.8025}, {"date": "2025-08-21", "open": 157.17, "high": 157.97, "low": 153.81, "close": 156.18, "volume": 94678600, "vwap_10d": 168.1678}, {"date": "2025-08-22", "open": 155.315, "high": 163.2, "low": 151.77, "close": 158.74, "volume": 102099200, "vwap_10d": 165.7207}, {"date": "2025-08-25", "open": 156.1, "high": 158.59, "low": 149.37, "close": 157.17, "volume": 86879800, "vwap_10d": 163.6168}, {"date": "2025-08-26", "open": 155.39, "high": 162.13, "low": 154.57, "close": 160.87, "volume": 86573700, "vwap_10d": 161.9235}, {"date": "2025-08-27", "open": 162.32, "high": 162.4, "low": 155.98, "close": 156.72, "volume": 76380600, "vwap_10d": 160.3577}, {"date": "2025-08-28", "open": 157.63, "high": 158.23, "low": 152.55, "close": 158.12, "volume": 57885200, "vwap_10d": 158.9465}, {"date": "2025-08-29", "open": 156.98, "high": 158.42, "low": 153.0, "close": 156.71, "volume": 45270500, "vwap_10d": 157.6989}, {"date": "2025-09-02", "open": 151.2, "high": 158.39, "low": 150.28, "close": 157.09, "volume": 65435000, "vwap_10d": 156.4543}, {"date": "2025-09-03", "open": 158.0, "high": 161.15, "low": 152.71, "close": 154.9, "volume": 66052300, "vwap_10d": 155.5175}, {"date": "2025-09-04", "open": 154.865, "high": 157.04, "low": 153.16, "close": 156.14, "volume": 53292300, "vwap_10d": 156.6829}, {"date": "2025-09-05", "open": 157.82, "high": 158.97, "low": 148.04, "close": 153.11, "volume": 81855900, "vwap_10d": 156.4105}, {"date": "2025-09-08", "open": 154.91, "high": 158.3, "low": 154.84, "close": 156.1, "volume": 47643000, "vwap_10d": 156.1962}, {"date": "2025-09-09", "open": 157.25, "high": 162.75, "low": 156.37, "close": 162.36, "volume": 61359500, "vwap_10d": 156.7482}, {"date": "2025-09-10", "open": 166.0, "high": 169.0, "low": 163.44, "close": 166.74, "volume": 62211400, "vwap_10d": 157.4144}, {"date": "2025-09-11", "open": 167.24, "high": 167.458, "low": 163.22, "close": 164.36, "volume": 42025500, "vwap_10d": 157.8373}, {"date": "2025-09-12", "open": 165.35, "high": 171.53, "low": 164.01, "close": 171.43, "volume": 54498500, "vwap_10d": 159.0187}, {"date": "2025-09-15", "open": 169.6, "high": 171.8, "low": 167.41, "close": 171.21, "volume": 45396100, "vwap_10d": 160.1174}, {"date": "2025-09-16", "open": 171.04, "high": 171.31, "low": 168.96, "close": 170.26, "volume": 34598700, "vwap_10d": 161.3297}, {"date": "2025-09-17", "open": 169.02, "high": 169.68, "low": 161.27, "close": 168.33, "volume": 69255500, "vwap_10d": 162.5725}, {"date": "2025-09-18", "open": 170.27, "high": 178.8, "low": 169.39, "close": 176.97, "volume": 70768600, "vwap_10d": 164.8022}, {"date": "2025-09-19", "open": 177.07, "high": 184.42, "low": 176.71, "close": 182.39, "volume": 109129900, "vwap_10d": 169.3425}, {"date": "2025-09-22", "open": 180.88, "high": 182.25, "low": 178.29, "close": 179.33, "volume": 45916700, "vwap_10d": 171.1841}, {"date": "2025-09-23", "open": 182.51, "high": 185.75, "low": 177.01, "close": 182.55, "volume": 62354800, "vwap_10d": 173.4102}, {"date": "2025-09-24", "open": 183.91, "high": 184.85, "low": 177.12, "close": 179.56, "volume": 45379700, "vwap_10d": 174.7185}, {"date": "2025-09-25", "open": 175.8, "high": 184.32, "low": 174.29, "close": 179.12, "volume": 72321200, "vwap_10d": 175.9205}, {"date": "2025-09-26", "open": 179.05, "high": 180.12, "low": 174.91, "close": 177.57, "volume": 44275800, "vwap_10d": 176.6697}, {"date": "2025-09-29", "open": 179.64, "high": 181.48, "low": 177.16, "close": 178.86, "volume": 38413800, "vwap_10d": 177.332}, {"date": "2025-09-30", "open": 178.98, "high": 182.77, "low": 178.22, "close": 182.42, "volume": 43561700, "vwap_10d": 178.0171}, {"date": "2025-10-01", "open": 181.32, "high": 186.28, "low": 179.5, "close": 184.95, "volume": 45717300, "vwap_10d": 179.8453}, {"date": "2025-10-02", "open": 186.7, "high": 188.2, "low": 182.95, "close": 187.05, "volume": 39849200, "vwap_10d": 180.9561}, {"date": "2025-10-03", "open": 186.4, "high": 186.84, "low": 170.77, "close": 173.07, "volume": 105533400, "vwap_10d": 180.2}, {"date": "2025-10-06", "open": 179.18, "high": 182.95, "low": 177.83, "close": 179.53, "volume": 52504200, "vwap_10d": 180.2111}, {"date": "2025-10-07", "open": 180.31, "high": 186.18, "low": 179.42, "close": 182.17, "volume": 58179300, "vwap_10d": 180.2876}, {"date": "2025-10-08", "open": 182.8, "high": 184.26, "low": 181.2, "close": 183.56, "volume": 36299700, "vwap_10d": 180.4527}, {"date": "2025-10-09", "open": 183.58, "high": 187.62, "low": 179.95, "close": 185.47, "volume": 45050300, "vwap_10d": 180.9596}, {"date": "2025-10-10", "open": 185.17, "high": 187.1, "low": 173.53, "close": 175.44, "volume": 55194000, "vwap_10d": 181.017}, {"date": "2025-10-13", "open": 178.68, "high": 179.22, "low": 173.45, "close": 177.21, "volume": 41332400, "vwap_10d": 180.8061}, {"date": "2025-10-14", "open": 176.0, "high": 182.34, "low": 170.82, "close": 179.74, "volume": 49261400, "vwap_10d": 180.4894}, {"date": "2025-10-15", "open": 181.655, "high": 184.35, "low": 176.02, "close": 179.62, "volume": 37372100, "vwap_10d": 180.1843}, {"date": "2025-10-16", "open": 181.78, "high": 184.82, "low": 176.45, "close": 178.12, "volume": 42870900, "vwap_10d": 179.7032}, {"date": "2025-10-17", "open": 177.75, "high": 181.59, "low": 173.95, "close": 178.15, "volume": 43421500, "vwap_10d": 180.0648}, {"date": "2025-10-20", "open": 179.49, "high": 183.09, "low": 177.44, "close": 181.59, "volume": 31975800, "vwap_10d": 180.1068}, {"date": "2025-10-21", "open": 182.06, "high": 182.389, "low": 178.65, "close": 181.51, "volume": 27528100, "vwap_10d": 179.8055}, {"date": "2025-10-22", "open": 181.93, "high": 182.21, "low": 169.42, "close": 175.49, "volume": 58263100, "vwap_10d": 178.996}, {"date": "2025-10-23", "open": 175.445, "high": 181.56, "low": 175.01, "close": 180.48, "volume": 35812300, "vwap_10d": 178.4441}, {"date": "2025-10-24", "open": 182.88, "high": 186.17, "low": 182.85, "close": 184.63, "volume": 34813500, "vwap_10d": 178.9357}, {"date": "2025-10-27", "open": 188.97, "high": 192.83, "low": 187.52, "close": 189.18, "volume": 47153100, "vwap_10d": 180.4319}, {"date": "2025-10-28", "open": 189.48, "high": 191.78, "low": 186.78, "close": 189.6, "volume": 38201000, "vwap_10d": 181.6365}, {"date": "2025-10-29", "open": 191.08, "high": 199.85, "low": 190.49, "close": 198.81, "volume": 65537300, "vwap_10d": 184.0053}, {"date": "2025-10-30", "open": 198.425, "high": 199.67, "low": 194.12, "close": 194.55, "volume": 43541700, "vwap_10d": 185.6644}, {"date": "2025-10-31", "open": 199.2, "high": 204.18, "low": 197.92, "close": 200.47, "volume": 52697600, "vwap_10d": 188.3156}, {"date": "2025-11-03", "open": 205.045, "high": 207.52, "low": 201.82, "close": 207.18, "volume": 81016800, "vwap_10d": 191.6658}, {"date": "2025-11-04", "open": 192.07, "high": 195.7, "low": 185.56, "close": 190.74, "volume": 121380900, "vwap_10d": 191.9709}, {"date": "2025-11-05", "open": 189.0, "high": 190.32, "low": 181.21, "close": 187.9, "volume": 76121000, "vwap_10d": 192.8425}, {"date": "2025-11-06", "open": 187.99, "high": 191.09, "low": 174.53, "close": 175.05, "volume": 78468600, "vwap_10d": 192.1538}, {"date": "2025-11-07", "open": 173.15, "high": 178.7, "low": 168.91, "close": 177.93, "volume": 73989700, "vwap_10d": 190.6195}, {"date": "2025-11-10", "open": 184.31, "high": 194.93, "low": 183.52, "close": 193.61, "volume": 87764200, "vwap_10d": 190.6787}, {"date": "2025-11-11", "open": 190.335, "high": 192.925, "low": 187.13, "close": 190.96, "volume": 49819700, "vwap_10d": 190.7231}, {"date": "2025-11-12", "open": 190.58, "high": 190.58, "low": 180.4, "close": 184.17, "volume": 55347100, "vwap_10d": 189.772}, {"date": "2025-11-13", "open": 181.715, "high": 182.7, "low": 170.731, "close": 172.14, "volume": 63188800, "vwap_10d": 188.1641}, {"date": "2025-11-14", "open": 166.975, "high": 177.29, "low": 164.5, "close": 174.01, "volume": 62596800, "vwap_10d": 185.9068}, {"date": "2025-11-17", "open": 170.53, "high": 174.24, "low": 167.68, "close": 171.25, "volume": 50339000, "vwap_10d": 182.6273}, {"date": "2025-11-18", "open": 168.37, "high": 172.83, "low": 165.5, "close": 167.33, "volume": 53710100, "vwap_10d": 179.978}, {"date": "2025-11-19", "open": 167.8, "high": 169.6, "low": 162.42, "close": 165.42, "volume": 46108200, "vwap_10d": 178.1273}, {"date": "2025-11-20", "open": 172.07, "high": 174.57, "low": 154.395, "close": 155.745, "volume": 78443900, "vwap_10d": 175.8625}, {"date": "2025-11-21", "open": 156.01, "high": 158.11, "low": 147.56, "close": 154.85, "volume": 71346400, "vwap_10d": 173.2806}, {"date": "2025-11-24", "open": 157.47, "high": 165.17, "low": 157.0, "close": 162.25, "volume": 57877800, "vwap_10d": 169.5747}, {"date": "2025-11-25", "open": 160.07, "high": 164.65, "low": 156.555, "close": 163.55, "volume": 36523500, "vwap_10d": 167.2705}, {"date": "2025-11-26", "open": 166.85, "high": 168.339, "low": 163.88, "close": 165.77, "volume": 34610500, "vwap_10d": 165.4204}, {"date": "2025-11-28", "open": 167.76, "high": 168.8, "low": 165.875, "close": 168.45, "volume": 17199500, "vwap_10d": 164.2485}, {"date": "2025-12-01", "open": 165.0, "high": 169.1, "low": 163.12, "close": 167.49, "volume": 27779600, "vwap_10d": 163.3966}, {"date": "2025-12-02", "open": 169.59, "high": 175.75, "low": 169.59, "close": 170.69, "volume": 35368000, "vwap_10d": 163.2318}, {"date": "2025-12-03", "open": 170.14, "high": 177.91, "low": 168.83, "close": 176.08, "volume": 30541600, "vwap_10d": 163.3397}, {"date": "2025-12-04", "open": 176.365, "high": 178.44, "low": 174.43, "close": 177.92, "volume": 29217800, "vwap_10d": 164.0136}, {"date": "2025-12-05", "open": 178.23, "high": 182.153, "low": 177.16, "close": 181.76, "volume": 32079300, "vwap_10d": 165.9307}, {"date": "2025-12-08", "open": 182.21, "high": 183.88, "low": 179.54, "close": 181.49, "volume": 30456700, "vwap_10d": 170.0575}, {"date": "2025-12-09", "open": 180.97, "high": 182.85, "low": 180.38, "close": 181.84, "volume": 18937600, "vwap_10d": 172.5016}, {"date": "2025-12-10", "open": 184.95, "high": 190.39, "low": 182.75, "close": 187.91, "volume": 59398000, "vwap_10d": 176.4674}, {"date": "2025-12-11", "open": 184.8, "high": 188.05, "low": 180.21, "close": 187.54, "volume": 36843200, "vwap_10d": 178.6239}, {"date": "2025-12-12", "open": 185.81, "high": 186.525, "low": 177.667, "close": 183.57, "volume": 42427400, "vwap_10d": 179.6606}, {"date": "2025-12-15", "open": 185.08, "high": 187.78, "low": 180.03, "close": 183.25, "volume": 32796100, "vwap_10d": 181.0944}, {"date": "2025-12-16", "open": 181.655, "high": 188.5, "low": 181.142, "close": 187.75, "volume": 42070300, "vwap_10d": 182.5473}, {"date": "2025-12-17", "open": 187.715, "high": 187.75, "low": 176.5, "close": 177.29, "volume": 50424700, "vwap_10d": 182.9592}, {"date": "2025-12-18", "open": 181.51, "high": 187.33, "low": 181.51, "close": 185.69, "volume": 40221500, "vwap_10d": 183.6566}, {"date": "2025-12-19", "open": 186.74, "high": 195.0, "low": 186.73, "close": 193.38, "volume": 76929400, "vwap_10d": 185.3252}, {"date": "2025-12-22", "open": 195.04, "high": 198.88, "low": 192.43, "close": 193.98, "volume": 36686000, "vwap_10d": 186.4418}, {"date": "2025-12-23", "open": 192.825, "high": 195.37, "low": 191.735, "close": 194.13, "volume": 24041000, "vwap_10d": 187.0432}, {"date": "2025-12-24", "open": 193.16, "high": 195.17, "low": 192.83, "close": 194.17, "volume": 11710100, "vwap_10d": 187.2551}, {"date": "2025-12-26", "open": 195.015, "high": 196.35, "low": 188.62, "close": 188.71, "volume": 26262000, "vwap_10d": 187.718}, {"date": "2025-12-29", "open": 186.85, "high": 187.2, "low": 183.64, "close": 184.18, "volume": 28242000, "vwap_10d": 188.0978}, {"date": "2025-12-30", "open": 184.35, "high": 184.729, "low": 180.7, "close": 180.84, "volume": 23336300, "vwap_10d": 188.1102}, {"date": "2025-12-31", "open": 181.13, "high": 181.53, "low": 177.25, "close": 177.75, "volume": 22997400, "vwap_10d": 187.7726}, {"date": "2026-01-02", "open": 181.3, "high": 181.35, "low": 166.35, "close": 167.86, "volume": 60634100, "vwap_10d": 186.0967}, {"date": "2026-01-05", "open": 174.88, "high": 175.82, "low": 171.79, "close": 174.04, "volume": 39511700, "vwap_10d": 184.8629}, {"date": "2026-01-06", "open": 175.76, "high": 180.19, "low": 174.77, "close": 179.71, "volume": 34838600, "vwap_10d": 182.4058}, {"date": "2026-01-07", "open": 179.8, "high": 187.28, "low": 177.66, "close": 181.68, "volume": 45349000, "vwap_10d": 180.9114}, {"date": "2026-01-08", "open": 185.615, "high": 185.66, "low": 174.37, "close": 176.86, "volume": 47304300, "vwap_10d": 179.7334}, {"date": "2026-01-09", "open": 177.02, "high": 178.72, "low": 174.75, "close": 177.49, "volume": 31362900, "vwap_10d": 179.0272}, {"date": "2026-01-12", "open": 177.685, "high": 182.5, "low": 176.34, "close": 179.41, "volume": 34954500, "vwap_10d": 178.1811}, {"date": "2026-01-13", "open": 178.875, "high": 181.1, "low": 176.14, "close": 178.96, "volume": 27769400, "vwap_10d": 177.6997}, {"date": "2026-01-14", "open": 178.125, "high": 181.598, "low": 173.95, "close": 178.4, "volume": 33651400, "vwap_10d": 177.4541}, {"date": "2026-01-15", "open": 178.71, "high": 180.6, "low": 176.53, "close": 177.07, "volume": 31109200, "vwap_10d": 177.4208}, {"date": "2026-01-16", "open": 179.36, "high": 182.43, "low": 170.01, "close": 170.96, "volume": 59483600, "vwap_10d": 177.8292}, {"date": "2026-01-20", "open": 167.625, "high": 171.97, "low": 166.24, "close": 168.53, "volume": 36708500, "vwap_10d": 177.3213}, {"date": "2026-01-21", "open": 168.402, "high": 169.49, "low": 161.11, "close": 165.33, "volume": 47851200, "vwap_10d": 175.7877}, {"date": "2026-01-22", "open": 168.925, "high": 169.0, "low": 164.95, "close": 165.9, "volume": 28499500, "vwap_10d": 174.3343}, {"date": "2026-01-23", "open": 167.27, "high": 172.0, "low": 166.3, "close": 169.6, "volume": 30285700, "vwap_10d": 173.2972}, {"date": "2026-01-26", "open": 168.21, "high": 170.59, "low": 167.325, "close": 167.47, "volume": 22777200, "vwap_10d": 172.6576}, {"date": "2026-01-27", "open": 167.48, "high": 169.44, "low": 164.69, "close": 165.7, "volume": 26542300, "vwap_10d": 171.5136}, {"date": "2026-01-28", "open": 164.4, "high": 165.045, "low": 157.24, "close": 157.35, "volume": 44822800, "vwap_10d": 169.545}, {"date": "2026-01-29", "open": 157.63, "high": 157.63, "low": 147.12, "close": 151.86, "volume": 59846800, "vwap_10d": 166.1298}, {"date": "2026-01-30", "open": 150.05, "high": 151.0, "low": 145.139, "close": 146.59, "volume": 47271000, "vwap_10d": 163.0335}, {"date": "2026-02-02", "open": 150.94, "high": 151.4, "low": 146.654, "close": 147.76, "volume": 72811100, "vwap_10d": 158.8853}, {"date": "2026-02-03", "open": 165.05, "high": 165.078, "low": 153.12, "close": 157.88, "volume": 113169200, "vwap_10d": 158.0995}, {"date": "2026-02-04", "open": 155.41, "high": 155.85, "low": 135.68, "close": 139.54, "volume": 113199500, "vwap_10d": 154.6735}, {"date": "2026-02-05", "open": 136.82, "high": 137.98, "low": 128.32, "close": 130.01, "volume": 93690800, "vwap_10d": 150.6859}, {"date": "2026-02-06", "open": 135.33, "high": 137.687, "low": 132.35, "close": 135.9, "volume": 62661400, "vwap_10d": 148.3561}, {"date": "2026-02-09", "open": 136.58, "high": 145.87, "low": 134.776, "close": 142.91, "volume": 58042500, "vwap_10d": 147.0919}, {"date": "2026-02-10", "open": 144.965, "high": 145.56, "low": 137.77, "close": 139.51, "volume": 56061300, "vwap_10d": 145.8794}, {"date": "2026-02-11", "open": 139.025, "high": 139.25, "low": 132.95, "close": 135.68, "volume": 52796100, "vwap_10d": 144.3026}, {"date": "2026-02-12", "open": 135.36, "high": 135.89, "low": 126.56, "close": 129.13, "volume": 74090600, "vwap_10d": 142.2859}, {"date": "2026-02-13", "open": 127.9, "high": 133.56, "low": 126.233, "close": 131.41, "volume": 49438100, "vwap_10d": 141.1581}, {"date": "2026-02-17", "open": 128.895, "high": 134.32, "low": 127.29, "close": 133.02, "volume": 48407100, "vwap_10d": 139.7621}, {"date": "2026-02-18", "open": 135.89, "high": 140.963, "low": 134.87, "close": 135.38, "volume": 59677100, "vwap_10d": 136.3176}, {"date": "2026-02-19", "open": 132.31, "high": 136.16, "low": 131.01, "close": 134.89, "volume": 42197200, "vwap_10d": 134.7488}, {"date": "2026-02-20", "open": 132.365, "high": 136.21, "low": 131.17, "close": 135.24, "volume": 53726800, "vwap_10d": 135.1332}, {"date": "2026-02-23", "open": 132.04, "high": 132.04, "low": 127.39, "close": 130.6, "volume": 52512200, "vwap_10d": 134.621}, {"date": "2026-02-24", "open": 129.005, "high": 130.24, "low": 126.37, "close": 128.84, "volume": 47121400, "vwap_10d": 133.4008}, {"date": "2026-02-25", "open": 130.61, "high": 136.09, "low": 129.18, "close": 134.19, "volume": 53078300, "vwap_10d": 132.585}, {"date": "2026-02-26", "open": 133.845, "high": 137.51, "low": 132.63, "close": 135.94, "volume": 45100000, "vwap_10d": 132.4844}, {"date": "2026-02-27", "open": 134.07, "high": 138.1, "low": 133.98, "close": 137.19, "volume": 59412400, "vwap_10d": 133.2014}, {"date": "2026-03-02", "open": 140.775, "high": 147.14, "low": 140.52, "close": 145.17, "volume": 72683900, "vwap_10d": 134.9463}, {"date": "2026-03-03", "open": 142.1, "high": 147.5, "low": 138.2, "close": 147.22, "volume": 67460200, "vwap_10d": 136.3446}, {"date": "2026-03-04", "open": 148.43, "high": 154.52, "low": 148.06, "close": 153.19, "volume": 60062200, "vwap_10d": 137.998}, {"date": "2026-03-05", "open": 152.94, "high": 156.38, "low": 149.61, "close": 152.67, "volume": 50714500, "vwap_10d": 139.6515}, {"date": "2026-03-06", "open": 150.44, "high": 161.45, "low": 150.29, "close": 157.16, "volume": 74980900, "vwap_10d": 142.2757}, {"date": "2026-03-09", "open": 155.69, "high": 158.44, "low": 152.97, "close": 156.43, "volume": 47574200, "vwap_10d": 144.5144}, {"date": "2026-03-10", "open": 155.99, "high": 156.657, "low": 150.14, "close": 151.14, "volume": 47501400, "vwap_10d": 146.4893}, {"date": "2026-03-11", "open": 151.38, "high": 153.169, "low": 149.33, "close": 151.6, "volume": 33955900, "vwap_10d": 148.0489}, {"date": "2026-03-12", "open": 153.01, "high": 155.88, "low": 150.98, "close": 153.5, "volume": 54409800, "vwap_10d": 149.5713}, {"date": "2026-03-13", "open": 153.3, "high": 154.56, "low": 148.58, "close": 150.95, "volume": 42460600, "vwap_10d": 151.1263}, {"date": "2026-03-16", "open": 152.45, "high": 153.86, "low": 151.17, "close": 152.72, "volume": 32898900, "vwap_10d": 152.1925}, {"date": "2026-03-17", "open": 152.405, "high": 156.75, "low": 152.12, "close": 155.08, "volume": 37118500, "vwap_10d": 153.4952}, {"date": "2026-03-18", "open": 154.945, "high": 156.69, "low": 152.61, "close": 152.77, "volume": 32476700, "vwap_10d": 153.7466}, {"date": "2026-03-19", "open": 153.1, "high": 156.15, "low": 150.5, "close": 155.68, "volume": 33915900, "vwap_10d": 153.8716}, {"date": "2026-03-20", "open": 155.2, "high": 156.65, "low": 149.09, "close": 150.68, "volume": 48700200, "vwap_10d": 153.2594}, {"date": "2026-03-23", "open": 153.24, "high": 161.08, "low": 153.24, "close": 160.84, "volume": 57507100, "vwap_10d": 153.6237}, {"date": "2026-03-24", "open": 160.07, "high": 162.4, "low": 151.64, "close": 154.78, "volume": 56155700, "vwap_10d": 154.0982}, {"date": "2026-03-25", "open": 157.42, "high": 160.27, "low": 154.855, "close": 154.96, "volume": 38543300, "vwap_10d": 154.542}, {"date": "2026-03-26", "open": 153.055, "high": 153.12, "low": 147.25, "close": 147.56, "volume": 43038400, "vwap_10d": 154.1501}, {"date": "2026-03-27", "open": 145.88, "high": 145.96, "low": 141.56, "close": 143.06, "volume": 35790800, "vwap_10d": 153.4993}, {"date": "2026-03-30", "open": 143.27, "high": 144.12, "low": 136.3, "close": 137.55, "volume": 41289800, "vwap_10d": 152.2087}, {"date": "2026-03-31", "open": 140.02, "high": 147.86, "low": 138.97, "close": 146.28, "volume": 45558600, "vwap_10d": 151.1747}, {"date": "2026-04-01", "open": 147.0, "high": 148.3, "low": 144.47, "close": 146.49, "volume": 34171000, "vwap_10d": 150.5881}, {"date": "2026-04-02", "open": 143.485, "high": 148.51, "low": 137.99, "close": 148.46, "volume": 30437000, "vwap_10d": 149.916}, {"date": "2026-04-06", "open": 148.36, "high": 150.61, "low": 146.631, "close": 147.93, "volume": 25142200, "vwap_10d": 149.5562}, {"date": "2026-04-07", "open": 146.882, "high": 150.27, "low": 144.45, "close": 150.07, "volume": 28671100, "vwap_10d": 148.1317}, {"date": "2026-04-08", "open": 154.765, "high": 156.28, "low": 139.17, "close": 140.76, "volume": 64827700, "vwap_10d": 146.5345}, {"date": "2026-04-09", "open": 139.395, "high": 139.54, "low": 128.47, "close": 130.49, "volume": 92361400, "vwap_10d": 142.7915}, {"date": "2026-04-10", "open": 128.48, "high": 129.2, "low": 122.68, "close": 128.06, "volume": 116656800, "vwap_10d": 138.5366}, {"date": "2026-04-13", "open": 130.23, "high": 134.42, "low": 129.15, "close": 132.37, "volume": 65772800, "vwap_10d": 137.4173}, {"date": "2026-04-14", "open": 134.427, "high": 138.07, "low": 134.0, "close": 135.7, "volume": 52786800, "vwap_10d": 137.1338}, {"date": "2026-04-15", "open": 136.79, "high": 142.58, "low": 134.93, "close": 142.15, "volume": 48389400, "vwap_10d": 136.7824}, {"date": "2026-04-16", "open": 144.29, "high": 145.55, "low": 139.53, "close": 142.76, "volume": 43746000, "vwap_10d": 136.6514}, {"date": "2026-04-17", "open": 145.315, "high": 148.28, "low": 143.3, "close": 146.39, "volume": 50657600, "vwap_10d": 137.0238}, {"date": "2026-04-20", "open": 145.0, "high": 147.2, "low": 143.83, "close": 145.89, "volume": 33482700, "vwap_10d": 137.0263}, {"date": "2026-04-21", "open": 146.81, "high": 149.87, "low": 143.999, "close": 145.97, "volume": 44830000, "vwap_10d": 137.2017}, {"date": "2026-04-22", "open": 148.36, "high": 152.68, "low": 147.42, "close": 152.62, "volume": 43460681, "vwap_10d": 137.3039}], "volume_profile": {"10d": {"buckets": [{"price": 123.43, "volume": 6208495.2}, {"price": 124.93, "volume": 25079360.0}, {"price": 126.43, "volume": 44078336.37}, {"price": 127.93, "volume": 36020479.56}, {"price": 129.43, "volume": 23992892.44}, {"price": 130.93, "volume": 38876816.89}, {"price": 132.43, "volume": 48116474.72}, {"price": 133.93, "volume": 33133270.96}, {"price": 135.43, "volume": 42437922.77}, {"price": 136.93, "volume": 30332937.96}, {"price": 138.43, "volume": 15772124.31}, {"price": 139.93, "volume": 19445815.93}, {"price": 141.43, "volume": 23928186.63}, {"price": 142.93, "volume": 23414562.38}, {"price": 144.43, "volume": 34919247.09}, {"price": 145.93, "volume": 64759665.41}, {"price": 147.43, "volume": 31373631.71}, {"price": 148.93, "volume": 13689845.07}, {"price": 150.43, "volume": 20717316.08}, {"price": 151.93, "volume": 15846799.52}], "vwap": 137.3039}, "20d": {"buckets": [{"price": 123.6198, "volume": 9715221.1}, {"price": 125.4993, "volume": 42846063.48}, {"price": 127.3788, "volume": 52433979.31}, {"price": 129.2583, "volume": 30249041.69}, {"price": 131.1378, "volume": 52520671.45}, {"price": 133.0173, "volume": 53408988.72}, {"price": 134.8968, "volume": 48118428.13}, {"price": 136.7763, "volume": 50100214.87}, {"price": 138.6558, "volume": 39167938.73}, {"price": 140.5353, "volume": 52003418.75}, {"price": 142.4148, "volume": 74416875.79}, {"price": 144.2943, "volume": 97249220.73}, {"price": 146.1738, "volume": 144328924.11}, {"price": 148.0533, "volume": 96329887.91}, {"price": 149.9328, "volume": 62911235.53}, {"price": 151.8123, "volume": 29627642.41}, {"price": 153.6918, "volume": 6504251.21}, {"price": 155.5713, "volume": 15884678.2}, {"price": 157.4508, "volume": 18523554.36}, {"price": 159.3303, "volume": 3273844.53}], "vwap": 140.9437}, "30d": {"buckets": [{"price": 123.673, "volume": 10899838.5}, {"price": 125.659, "volume": 48340859.69}, {"price": 127.645, "volume": 51973315.08}, {"price": 129.631, "volume": 32283195.68}, {"price": 131.617, "volume": 62710787.88}, {"price": 133.603, "volume": 47591617.14}, {"price": 135.589, "volume": 60956872.71}, {"price": 137.575, "volume": 40579481.8}, {"price": 139.561, "volume": 48177975.27}, {"price": 141.547, "volume": 64964309.74}, {"price": 143.533, "volume": 92579990.34}, {"price": 145.519, "volume": 144414487.61}, {"price": 147.505, "volume": 116880514.27}, {"price": 149.491, "volume": 97836016.39}, {"price": 151.477, "volume": 137694836.58}, {"price": 153.463, "volume": 154919247.31}, {"price": 155.449, "volume": 95230655.26}, {"price": 157.435, "volume": 59161515.16}, {"price": 159.421, "volume": 32042365.49}, {"price": 161.407, "volume": 9975499.1}], "vwap": 144.9448}, "40d": {"buckets": [{"price": 123.673, "volume": 10899845.52}, {"price": 125.659, "volume": 48342853.06}, {"price": 127.645, "volume": 52124183.35}, {"price": 129.631, "volume": 35328871.75}, {"price": 131.617, "volume": 79368471.33}, {"price": 133.603, "volume": 82584529.8}, {"price": 135.589, "volume": 131946555.95}, {"price": 137.575, "volume": 72160880.45}, {"price": 139.561, "volume": 52189747.54}, {"price": 141.547, "volume": 85259381.36}, {"price": 143.533, "volume": 145785841.17}, {"price": 145.519, "volume": 190760791.45}, {"price": 147.505, "volume": 132155317.66}, {"price": 149.491, "volume": 117286407.72}, {"price": 151.477, "volume": 205872059.76}, {"price": 153.463, "volume": 234564613.25}, {"price": 155.449, "volume": 157139363.34}, {"price": 157.435, "volume": 95297197.44}, {"price": 159.421, "volume": 44690710.96}, {"price": 161.407, "volume": 14023758.14}], "vwap": 145.3968}, "50d": {"buckets": [{"price": 123.673, "volume": 11261987.36}, {"price": 125.659, "volume": 52611327.69}, {"price": 127.645, "volume": 104084255.83}, {"price": 129.631, "volume": 143813995.27}, {"price": 131.617, "volume": 164137978.2}, {"price": 133.603, "volume": 174833166.06}, {"price": 135.589, "volume": 212820796.46}, {"price": 137.575, "volume": 124197901.47}, {"price": 139.561, "volume": 80023560.21}, {"price": 141.547, "volume": 107471993.97}, {"price": 143.533, "volume": 155232762.61}, {"price": 145.519, "volume": 192209992.97}, {"price": 147.505, "volume": 132233934.5}, {"price": 149.491, "volume": 117287915.26}, {"price": 151.477, "volume": 205872069.98}, {"price": 153.463, "volume": 234564613.28}, {"price": 155.449, "volume": 157139363.34}, {"price": 157.435, "volume": 95297197.44}, {"price": 159.421, "volume": 44690710.96}, {"price": 161.407, "volume": 14023758.14}], "vwap": 142.8426}, "60d": {"buckets": [{"price": 123.849, "volume": 16175085.28}, {"price": 126.187, "volume": 78028586.03}, {"price": 128.525, "volume": 160990509.53}, {"price": 130.863, "volume": 218869494.64}, {"price": 133.201, "volume": 250081396.82}, {"price": 135.539, "volume": 314299834.94}, {"price": 137.877, "volume": 156520447.85}, {"price": 140.215, "volume": 135125293.56}, {"price": 142.553, "volume": 196812039.39}, {"price": 144.891, "volume": 248553482.22}, {"price": 147.229, "volume": 250701406.63}, {"price": 149.567, "volume": 218197763.55}, {"price": 151.905, "volume": 299122403.11}, {"price": 154.243, "volume": 271088896.11}, {"price": 156.581, "volume": 178186426.96}, {"price": 158.919, "volume": 119977577.16}, {"price": 161.257, "volume": 59401766.84}, {"price": 163.595, "volume": 15646328.71}, {"price": 165.933, "volume": 19990435.92}, {"price": 168.271, "volume": 8097505.75}], "vwap": 143.7476}, "70d": {"buckets": [{"price": 124.1755, "volume": 28627539.6}, {"price": 127.1665, "volume": 146340227.6}, {"price": 130.1575, "volume": 259445927.7}, {"price": 133.1485, "volume": 321202406.43}, {"price": 136.1395, "volume": 367032804.36}, {"price": 139.1305, "volume": 158018064.14}, {"price": 142.1215, "volume": 236240500.97}, {"price": 145.1125, "volume": 327281112.59}, {"price": 148.1035, "volume": 302031697.92}, {"price": 151.0945, "volume": 326318262.21}, {"price": 154.0855, "volume": 358139402.47}, {"price": 157.0765, "volume": 211717605.06}, {"price": 160.0675, "volume": 117898441.39}, {"price": 163.0585, "volume": 43314385.81}, {"price": 166.0495, "volume": 84685701.87}, {"price": 169.0405, "volume": 92346701.44}, {"price": 172.0315, "volume": 23962562.48}, {"price": 175.0225, "volume": 30067161.25}, {"price": 178.0135, "volume": 104057279.17}, {"price": 181.0045, "volume": 30229096.56}], "vwap": 146.5932}, "80d": {"buckets": [{"price": 124.5218, "volume": 49707952.34}, {"price": 128.2053, "volume": 228150614.31}, {"price": 131.8888, "volume": 369405139.0}, {"price": 135.5723, "volume": 465800236.24}, {"price": 139.2558, "volume": 195801083.35}, {"price": 142.9393, "volume": 318253555.19}, {"price": 146.6228, "volume": 407604561.07}, {"price": 150.3063, "volume": 372373677.08}, {"price": 153.9898, "volume": 443719271.06}, {"price": 157.6733, "volume": 241285425.75}, {"price": 161.3568, "volume": 95750895.85}, {"price": 165.0403, "volume": 85075416.07}, {"price": 168.7238, "volume": 131690361.01}, {"price": 172.4073, "volume": 83972723.54}, {"price": 176.0908, "volume": 139807160.63}, {"price": 179.7743, "volume": 189030779.77}, {"price": 183.4578, "volume": 75541090.85}, {"price": 187.1413, "volume": 11646034.88}, {"price": 190.8248, "volume": 19482451.94}, {"price": 194.5083, "volume": 4696751.07}], "vwap": 149.5707}, "90d": {"buckets": [{"price": 124.585, "volume": 54926555.68}, {"price": 128.395, "volume": 246450094.13}, {"price": 132.205, "volume": 389506897.3}, {"price": 136.015, "volume": 449525080.04}, {"price": 139.825, "volume": 209822125.22}, {"price": 143.635, "volume": 354045089.06}, {"price": 147.445, "volume": 425610461.2}, {"price": 151.255, "volume": 425465517.79}, {"price": 155.065, "volume": 387999529.14}, {"price": 158.875, "volume": 199324190.72}, {"price": 162.685, "volume": 62143067.99}, {"price": 166.495, "volume": 120655389.58}, {"price": 170.305, "volume": 102378590.32}, {"price": 174.115, "volume": 101644488.96}, {"price": 177.925, "volume": 265890586.99}, {"price": 181.735, "volume": 169422431.03}, {"price": 185.545, "volume": 173429621.15}, {"price": 189.355, "volume": 52961701.23}, {"price": 193.165, "volume": 110570052.78}, {"price": 196.975, "volume": 21173410.68}], "vwap": 153.0026}, "100d": {"buckets": [{"price": 124.585, "volume": 54926555.68}, {"price": 128.395, "volume": 246450094.13}, {"price": 132.205, "volume": 389506897.3}, {"price": 136.015, "volume": 449525080.04}, {"price": 139.825, "volume": 209822125.22}, {"price": 143.635, "volume": 354045089.06}, {"price": 147.445, "volume": 425610461.2}, {"price": 151.255, "volume": 425465517.79}, {"price": 155.065, "volume": 387999529.14}, {"price": 158.875, "volume": 199324236.34}, {"price": 162.685, "volume": 63482037.07}, {"price": 166.495, "volume": 197742347.57}, {"price": 170.305, "volume": 128542106.25}, {"price": 174.115, "volume": 137740159.6}, {"price": 177.925, "volume": 306839370.87}, {"price": 181.735, "volume": 244969088.5}, {"price": 185.545, "volume": 208988519.39}, {"price": 189.355, "volume": 75542152.66}, {"price": 193.165, "volume": 110838642.75}, {"price": 196.975, "volume": 21173470.43}], "vwap": 154.6083}, "110d": {"buckets": [{"price": 124.585, "volume": 54926555.68}, {"price": 128.395, "volume": 246450094.14}, {"price": 132.205, "volume": 389506898.33}, {"price": 136.015, "volume": 449525143.03}, {"price": 139.825, "volume": 209824359.45}, {"price": 143.635, "volume": 354124883.85}, {"price": 147.445, "volume": 429010405.44}, {"price": 151.255, "volume": 456949430.03}, {"price": 155.065, "volume": 433293768.58}, {"price": 158.875, "volume": 255472907.04}, {"price": 162.685, "volume": 155768271.93}, {"price": 166.495, "volume": 284537283.68}, {"price": 170.305, "volume": 240216701.67}, {"price": 174.115, "volume": 201001986.75}, {"price": 177.925, "volume": 333907843.11}, {"price": 181.735, "volume": 262332808.53}, {"price": 185.545, "volume": 241502160.48}, {"price": 189.355, "volume": 83446080.93}, {"price": 193.165, "volume": 111043463.47}, {"price": 196.975, "volume": 21174034.85}], "vwap": 156.0053}, "120d": {"buckets": [{"price": 124.801, "volume": 75637620.78}, {"price": 129.043, "volume": 304293863.94}, {"price": 133.285, "volume": 473672758.01}, {"price": 137.527, "volume": 367807648.97}, {"price": 141.769, "volume": 325035384.74}, {"price": 146.011, "volume": 446684025.62}, {"price": 150.253, "volume": 466911279.19}, {"price": 154.495, "volume": 532718124.18}, {"price": 158.737, "volume": 291917174.57}, {"price": 162.979, "volume": 168394238.54}, {"price": 167.221, "volume": 341081134.47}, {"price": 171.463, "volume": 260719456.46}, {"price": 175.705, "volume": 338222401.92}, {"price": 179.947, "volume": 401131213.99}, {"price": 184.189, "volume": 347827323.22}, {"price": 188.431, "volume": 278809683.95}, {"price": 192.673, "volume": 261915877.01}, {"price": 196.915, "volume": 123880718.46}, {"price": 201.157, "volume": 56658747.2}, {"price": 205.399, "volume": 81033905.75}], "vwap": 160.2892}, "130d": {"buckets": [{"price": 124.801, "volume": 75637620.78}, {"price": 129.043, "volume": 304293863.94}, {"price": 133.285, "volume": 473672758.01}, {"price": 137.527, "volume": 367807648.97}, {"price": 141.769, "volume": 325035384.74}, {"price": 146.011, "volume": 446684025.62}, {"price": 150.253, "volume": 466911279.19}, {"price": 154.495, "volume": 532718124.19}, {"price": 158.737, "volume": 291917198.17}, {"price": 162.979, "volume": 168405419.59}, {"price": 167.221, "volume": 341992542.92}, {"price": 171.463, "volume": 273657600.09}, {"price": 175.705, "volume": 403102781.63}, {"price": 179.947, "volume": 588818203.81}, {"price": 184.189, "volume": 393446212.65}, {"price": 188.431, "volume": 355378999.98}, {"price": 192.673, "volume": 270710896.27}, {"price": 196.915, "volume": 123880767.5}, {"price": 201.157, "volume": 56658747.2}, {"price": 205.399, "volume": 81033905.75}], "vwap": 161.6091}, "140d": {"buckets": [{"price": 124.801, "volume": 75637620.78}, {"price": 129.043, "volume": 304293863.94}, {"price": 133.285, "volume": 473672758.01}, {"price": 137.527, "volume": 367807648.97}, {"price": 141.769, "volume": 325035384.74}, {"price": 146.011, "volume": 446684025.62}, {"price": 150.253, "volume": 466911279.2}, {"price": 154.495, "volume": 532718132.1}, {"price": 158.737, "volume": 291918831.55}, {"price": 162.979, "volume": 168516542.13}, {"price": 167.221, "volume": 344575895.91}, {"price": 171.463, "volume": 297329935.62}, {"price": 175.705, "volume": 525612837.57}, {"price": 179.947, "volume": 749600701.64}, {"price": 184.189, "volume": 592506298.52}, {"price": 188.431, "volume": 375550041.66}, {"price": 192.673, "volume": 270739767.32}, {"price": 196.915, "volume": 123880962.2}, {"price": 201.157, "volume": 56658747.74}, {"price": 205.399, "volume": 81033905.75}], "vwap": 163.0587}, "150d": {"buckets": [{"price": 124.801, "volume": 75637620.78}, {"price": 129.043, "volume": 304293863.94}, {"price": 133.285, "volume": 473672758.01}, {"price": 137.527, "volume": 367807648.97}, {"price": 141.769, "volume": 325035384.74}, {"price": 146.011, "volume": 446684025.62}, {"price": 150.253, "volume": 466911279.2}, {"price": 154.495, "volume": 532718137.73}, {"price": 158.737, "volume": 291987841.78}, {"price": 162.979, "volume": 182961058.78}, {"price": 167.221, "volume": 396369183.76}, {"price": 171.463, "volume": 316718017.94}, {"price": 175.705, "volume": 627215940.87}, {"price": 179.947, "volume": 1092915592.98}, {"price": 184.189, "volume": 662654475.89}, {"price": 188.431, "volume": 376166445.18}, {"price": 192.673, "volume": 270739989.11}, {"price": 196.915, "volume": 123880962.2}, {"price": 201.157, "volume": 56658747.74}, {"price": 205.399, "volume": 81033905.75}], "vwap": 164.2576}, "160d": {"buckets": [{"price": 124.801, "volume": 75637620.78}, {"price": 129.043, "volume": 304293863.94}, {"price": 133.285, "volume": 473672758.01}, {"price": 137.527, "volume": 367807651.5}, {"price": 141.769, "volume": 325041532.46}, {"price": 146.011, "volume": 448029060.56}, {"price": 150.253, "volume": 494266351.89}, {"price": 154.495, "volume": 706507712.19}, {"price": 158.737, "volume": 377641982.01}, {"price": 162.979, "volume": 233190324.92}, {"price": 167.221, "volume": 507907946.21}, {"price": 171.463, "volume": 415646632.7}, {"price": 175.705, "volume": 627302522.84}, {"price": 179.947, "volume": 1092915595.12}, {"price": 184.189, "volume": 662654475.89}, {"price": 188.431, "volume": 376166445.18}, {"price": 192.673, "volume": 270739989.11}, {"price": 196.915, "volume": 123880962.2}, {"price": 201.157, "volume": 56658747.74}, {"price": 205.399, "volume": 81033905.75}], "vwap": 164.0585}, "170d": {"buckets": [{"price": 124.801, "volume": 75637620.78}, {"price": 129.043, "volume": 304293864.08}, {"price": 133.285, "volume": 473672908.05}, {"price": 137.527, "volume": 367844882.02}, {"price": 141.769, "volume": 327221437.83}, {"price": 146.011, "volume": 478194567.0}, {"price": 150.253, "volume": 604504710.71}, {"price": 154.495, "volume": 1100284130.42}, {"price": 158.737, "volume": 699437919.81}, {"price": 162.979, "volume": 317460516.87}, {"price": 167.221, "volume": 535153236.09}, {"price": 171.463, "volume": 419254189.41}, {"price": 175.705, "volume": 627445976.36}, {"price": 179.947, "volume": 1092917289.73}, {"price": 184.189, "volume": 662654481.83}, {"price": 188.431, "volume": 376166445.19}, {"price": 192.673, "volume": 270739989.11}, {"price": 196.915, "volume": 123880962.2}, {"price": 201.157, "volume": 56658747.74}, {"price": 205.399, "volume": 81033905.75}], "vwap": 163.2168}, "180d": {"buckets": [{"price": 124.801, "volume": 75637620.78}, {"price": 129.043, "volume": 304293864.08}, {"price": 133.285, "volume": 473672908.05}, {"price": 137.527, "volume": 367844882.02}, {"price": 141.769, "volume": 327221437.83}, {"price": 146.011, "volume": 478194567.0}, {"price": 150.253, "volume": 604504710.71}, {"price": 154.495, "volume": 1100284130.42}, {"price": 158.737, "volume": 699437919.81}, {"price": 162.979, "volume": 317460538.32}, {"price": 167.221, "volume": 535900455.58}, {"price": 171.463, "volume": 527642627.09}, {"price": 175.705, "volume": 815274567.14}, {"price": 179.947, "volume": 1218056653.6}, {"price": 184.189, "volume": 850376806.39}, {"price": 188.431, "volume": 461350983.0}, {"price": 192.673, "volume": 271031663.41}, {"price": 196.915, "volume": 123880992.27}, {"price": 201.157, "volume": 56658747.74}, {"price": 205.399, "volume": 81033905.75}], "vwap": 164.3963}, "190d": {"buckets": [{"price": 124.801, "volume": 75637620.78}, {"price": 129.043, "volume": 304293864.08}, {"price": 133.285, "volume": 473672908.05}, {"price": 137.527, "volume": 367844882.04}, {"price": 141.769, "volume": 327234192.95}, {"price": 146.011, "volume": 494038051.05}, {"price": 150.253, "volume": 660925986.22}, {"price": 154.495, "volume": 1255969781.81}, {"price": 158.737, "volume": 1001532763.66}, {"price": 162.979, "volume": 318442319.25}, {"price": 167.221, "volume": 535900464.72}, {"price": 171.463, "volume": 527642627.09}, {"price": 175.705, "volume": 815274567.14}, {"price": 179.947, "volume": 1218056653.6}, {"price": 184.189, "volume": 850376806.39}, {"price": 188.431, "volume": 461350983.0}, {"price": 192.673, "volume": 271031663.41}, {"price": 196.915, "volume": 123880992.27}, {"price": 201.157, "volume": 56658747.74}, {"price": 205.399, "volume": 81033905.75}], "vwap": 163.9715}, "200d": {"buckets": [{"price": 124.801, "volume": 75637620.78}, {"price": 129.043, "volume": 304293864.08}, {"price": 133.285, "volume": 473673146.46}, {"price": 137.527, "volume": 430050288.13}, {"price": 141.769, "volume": 508392269.21}, {"price": 146.011, "volume": 562511149.81}, {"price": 150.253, "volume": 800078843.34}, {"price": 154.495, "volume": 1399281790.87}, {"price": 158.737, "volume": 1001540177.96}, {"price": 162.979, "volume": 318442319.25}, {"price": 167.221, "volume": 535900464.72}, {"price": 171.463, "volume": 527642627.09}, {"price": 175.705, "volume": 815274567.14}, {"price": 179.947, "volume": 1218056653.6}, {"price": 184.189, "volume": 850376806.39}, {"price": 188.431, "volume": 461350983.0}, {"price": 192.673, "volume": 271031663.41}, {"price": 196.915, "volume": 123880992.27}, {"price": 201.157, "volume": 56658747.74}, {"price": 205.399, "volume": 81033905.75}], "vwap": 163.0317}}, "vms_matrix": {"cells": [{"endpoint": 10, "start": 20, "score": -0.025825}, {"endpoint": 10, "start": 30, "score": -0.026715}, {"endpoint": 10, "start": 40, "score": -0.018909}, {"endpoint": 10, "start": 50, "score": -0.009838}, {"endpoint": 10, "start": 60, "score": -0.009131}, {"endpoint": 10, "start": 70, "score": -0.010851}, {"endpoint": 10, "start": 80, "score": -0.01215}, {"endpoint": 10, "start": 90, "score": -0.013441}, {"endpoint": 10, "start": 100, "score": -0.013102}, {"endpoint": 10, "start": 110, "score": -0.012688}, {"endpoint": 20, "start": 30, "score": -0.027604}, {"endpoint": 20, "start": 40, "score": -0.015433}, {"endpoint": 20, "start": 50, "score": -0.004451}, {"endpoint": 20, "start": 60, "score": -0.004912}, {"endpoint": 20, "start": 70, "score": -0.007829}, {"endpoint": 20, "start": 80, "score": -0.009853}, {"endpoint": 20, "start": 90, "score": -0.011659}, {"endpoint": 20, "start": 100, "score": -0.0115}, {"endpoint": 20, "start": 110, "score": -0.011218}, {"endpoint": 20, "start": 120, "score": -0.01278}, {"endpoint": 30, "start": 40, "score": -0.003109}, {"endpoint": 30, "start": 50, "score": 0.007331}, {"endpoint": 30, "start": 60, "score": 0.002768}, {"endpoint": 30, "start": 70, "score": -0.002823}, {"endpoint": 30, "start": 80, "score": -0.006264}, {"endpoint": 30, "start": 90, "score": -0.008977}, {"endpoint": 30, "start": 100, "score": -0.009178}, {"endpoint": 30, "start": 110, "score": -0.00915}, {"endpoint": 30, "start": 120, "score": -0.011119}, {"endpoint": 30, "start": 130, "score": -0.010824}, {"endpoint": 40, "start": 50, "score": 0.017881}, {"endpoint": 40, "start": 60, "score": 0.00572}, {"endpoint": 40, "start": 70, "score": -0.002728}, {"endpoint": 40, "start": 80, "score": -0.007051}, {"endpoint": 40, "start": 90, "score": -0.010146}, {"endpoint": 40, "start": 100, "score": -0.010186}, {"endpoint": 40, "start": 110, "score": -0.01001}, {"endpoint": 40, "start": 120, "score": -0.012115}, {"endpoint": 40, "start": 130, "score": -0.011677}, {"endpoint": 40, "start": 140, "score": -0.011399}, {"endpoint": 50, "start": 60, "score": -0.006296}, {"endpoint": 50, "start": 70, "score": -0.012875}, {"endpoint": 50, "start": 80, "score": -0.015225}, {"endpoint": 50, "start": 90, "score": -0.017031}, {"endpoint": 50, "start": 100, "score": -0.015706}, {"endpoint": 50, "start": 110, "score": -0.014584}, {"endpoint": 50, "start": 120, "score": -0.016328}, {"endpoint": 50, "start": 130, "score": -0.015311}, {"endpoint": 50, "start": 140, "score": -0.0146}, {"endpoint": 50, "start": 150, "score": -0.013872}, {"endpoint": 60, "start": 70, "score": -0.019411}, {"endpoint": 60, "start": 80, "score": -0.019659}, {"endpoint": 60, "start": 90, "score": -0.020584}, {"endpoint": 60, "start": 100, "score": -0.018044}, {"endpoint": 60, "start": 110, "score": -0.016233}, {"endpoint": 60, "start": 120, "score": -0.01799}, {"endpoint": 60, "start": 130, "score": -0.016592}, {"endpoint": 60, "start": 140, "score": -0.015633}, {"endpoint": 60, "start": 150, "score": -0.01471}, {"endpoint": 60, "start": 160, "score": -0.013129}, {"endpoint": 70, "start": 80, "score": -0.019907}, {"endpoint": 70, "start": 90, "score": -0.02117}, {"endpoint": 70, "start": 100, "score": -0.017588}, {"endpoint": 70, "start": 110, "score": -0.015437}, {"endpoint": 70, "start": 120, "score": -0.017705}, {"endpoint": 70, "start": 130, "score": -0.016122}, {"endpoint": 70, "start": 140, "score": -0.015092}, {"endpoint": 70, "start": 150, "score": -0.014121}, {"endpoint": 70, "start": 160, "score": -0.012429}, {"endpoint": 70, "start": 170, "score": -0.010684}, {"endpoint": 80, "start": 90, "score": -0.022431}, {"endpoint": 80, "start": 100, "score": -0.016426}, {"endpoint": 80, "start": 110, "score": -0.013942}, {"endpoint": 80, "start": 120, "score": -0.017154}, {"endpoint": 80, "start": 130, "score": -0.015363}, {"endpoint": 80, "start": 140, "score": -0.014287}, {"endpoint": 80, "start": 150, "score": -0.013292}, {"endpoint": 80, "start": 160, "score": -0.01149}, {"endpoint": 80, "start": 170, "score": -0.009654}, {"endpoint": 80, "start": 180, "score": -0.009407}, {"endpoint": 90, "start": 100, "score": -0.010385}, {"endpoint": 90, "start": 110, "score": -0.00967}, {"endpoint": 90, "start": 120, "score": -0.015389}, {"endpoint": 90, "start": 130, "score": -0.013588}, {"endpoint": 90, "start": 140, "score": -0.01265}, {"endpoint": 90, "start": 150, "score": -0.01176}, {"endpoint": 90, "start": 160, "score": -0.009917}, {"endpoint": 90, "start": 170, "score": -0.008045}, {"endpoint": 90, "start": 180, "score": -0.007949}, {"endpoint": 90, "start": 190, "score": -0.0069}, {"endpoint": 100, "start": 110, "score": -0.008955}, {"endpoint": 100, "start": 120, "score": -0.017881}, {"endpoint": 100, "start": 130, "score": -0.014654}, {"endpoint": 100, "start": 140, "score": -0.013216}, {"endpoint": 100, "start": 150, "score": -0.012035}, {"endpoint": 100, "start": 160, "score": -0.009839}, {"endpoint": 100, "start": 170, "score": -0.007711}, {"endpoint": 100, "start": 180, "score": -0.007644}, {"endpoint": 100, "start": 190, "score": -0.006512}, {"endpoint": 100, "start": 200, "score": -0.005291}], "row_scores": [-0.019162, -0.014375, -0.001626, 0.001751, -0.012606, -0.01861, -0.018077, -0.016863, -0.011384, -0.012125], "vms": -0.012197}, "latest_price": 152.62, "_meta": {"updated_at": "2026-04-23 07:53"}}