{"name": "테슬라", "ticker": "TSLA", "ohlcv": [{"date": "2025-06-11", "open": 334.4, "high": 335.5, "low": 322.5, "close": 326.43, "volume": 122611400, "vwap_20d": null}, {"date": "2025-06-12", "open": 323.08, "high": 332.56, "low": 316.86, "close": 319.11, "volume": 105127500, "vwap_20d": null}, {"date": "2025-06-13", "open": 313.97, "high": 332.99, "low": 313.3, "close": 325.31, "volume": 128964300, "vwap_20d": null}, {"date": "2025-06-16", "open": 331.29, "high": 332.05, "low": 326.41, "close": 329.13, "volume": 83925900, "vwap_20d": null}, {"date": "2025-06-17", "open": 326.09, "high": 327.26, "low": 314.74, "close": 316.35, "volume": 88282700, "vwap_20d": null}, {"date": "2025-06-18", "open": 317.31, "high": 329.32, "low": 315.45, "close": 322.05, "volume": 95137700, "vwap_20d": null}, {"date": "2025-06-20", "open": 327.95, "high": 332.36, "low": 317.78, "close": 322.16, "volume": 108688000, "vwap_20d": null}, {"date": "2025-06-23", "open": 327.54, "high": 357.54, "low": 327.48, "close": 348.68, "volume": 190716800, "vwap_20d": null}, {"date": "2025-06-24", "open": 356.17, "high": 356.26, "low": 340.44, "close": 340.47, "volume": 114736200, "vwap_20d": null}, {"date": "2025-06-25", "open": 342.7, "high": 343.0, "low": 320.4, "close": 327.55, "volume": 119845100, "vwap_20d": null}, {"date": "2025-06-26", "open": 324.61, "high": 331.05, "low": 323.61, "close": 325.78, "volume": 80440900, "vwap_20d": null}, {"date": "2025-06-27", "open": 324.51, "high": 329.34, "low": 317.5, "close": 323.63, "volume": 89067000, "vwap_20d": null}, {"date": "2025-06-30", "open": 319.9, "high": 325.58, "low": 316.6, "close": 317.66, "volume": 76695100, "vwap_20d": null}, {"date": "2025-07-01", "open": 298.46, "high": 305.89, "low": 293.21, "close": 300.71, "volume": 145085700, "vwap_20d": null}, {"date": "2025-07-02", "open": 312.63, "high": 316.83, "low": 303.82, "close": 315.65, "volume": 119483700, "vwap_20d": null}, {"date": "2025-07-03", "open": 317.99, "high": 318.45, "low": 312.76, "close": 315.35, "volume": 58042300, "vwap_20d": null}, {"date": "2025-07-07", "open": 291.37, "high": 296.15, "low": 288.77, "close": 293.94, "volume": 131177900, "vwap_20d": null}, {"date": "2025-07-08", "open": 297.0, "high": 304.05, "low": 294.35, "close": 297.81, "volume": 103246700, "vwap_20d": null}, {"date": "2025-07-09", "open": 297.55, "high": 300.15, "low": 293.55, "close": 295.88, "volume": 75586800, "vwap_20d": null}, {"date": "2025-07-10", "open": 300.05, "high": 310.48, "low": 300.0, "close": 309.87, "volume": 104365300, "vwap_20d": null}, {"date": "2025-07-11", "open": 307.89, "high": 314.09, "low": 305.65, "close": 313.51, "volume": 79236400, "vwap_20d": 319.8812}, {"date": "2025-07-14", "open": 317.73, "high": 322.6, "low": 312.67, "close": 316.9, "volume": 78043400, "vwap_20d": 319.066}, {"date": "2025-07-15", "open": 319.68, "high": 321.2, "low": 310.5, "close": 310.78, "volume": 77556300, "vwap_20d": 318.8111}, {"date": "2025-07-16", "open": 312.8, "high": 323.5, "low": 312.62, "close": 321.67, "volume": 97284800, "vwap_20d": 318.3096}, {"date": "2025-07-17", "open": 323.15, "high": 324.34, "low": 317.06, "close": 319.41, "volume": 73922900, "vwap_20d": 317.9166}, {"date": "2025-07-18", "open": 321.66, "high": 330.9, "low": 321.42, "close": 329.65, "volume": 94255000, "vwap_20d": 317.9372}, {"date": "2025-07-21", "open": 334.4, "high": 338.0, "low": 326.88, "close": 328.49, "volume": 75768800, "vwap_20d": 318.1713}, {"date": "2025-07-22", "open": 329.74, "high": 335.41, "low": 321.55, "close": 332.11, "volume": 77370400, "vwap_20d": 318.3411}, {"date": "2025-07-23", "open": 330.9, "high": 336.2, "low": 328.67, "close": 332.56, "volume": 92553800, "vwap_20d": 316.21}, {"date": "2025-07-24", "open": 310.0, "high": 310.15, "low": 300.41, "close": 305.3, "volume": 156966000, "vwap_20d": 315.1778}, {"date": "2025-07-25", "open": 308.74, "high": 323.63, "low": 308.01, "close": 316.06, "volume": 148227000, "vwap_20d": 313.4002}, {"date": "2025-07-28", "open": 318.45, "high": 330.49, "low": 315.69, "close": 325.59, "volume": 112673800, "vwap_20d": 313.0377}, {"date": "2025-07-29", "open": 325.55, "high": 326.25, "low": 318.25, "close": 321.2, "volume": 87358900, "vwap_20d": 313.1871}, {"date": "2025-07-30", "open": 322.18, "high": 324.45, "low": 311.62, "close": 319.04, "volume": 83931900, "vwap_20d": 313.3092}, {"date": "2025-07-31", "open": 319.61, "high": 321.37, "low": 306.1, "close": 308.27, "volume": 85270900, "vwap_20d": 314.5362}, {"date": "2025-08-01", "open": 306.21, "high": 309.31, "low": 297.82, "close": 302.63, "volume": 89121400, "vwap_20d": 314.5719}, {"date": "2025-08-04", "open": 309.08, "high": 312.12, "low": 303.0, "close": 309.26, "volume": 78683900, "vwap_20d": 314.0193}, {"date": "2025-08-05", "open": 308.95, "high": 312.45, "low": 305.5, "close": 308.72, "volume": 57961300, "vwap_20d": 315.2544}, {"date": "2025-08-06", "open": 307.89, "high": 320.47, "low": 306.93, "close": 319.91, "volume": 78523600, "vwap_20d": 315.9814}, {"date": "2025-08-07", "open": 319.79, "high": 322.4, "low": 316.16, "close": 322.27, "volume": 66658700, "vwap_20d": 316.7815}, {"date": "2025-08-08", "open": 321.43, "high": 335.15, "low": 320.98, "close": 329.65, "volume": 91200300, "vwap_20d": 317.4939}, {"date": "2025-08-11", "open": 335.0, "high": 346.64, "low": 334.15, "close": 339.03, "volume": 105320200, "vwap_20d": 318.3349}, {"date": "2025-08-12", "open": 345.0, "high": 345.26, "low": 332.94, "close": 340.84, "volume": 80522100, "vwap_20d": 319.6188}, {"date": "2025-08-13", "open": 341.5, "high": 348.98, "low": 338.2, "close": 339.38, "volume": 67838900, "vwap_20d": 320.7269}, {"date": "2025-08-14", "open": 335.76, "high": 340.47, "low": 330.4, "close": 335.58, "volume": 75000700, "vwap_20d": 321.62}, {"date": "2025-08-15", "open": 337.66, "high": 339.3, "low": 327.02, "close": 330.56, "volume": 74319800, "vwap_20d": 322.2513}, {"date": "2025-08-18", "open": 329.62, "high": 336.27, "low": 329.59, "close": 335.16, "volume": 56956600, "vwap_20d": 322.4016}, {"date": "2025-08-19", "open": 335.79, "high": 340.55, "low": 327.85, "close": 329.31, "volume": 75956000, "vwap_20d": 322.3909}, {"date": "2025-08-20", "open": 329.22, "high": 331.37, "low": 314.6, "close": 323.9, "volume": 77481800, "vwap_20d": 322.509}, {"date": "2025-08-21", "open": 322.08, "high": 324.9, "low": 318.68, "close": 320.11, "volume": 55744400, "vwap_20d": 322.0164}, {"date": "2025-08-22", "open": 321.66, "high": 340.25, "low": 319.69, "close": 340.01, "volume": 94016300, "vwap_20d": 323.5822}, {"date": "2025-08-25", "open": 338.9, "high": 349.53, "low": 335.03, "close": 346.6, "volume": 86670000, "vwap_20d": 324.8693}, {"date": "2025-08-26", "open": 344.93, "high": 351.9, "low": 343.72, "close": 351.67, "volume": 76651600, "vwap_20d": 325.9577}, {"date": "2025-08-27", "open": 351.94, "high": 355.39, "low": 349.16, "close": 349.6, "volume": 65519000, "vwap_20d": 327.3282}, {"date": "2025-08-28", "open": 350.91, "high": 353.55, "low": 340.26, "close": 345.98, "volume": 67903200, "vwap_20d": 328.8591}, {"date": "2025-08-29", "open": 347.23, "high": 348.75, "low": 331.7, "close": 333.87, "volume": 81145700, "vwap_20d": 330.5982}, {"date": "2025-09-02", "open": 328.23, "high": 333.33, "low": 325.6, "close": 329.36, "volume": 58392000, "vwap_20d": 332.604}, {"date": "2025-09-03", "open": 335.2, "high": 343.33, "low": 328.51, "close": 334.09, "volume": 88733300, "vwap_20d": 333.7704}, {"date": "2025-09-04", "open": 336.15, "high": 338.89, "low": 331.48, "close": 338.53, "volume": 60711000, "vwap_20d": 334.8041}, {"date": "2025-09-05", "open": 348.0, "high": 355.87, "low": 344.68, "close": 350.84, "volume": 108989800, "vwap_20d": 335.864}, {"date": "2025-09-08", "open": 354.64, "high": 358.44, "low": 344.84, "close": 346.4, "volume": 75208300, "vwap_20d": 337.5515}, {"date": "2025-09-09", "open": 348.44, "high": 350.77, "low": 343.82, "close": 346.97, "volume": 53816000, "vwap_20d": 338.6994}, {"date": "2025-09-10", "open": 350.55, "high": 356.33, "low": 346.07, "close": 347.79, "volume": 72121700, "vwap_20d": 338.9195}, {"date": "2025-09-11", "open": 350.17, "high": 368.99, "low": 347.6, "close": 368.81, "volume": 103756000, "vwap_20d": 339.4233}, {"date": "2025-09-12", "open": 370.94, "high": 396.69, "low": 370.24, "close": 395.94, "volume": 168156400, "vwap_20d": 340.7771}, {"date": "2025-09-15", "open": 423.13, "high": 425.7, "low": 402.43, "close": 410.04, "volume": 163823700, "vwap_20d": 345.8645}, {"date": "2025-09-16", "open": 414.5, "high": 423.25, "low": 411.43, "close": 421.62, "volume": 104285700, "vwap_20d": 353.0439}, {"date": "2025-09-17", "open": 415.75, "high": 428.31, "low": 409.67, "close": 425.86, "volume": 106133500, "vwap_20d": 357.602}, {"date": "2025-09-18", "open": 428.87, "high": 432.22, "low": 416.56, "close": 416.85, "volume": 90454500, "vwap_20d": 362.5025}, {"date": "2025-09-19", "open": 421.82, "high": 429.47, "low": 421.72, "close": 426.07, "volume": 93131000, "vwap_20d": 367.2216}, {"date": "2025-09-22", "open": 431.11, "high": 444.98, "low": 429.13, "close": 434.21, "volume": 97108800, "vwap_20d": 371.5517}, {"date": "2025-09-23", "open": 439.88, "high": 440.97, "low": 423.72, "close": 425.85, "volume": 83422700, "vwap_20d": 376.9622}, {"date": "2025-09-24", "open": 429.83, "high": 444.21, "low": 429.03, "close": 442.79, "volume": 93133600, "vwap_20d": 380.9854}, {"date": "2025-09-25", "open": 435.24, "high": 435.35, "low": 419.08, "close": 423.39, "volume": 96746400, "vwap_20d": 385.2449}, {"date": "2025-09-26", "open": 428.3, "high": 440.47, "low": 421.02, "close": 440.4, "volume": 101628200, "vwap_20d": 388.5056}, {"date": "2025-09-29", "open": 444.35, "high": 450.98, "low": 439.5, "close": 443.21, "volume": 79491500, "vwap_20d": 392.4272}, {"date": "2025-09-30", "open": 441.52, "high": 445.0, "low": 433.12, "close": 444.72, "volume": 74358000, "vwap_20d": 396.9794}, {"date": "2025-10-01", "open": 443.8, "high": 462.29, "low": 440.75, "close": 459.46, "volume": 98122300, "vwap_20d": 400.8287}, {"date": "2025-10-02", "open": 470.54, "high": 470.75, "low": 435.57, "close": 436.0, "volume": 137009000, "vwap_20d": 406.5152}, {"date": "2025-10-03", "open": 443.29, "high": 446.77, "low": 416.58, "close": 429.83, "volume": 133188200, "vwap_20d": 411.4475}, {"date": "2025-10-06", "open": 440.75, "high": 453.55, "low": 436.69, "close": 453.25, "volume": 85324900, "vwap_20d": 416.0131}, {"date": "2025-10-07", "open": 447.82, "high": 452.68, "low": 432.45, "close": 433.09, "volume": 102296100, "vwap_20d": 419.7848}, {"date": "2025-10-08", "open": 437.57, "high": 441.33, "low": 425.23, "close": 438.69, "volume": 71192100, "vwap_20d": 422.609}, {"date": "2025-10-09", "open": 431.81, "high": 436.35, "low": 426.18, "close": 435.54, "volume": 69339900, "vwap_20d": 425.5713}, {"date": "2025-10-10", "open": 436.54, "high": 443.13, "low": 411.45, "close": 413.49, "volume": 112107900, "vwap_20d": 429.1016}, {"date": "2025-10-13", "open": 423.53, "high": 436.89, "low": 419.7, "close": 435.9, "volume": 79552800, "vwap_20d": 432.2739}, {"date": "2025-10-14", "open": 426.79, "high": 434.2, "low": 417.86, "close": 429.24, "volume": 72669400, "vwap_20d": 433.9035}, {"date": "2025-10-15", "open": 434.9, "high": 440.51, "low": 426.33, "close": 435.15, "volume": 71558200, "vwap_20d": 434.4809}, {"date": "2025-10-16", "open": 434.73, "high": 439.35, "low": 421.31, "close": 428.75, "volume": 77189900, "vwap_20d": 435.2468}, {"date": "2025-10-17", "open": 425.5, "high": 441.46, "low": 423.6, "close": 439.31, "volume": 89331600, "vwap_20d": 435.6765}, {"date": "2025-10-20", "open": 443.87, "high": 449.8, "low": 440.61, "close": 447.43, "volume": 63719000, "vwap_20d": 436.1397}, {"date": "2025-10-21", "open": 445.76, "high": 449.3, "low": 442.05, "close": 442.6, "volume": 54412200, "vwap_20d": 436.4903}, {"date": "2025-10-22", "open": 443.45, "high": 445.54, "low": 429.0, "close": 438.97, "volume": 84023500, "vwap_20d": 437.0412}, {"date": "2025-10-23", "open": 420.0, "high": 449.4, "low": 413.9, "close": 448.98, "volume": 126709800, "vwap_20d": 436.9924}, {"date": "2025-10-24", "open": 446.83, "high": 451.68, "low": 430.17, "close": 433.72, "volume": 94727800, "vwap_20d": 437.6259}, {"date": "2025-10-27", "open": 439.98, "high": 460.16, "low": 438.69, "close": 452.42, "volume": 105867500, "vwap_20d": 437.8833}, {"date": "2025-10-28", "open": 454.78, "high": 467.0, "low": 451.6, "close": 460.55, "volume": 80185700, "vwap_20d": 438.3251}, {"date": "2025-10-29", "open": 462.5, "high": 465.7, "low": 452.65, "close": 461.51, "volume": 67983500, "vwap_20d": 439.1649}, {"date": "2025-10-30", "open": 451.05, "high": 455.06, "low": 439.61, "close": 440.1, "volume": 72447900, "vwap_20d": 439.1326}, {"date": "2025-10-31", "open": 446.75, "high": 458.0, "low": 443.69, "close": 456.56, "volume": 83135800, "vwap_20d": 438.7045}, {"date": "2025-11-03", "open": 455.99, "high": 474.07, "low": 453.8, "close": 468.37, "volume": 84595200, "vwap_20d": 440.0103}, {"date": "2025-11-04", "open": 454.46, "high": 460.22, "low": 443.6, "close": 444.26, "volume": 87756600, "vwap_20d": 440.8952}, {"date": "2025-11-05", "open": 452.05, "high": 466.33, "low": 440.71, "close": 462.07, "volume": 85573000, "vwap_20d": 441.4382}, {"date": "2025-11-06", "open": 461.96, "high": 467.45, "low": 435.09, "close": 445.91, "volume": 109622900, "vwap_20d": 442.476}, {"date": "2025-11-07", "open": 437.92, "high": 439.36, "low": 421.88, "close": 429.52, "volume": 103471500, "vwap_20d": 443.3235}, {"date": "2025-11-10", "open": 439.6, "high": 449.67, "low": 433.36, "close": 445.23, "volume": 76515900, "vwap_20d": 443.8136}, {"date": "2025-11-11", "open": 439.4, "high": 442.49, "low": 432.36, "close": 439.62, "volume": 60533200, "vwap_20d": 444.3762}, {"date": "2025-11-12", "open": 442.15, "high": 442.33, "low": 426.56, "close": 430.6, "volume": 58513500, "vwap_20d": 444.8993}, {"date": "2025-11-13", "open": 423.13, "high": 424.5, "low": 396.34, "close": 401.99, "volume": 118948000, "vwap_20d": 444.9554}, {"date": "2025-11-14", "open": 386.3, "high": 412.19, "low": 382.78, "close": 404.35, "volume": 105506700, "vwap_20d": 443.0892}, {"date": "2025-11-17", "open": 398.74, "high": 423.96, "low": 398.74, "close": 408.92, "volume": 102214300, "vwap_20d": 440.8187}, {"date": "2025-11-18", "open": 405.38, "high": 408.9, "low": 393.71, "close": 401.25, "volume": 80688600, "vwap_20d": 438.8806}, {"date": "2025-11-19", "open": 406.18, "high": 411.78, "low": 398.5, "close": 403.99, "volume": 72047700, "vwap_20d": 437.0134}, {"date": "2025-11-20", "open": 414.63, "high": 428.94, "low": 394.74, "close": 395.23, "volume": 113548800, "vwap_20d": 435.6666}, {"date": "2025-11-21", "open": 402.32, "high": 402.8, "low": 383.76, "close": 391.09, "volume": 100460600, "vwap_20d": 433.6546}, {"date": "2025-11-24", "open": 402.17, "high": 421.72, "low": 401.09, "close": 417.78, "volume": 96806400, "vwap_20d": 431.0721}, {"date": "2025-11-25", "open": 414.42, "high": 420.48, "low": 405.95, "close": 419.4, "volume": 71915600, "vwap_20d": 428.9439}, {"date": "2025-11-26", "open": 423.95, "high": 426.94, "low": 416.89, "close": 426.58, "volume": 63463000, "vwap_20d": 426.9748}, {"date": "2025-11-28", "open": 426.59, "high": 432.93, "low": 426.2, "close": 430.17, "volume": 36252900, "vwap_20d": 425.564}, {"date": "2025-12-01", "open": 425.32, "high": 433.66, "low": 425.29, "close": 430.14, "volume": 57463600, "vwap_20d": 424.844}, {"date": "2025-12-02", "open": 430.81, "high": 436.8, "low": 422.12, "close": 429.24, "volume": 69336600, "vwap_20d": 423.6397}, {"date": "2025-12-03", "open": 432.1, "high": 447.92, "low": 431.11, "close": 446.74, "volume": 87483000, "vwap_20d": 421.7334}, {"date": "2025-12-04", "open": 449.94, "high": 454.63, "low": 445.39, "close": 454.53, "volume": 71906500, "vwap_20d": 421.3394}, {"date": "2025-12-05", "open": 453.03, "high": 458.87, "low": 451.66, "close": 455.0, "volume": 56427500, "vwap_20d": 420.8713}, {"date": "2025-12-08", "open": 447.45, "high": 449.75, "low": 435.25, "close": 439.58, "volume": 69165800, "vwap_20d": 420.1362}, {"date": "2025-12-09", "open": 437.54, "high": 452.39, "low": 435.7, "close": 445.17, "volume": 62367400, "vwap_20d": 420.4119}, {"date": "2025-12-10", "open": 446.07, "high": 456.88, "low": 443.61, "close": 451.45, "volume": 63257500, "vwap_20d": 420.2754}, {"date": "2025-12-11", "open": 448.95, "high": 449.27, "low": 440.33, "close": 446.89, "volume": 55979500, "vwap_20d": 420.812}, {"date": "2025-12-12", "open": 448.09, "high": 463.01, "low": 441.67, "close": 458.96, "volume": 95656700, "vwap_20d": 421.2359}, {"date": "2025-12-15", "open": 469.44, "high": 481.77, "low": 467.66, "close": 475.31, "volume": 114542200, "vwap_20d": 424.3263}, {"date": "2025-12-16", "open": 472.21, "high": 491.5, "low": 465.83, "close": 489.88, "volume": 107608100, "vwap_20d": 429.7945}, {"date": "2025-12-17", "open": 488.22, "high": 495.28, "low": 466.2, "close": 467.26, "volume": 106490400, "vwap_20d": 434.6961}, {"date": "2025-12-18", "open": 478.16, "high": 490.86, "low": 473.12, "close": 483.37, "volume": 95168400, "vwap_20d": 439.2843}, {"date": "2025-12-19", "open": 488.12, "high": 490.49, "low": 474.72, "close": 481.2, "volume": 103305400, "vwap_20d": 443.4188}, {"date": "2025-12-22", "open": 489.88, "high": 498.83, "low": 485.33, "close": 488.73, "volume": 86916100, "vwap_20d": 448.594}, {"date": "2025-12-23", "open": 489.4, "high": 491.97, "low": 482.84, "close": 485.56, "volume": 58223600, "vwap_20d": 454.476}, {"date": "2025-12-24", "open": 488.48, "high": 490.9, "low": 476.8, "close": 485.4, "volume": 41285400, "vwap_20d": 458.291}, {"date": "2025-12-26", "open": 485.23, "high": 489.09, "low": 473.82, "close": 475.19, "volume": 58780700, "vwap_20d": 461.0781}, {"date": "2025-12-29", "open": 469.0, "high": 469.4, "low": 459.0, "close": 459.64, "volume": 66263000, "vwap_20d": 463.3771}, {"date": "2025-12-30", "open": 461.09, "high": 463.12, "low": 453.83, "close": 454.43, "volume": 59238500, "vwap_20d": 464.1446}, {"date": "2025-12-31", "open": 456.1, "high": 456.55, "low": 449.3, "close": 449.72, "volume": 49078000, "vwap_20d": 465.1677}, {"date": "2026-01-02", "open": 457.8, "high": 458.34, "low": 435.3, "close": 438.07, "volume": 85535400, "vwap_20d": 466.38}, {"date": "2026-01-05", "open": 447.99, "high": 457.55, "low": 444.57, "close": 451.67, "volume": 67940800, "vwap_20d": 466.5835}, {"date": "2026-01-06", "open": 446.38, "high": 448.25, "low": 428.78, "close": 432.96, "volume": 89093800, "vwap_20d": 466.6118}, {"date": "2026-01-07", "open": 435.9, "high": 438.37, "low": 431.29, "close": 431.41, "volume": 59828800, "vwap_20d": 465.2635}, {"date": "2026-01-08", "open": 427.89, "high": 436.89, "low": 424.37, "close": 435.8, "volume": 57041100, "vwap_20d": 465.1033}, {"date": "2026-01-09", "open": 435.95, "high": 449.05, "low": 430.39, "close": 445.01, "volume": 67331500, "vwap_20d": 464.6948}, {"date": "2026-01-12", "open": 441.23, "high": 454.3, "low": 438.0, "close": 448.96, "volume": 61649600, "vwap_20d": 464.2528}, {"date": "2026-01-13", "open": 450.2, "high": 451.81, "low": 443.95, "close": 447.2, "volume": 53719200, "vwap_20d": 464.2478}, {"date": "2026-01-14", "open": 442.81, "high": 443.91, "low": 434.22, "close": 439.2, "volume": 57259500, "vwap_20d": 464.2743}, {"date": "2026-01-15", "open": 441.13, "high": 445.36, "low": 437.65, "close": 438.57, "volume": 49465800, "vwap_20d": 462.4167}, {"date": "2026-01-16", "open": 439.5, "high": 447.25, "low": 435.26, "close": 437.5, "volume": 60220600, "vwap_20d": 460.0716}, {"date": "2026-01-20", "open": 429.36, "high": 430.73, "low": 417.44, "close": 419.25, "volume": 63187300, "vwap_20d": 457.8651}, {"date": "2026-01-21", "open": 421.66, "high": 438.2, "low": 419.62, "close": 431.44, "volume": 68124000, "vwap_20d": 454.3389}, {"date": "2026-01-22", "open": 435.16, "high": 449.5, "low": 432.63, "close": 449.36, "volume": 71546700, "vwap_20d": 450.7335}, {"date": "2026-01-23", "open": 447.43, "high": 452.43, "low": 444.04, "close": 449.06, "volume": 56771400, "vwap_20d": 447.5396}, {"date": "2026-01-26", "open": 445.0, "high": 445.04, "low": 434.28, "close": 435.2, "volume": 49397400, "vwap_20d": 445.7412}, {"date": "2026-01-27", "open": 437.41, "high": 437.52, "low": 430.69, "close": 430.9, "volume": 37733100, "vwap_20d": 444.163}, {"date": "2026-01-28", "open": 431.91, "high": 438.26, "low": 430.1, "close": 431.46, "volume": 54857400, "vwap_20d": 442.1443}, {"date": "2026-01-29", "open": 437.8, "high": 440.23, "low": 414.62, "close": 416.56, "volume": 81686100, "vwap_20d": 440.6286}, {"date": "2026-01-30", "open": 425.35, "high": 439.88, "low": 422.7, "close": 430.41, "volume": 82626100, "vwap_20d": 438.7651}, {"date": "2026-02-02", "open": 421.29, "high": 427.15, "low": 414.5, "close": 421.81, "volume": 58739500, "vwap_20d": 437.7578}, {"date": "2026-02-03", "open": 424.27, "high": 428.56, "low": 413.69, "close": 421.96, "volume": 56886500, "vwap_20d": 436.56}, {"date": "2026-02-04", "open": 420.46, "high": 423.9, "low": 399.18, "close": 406.01, "volume": 74606900, "vwap_20d": 435.0364}, {"date": "2026-02-05", "open": 397.02, "high": 402.1, "low": 387.53, "close": 397.21, "volume": 72819800, "vwap_20d": 433.3442}, {"date": "2026-02-06", "open": 400.87, "high": 414.55, "low": 397.75, "close": 411.11, "volume": 62677100, "vwap_20d": 431.073}, {"date": "2026-02-09", "open": 409.91, "high": 421.25, "low": 407.29, "close": 417.32, "volume": 54484300, "vwap_20d": 429.8392}, {"date": "2026-02-10", "open": 418.08, "high": 427.25, "low": 417.0, "close": 425.21, "volume": 64450200, "vwap_20d": 428.5576}, {"date": "2026-02-11", "open": 427.96, "high": 436.35, "low": 420.03, "close": 428.27, "volume": 57362000, "vwap_20d": 427.3531}, {"date": "2026-02-12", "open": 430.3, "high": 436.23, "low": 414.0, "close": 417.07, "volume": 61933400, "vwap_20d": 426.5111}, {"date": "2026-02-13", "open": 414.31, "high": 424.06, "low": 410.88, "close": 417.44, "volume": 51434100, "vwap_20d": 425.7254}, {"date": "2026-02-17", "open": 412.36, "high": 413.72, "low": 400.51, "close": 410.63, "volume": 59678800, "vwap_20d": 424.7928}, {"date": "2026-02-18", "open": 411.11, "high": 416.9, "low": 409.58, "close": 411.32, "volume": 45921400, "vwap_20d": 423.261}, {"date": "2026-02-19", "open": 407.25, "high": 415.25, "low": 404.11, "close": 411.71, "volume": 51019600, "vwap_20d": 422.9007}, {"date": "2026-02-20", "open": 408.3, "high": 414.7, "low": 405.5, "close": 411.82, "volume": 57912200, "vwap_20d": 421.9834}, {"date": "2026-02-23", "open": 407.29, "high": 407.7, "low": 394.04, "close": 399.83, "volume": 69680000, "vwap_20d": 420.136}, {"date": "2026-02-24", "open": 399.5, "high": 410.82, "low": 397.64, "close": 409.38, "volume": 58579500, "vwap_20d": 417.67}, {"date": "2026-02-25", "open": 412.15, "high": 420.34, "low": 412.15, "close": 417.4, "volume": 54809700, "vwap_20d": 416.2557}, {"date": "2026-02-26", "open": 414.42, "high": 416.81, "low": 403.66, "close": 408.58, "volume": 53602500, "vwap_20d": 415.7584}, {"date": "2026-02-27", "open": 402.94, "high": 407.12, "low": 398.11, "close": 402.51, "volume": 56890100, "vwap_20d": 414.7133}, {"date": "2026-03-02", "open": 390.6, "high": 404.54, "low": 388.25, "close": 403.32, "volume": 55088300, "vwap_20d": 413.5289}, {"date": "2026-03-03", "open": 395.09, "high": 396.34, "low": 385.39, "close": 392.43, "volume": 62617300, "vwap_20d": 411.6132}, {"date": "2026-03-04", "open": 397.85, "high": 408.33, "low": 394.58, "close": 405.94, "volume": 68305500, "vwap_20d": 410.0657}, {"date": "2026-03-05", "open": 401.57, "high": 408.62, "low": 399.42, "close": 405.55, "volume": 51925900, "vwap_20d": 409.1183}, {"date": "2026-03-06", "open": 398.09, "high": 402.35, "low": 394.21, "close": 396.73, "volume": 64054600, "vwap_20d": 408.878}, {"date": "2026-03-09", "open": 390.05, "high": 401.59, "low": 381.4, "close": 398.68, "volume": 67018900, "vwap_20d": 409.095}, {"date": "2026-03-10", "open": 402.22, "high": 406.59, "low": 398.19, "close": 399.24, "volume": 59258700, "vwap_20d": 408.2914}, {"date": "2026-03-11", "open": 402.28, "high": 416.38, "low": 402.15, "close": 407.82, "volume": 62559900, "vwap_20d": 407.6145}, {"date": "2026-03-12", "open": 405.18, "high": 406.5, "low": 394.65, "close": 395.01, "volume": 60973800, "vwap_20d": 406.8208}, {"date": "2026-03-13", "open": 399.17, "high": 400.2, "low": 389.95, "close": 391.2, "volume": 58504100, "vwap_20d": 405.3639}, {"date": "2026-03-16", "open": 396.22, "high": 403.73, "low": 394.42, "close": 395.56, "volume": 58068300, "vwap_20d": 403.8788}, {"date": "2026-03-17", "open": 395.69, "high": 400.12, "low": 393.0, "close": 399.27, "volume": 46890500, "vwap_20d": 402.99}, {"date": "2026-03-18", "open": 399.0, "high": 403.07, "low": 392.31, "close": 392.78, "volume": 50853100, "vwap_20d": 402.4957}, {"date": "2026-03-19", "open": 387.27, "high": 387.27, "low": 378.73, "close": 380.3, "volume": 67078300, "vwap_20d": 401.8183}, {"date": "2026-03-20", "open": 379.85, "high": 379.89, "low": 364.46, "close": 367.96, "volume": 78628600, "vwap_20d": 400.3439}, {"date": "2026-03-23", "open": 373.09, "high": 385.33, "low": 372.73, "close": 380.85, "volume": 74606000, "vwap_20d": 397.9311}, {"date": "2026-03-24", "open": 376.56, "high": 387.48, "low": 376.31, "close": 383.03, "volume": 60004900, "vwap_20d": 396.6541}, {"date": "2026-03-25", "open": 389.99, "high": 396.23, "low": 385.01, "close": 385.95, "volume": 55157300, "vwap_20d": 395.4928}, {"date": "2026-03-26", "open": 381.6, "high": 384.44, "low": 371.87, "close": 372.11, "volume": 55522900, "vwap_20d": 394.2407}, {"date": "2026-03-27", "open": 369.69, "high": 369.86, "low": 359.47, "close": 361.83, "volume": 61869200, "vwap_20d": 392.7344}], "volume_profile": {"10d": {"buckets": [{"price": 360.5765, "volume": 11143862.09}, {"price": 362.7895, "volume": 22788486.87}, {"price": 365.0025, "volume": 25430335.84}, {"price": 367.2155, "volume": 20983355.54}, {"price": 369.4285, "volume": 20638881.71}, {"price": 371.6415, "volume": 24226174.92}, {"price": 373.8545, "volume": 29171960.07}, {"price": 376.0675, "volume": 35736790.45}, {"price": 378.2805, "volume": 46571666.8}, {"price": 380.4935, "volume": 63423401.87}, {"price": 382.7065, "volume": 61629664.41}, {"price": 384.9195, "volume": 34999614.73}, {"price": 387.1325, "volume": 20934711.19}, {"price": 389.3455, "volume": 19084437.56}, {"price": 391.5585, "volume": 16553641.79}, {"price": 393.7715, "volume": 23200008.81}, {"price": 395.9845, "volume": 49764204.12}, {"price": 398.1975, "volume": 55570474.68}, {"price": 400.4105, "volume": 22801726.71}, {"price": 402.6235, "volume": 4025699.86}], "vwap": 382.453}, "20d": {"buckets": [{"price": 360.8928, "volume": 16487221.59}, {"price": 363.7383, "volume": 32640281.74}, {"price": 366.5838, "volume": 28435676.62}, {"price": 369.4293, "volume": 26527175.51}, {"price": 372.2748, "volume": 32805341.21}, {"price": 375.1203, "volume": 42019817.71}, {"price": 377.9658, "volume": 57373831.55}, {"price": 380.8113, "volume": 84338551.01}, {"price": 383.6568, "volume": 67984024.02}, {"price": 386.5023, "volume": 40436904.76}, {"price": 389.3478, "volume": 61328955.06}, {"price": 392.1933, "volume": 89311410.47}, {"price": 395.0388, "volume": 133321911.6}, {"price": 397.8843, "volume": 183975801.1}, {"price": 400.7298, "volume": 132193664.24}, {"price": 403.5753, "volume": 89403511.34}, {"price": 406.4208, "volume": 53877256.78}, {"price": 409.2663, "volume": 28052985.28}, {"price": 412.1118, "volume": 13921101.67}, {"price": 414.9573, "volume": 4550676.75}], "vwap": 390.7903}, "50d": {"buckets": [{"price": 361.794, "volume": 37210594.78}, {"price": 366.442, "volume": 46815285.3}, {"price": 371.09, "volume": 48644003.16}, {"price": 375.738, "volume": 72733541.97}, {"price": 380.386, "volume": 133409493.66}, {"price": 385.034, "volume": 80296313.79}, {"price": 389.682, "volume": 116209967.85}, {"price": 394.33, "volume": 235767909.53}, {"price": 398.978, "volume": 364418213.12}, {"price": 403.626, "volume": 292876583.81}, {"price": 408.274, "volume": 260312522.18}, {"price": 412.922, "volume": 236545894.08}, {"price": 417.57, "volume": 196782254.7}, {"price": 422.218, "volume": 221541413.94}, {"price": 426.866, "volume": 154625841.61}, {"price": 431.514, "volume": 166133411.27}, {"price": 436.162, "volume": 115275753.23}, {"price": 440.81, "volume": 131431066.51}, {"price": 445.458, "volume": 57606437.7}, {"price": 450.106, "volume": 49453097.81}], "vwap": 408.5419}, "100d": {"buckets": [{"price": 362.954, "volume": 65606788.8}, {"price": 369.922, "volume": 66017612.4}, {"price": 376.89, "volume": 123276479.03}, {"price": 383.858, "volume": 175843775.91}, {"price": 390.826, "volume": 297654361.16}, {"price": 397.794, "volume": 668581057.85}, {"price": 404.762, "volume": 668394434.41}, {"price": 411.73, "volume": 589573913.44}, {"price": 418.698, "volume": 437167351.16}, {"price": 425.666, "volume": 443443056.85}, {"price": 432.634, "volume": 611849296.82}, {"price": 439.602, "volume": 620362431.97}, {"price": 446.57, "volume": 599823697.73}, {"price": 453.538, "volume": 470744578.55}, {"price": 460.506, "volume": 194252399.28}, {"price": 467.474, "volume": 103495673.31}, {"price": 474.442, "volume": 201946858.43}, {"price": 481.41, "volume": 289927013.6}, {"price": 488.378, "volume": 213713120.91}, {"price": 495.346, "volume": 40193698.38}], "vwap": 428.0606}, "200d": {"buckets": [{"price": 294.0215, "volume": 330288024.07}, {"price": 304.5245, "volume": 637375432.01}, {"price": 315.0275, "volume": 1107185778.74}, {"price": 325.5305, "volume": 1644782237.52}, {"price": 336.0335, "volume": 1026522315.68}, {"price": 346.5365, "volume": 866548232.63}, {"price": 357.0395, "volume": 132048933.94}, {"price": 367.5425, "volume": 168982208.57}, {"price": 378.0455, "volume": 293617595.38}, {"price": 388.5485, "volume": 410640671.35}, {"price": 399.0515, "volume": 1054726920.23}, {"price": 409.5545, "volume": 1044742399.22}, {"price": 420.0575, "volume": 1202564456.42}, {"price": 430.5605, "volume": 1808894271.3}, {"price": 441.0635, "volume": 1851725541.89}, {"price": 451.5665, "volume": 1232004258.61}, {"price": 462.0695, "volume": 445959321.38}, {"price": 472.5725, "volume": 239490837.62}, {"price": 483.0755, "volume": 446284382.74}, {"price": 493.5785, "volume": 108023680.7}], "vwap": 392.118}}, "sci_matrix": {"cells": [{"endpoint": 10, "start": 20, "slope": -8.33732, "above": false}, {"endpoint": 10, "start": 30, "slope": -7.044787, "above": false}, {"endpoint": 10, "start": 40, "slope": -6.550041, "above": false}, {"endpoint": 10, "start": 50, "slope": -6.522237, "above": false}, {"endpoint": 10, "start": 60, "slope": -6.400024, "above": false}, {"endpoint": 10, "start": 70, "slope": -7.24397, "above": false}, {"endpoint": 10, "start": 80, "slope": -6.715431, "above": false}, {"endpoint": 10, "start": 90, "slope": -5.561368, "above": false}, {"endpoint": 10, "start": 100, "slope": -5.067508, "above": false}, {"endpoint": 10, "start": 110, "slope": -4.762157, "above": false}, {"endpoint": 20, "start": 30, "slope": -5.752254, "above": false}, {"endpoint": 20, "start": 40, "slope": -5.656402, "above": false}, {"endpoint": 20, "start": 50, "slope": -5.91721, "above": false}, {"endpoint": 20, "start": 60, "slope": -5.9157, "above": false}, {"endpoint": 20, "start": 70, "slope": -7.0253, "above": false}, {"endpoint": 20, "start": 80, "slope": -6.445116, "above": false}, {"endpoint": 20, "start": 90, "slope": -5.164803, "above": false}, {"endpoint": 20, "start": 100, "slope": -4.658781, "above": false}, {"endpoint": 20, "start": 110, "slope": -4.364917, "above": false}, {"endpoint": 20, "start": 120, "slope": -3.959872, "above": false}, {"endpoint": 30, "start": 40, "slope": -5.560549, "above": false}, {"endpoint": 30, "start": 50, "slope": -5.999687, "above": false}, {"endpoint": 30, "start": 60, "slope": -5.970182, "above": false}, {"endpoint": 30, "start": 70, "slope": -7.343562, "above": false}, {"endpoint": 30, "start": 80, "slope": -6.583688, "above": false}, {"endpoint": 30, "start": 90, "slope": -5.066895, "above": false}, {"endpoint": 30, "start": 100, "slope": -4.502571, "above": false}, {"endpoint": 30, "start": 110, "slope": -4.1915, "above": false}, {"endpoint": 30, "start": 120, "slope": -3.760718, "above": false}, {"endpoint": 30, "start": 130, "slope": -3.467759, "above": false}, {"endpoint": 40, "start": 50, "slope": -6.438826, "above": false}, {"endpoint": 40, "start": 60, "slope": -6.174999, "above": false}, {"endpoint": 40, "start": 70, "slope": -7.9379, "above": false}, {"endpoint": 40, "start": 80, "slope": -6.839473, "above": false}, {"endpoint": 40, "start": 90, "slope": -4.968164, "above": false}, {"endpoint": 40, "start": 100, "slope": -4.326241, "above": false}, {"endpoint": 40, "start": 110, "slope": -3.995921, "above": false}, {"endpoint": 40, "start": 120, "slope": -3.535739, "above": false}, {"endpoint": 40, "start": 130, "slope": -3.235227, "above": false}, {"endpoint": 40, "start": 140, "slope": -2.54824, "above": false}, {"endpoint": 50, "start": 60, "slope": -5.911171, "above": false}, {"endpoint": 50, "start": 70, "slope": -8.687437, "above": false}, {"endpoint": 50, "start": 80, "slope": -6.973022, "above": false}, {"endpoint": 50, "start": 90, "slope": -4.600499, "above": false}, {"endpoint": 50, "start": 100, "slope": -3.903724, "above": false}, {"endpoint": 50, "start": 110, "slope": -3.58877, "above": false}, {"endpoint": 50, "start": 120, "slope": -3.121012, "above": false}, {"endpoint": 50, "start": 130, "slope": -2.834777, "above": false}, {"endpoint": 50, "start": 140, "slope": -2.115952, "above": false}, {"endpoint": 50, "start": 150, "slope": -1.308127, "above": false}, {"endpoint": 60, "start": 70, "slope": -11.463702, "above": false}, {"endpoint": 60, "start": 80, "slope": -7.503948, "above": false}, {"endpoint": 60, "start": 90, "slope": -4.163608, "above": false}, {"endpoint": 60, "start": 100, "slope": -3.401863, "above": false}, {"endpoint": 60, "start": 110, "slope": -3.12429, "above": false}, {"endpoint": 60, "start": 120, "slope": -2.655986, "above": false}, {"endpoint": 60, "start": 130, "slope": -2.395292, "above": false}, {"endpoint": 60, "start": 140, "slope": -1.64155, "above": false}, {"endpoint": 60, "start": 150, "slope": -0.796678, "above": false}, {"endpoint": 60, "start": 160, "slope": -0.158107, "above": false}, {"endpoint": 70, "start": 80, "slope": -3.544194, "above": false}, {"endpoint": 70, "start": 90, "slope": -0.51356, "above": false}, {"endpoint": 70, "start": 100, "slope": -0.714583, "above": false}, {"endpoint": 70, "start": 110, "slope": -1.039437, "above": false}, {"endpoint": 70, "start": 120, "slope": -0.894443, "above": false}, {"endpoint": 70, "start": 130, "slope": -0.883891, "above": false}, {"endpoint": 70, "start": 140, "slope": -0.238385, "above": false}, {"endpoint": 70, "start": 150, "slope": 0.536701, "above": false}, {"endpoint": 70, "start": 160, "slope": 1.098071, "above": false}, {"endpoint": 70, "start": 170, "slope": 1.656316, "above": false}, {"endpoint": 80, "start": 90, "slope": 2.517073, "above": false}, {"endpoint": 80, "start": 100, "slope": 0.700223, "above": false}, {"endpoint": 80, "start": 110, "slope": -0.204519, "above": false}, {"endpoint": 80, "start": 120, "slope": -0.232005, "above": false}, {"endpoint": 80, "start": 130, "slope": -0.35183, "above": false}, {"endpoint": 80, "start": 140, "slope": 0.312583, "above": false}, {"endpoint": 80, "start": 150, "slope": 1.119685, "above": false}, {"endpoint": 80, "start": 160, "slope": 1.678354, "above": false}, {"endpoint": 80, "start": 170, "slope": 2.234151, "above": false}, {"endpoint": 80, "start": 180, "slope": 2.59217, "above": false}, {"endpoint": 90, "start": 100, "slope": -1.116628, "above": false}, {"endpoint": 90, "start": 110, "slope": -1.565314, "above": false}, {"endpoint": 90, "start": 120, "slope": -1.148364, "above": false}, {"endpoint": 90, "start": 130, "slope": -1.069056, "above": false}, {"endpoint": 90, "start": 140, "slope": -0.128315, "above": false}, {"endpoint": 90, "start": 150, "slope": 0.886787, "above": false}, {"endpoint": 90, "start": 160, "slope": 1.558537, "above": false}, {"endpoint": 90, "start": 170, "slope": 2.198785, "above": false}, {"endpoint": 90, "start": 180, "slope": 2.600514, "above": false}, {"endpoint": 90, "start": 190, "slope": 3.001629, "above": false}, {"endpoint": 100, "start": 110, "slope": -2.014001, "above": false}, {"endpoint": 100, "start": 120, "slope": -1.164233, "above": false}, {"endpoint": 100, "start": 130, "slope": -1.053198, "above": false}, {"endpoint": 100, "start": 140, "slope": 0.118763, "above": false}, {"endpoint": 100, "start": 150, "slope": 1.287471, "above": false}, {"endpoint": 100, "start": 160, "slope": 2.004397, "above": false}, {"endpoint": 100, "start": 170, "slope": 2.672416, "above": false}, {"endpoint": 100, "start": 180, "slope": 3.065157, "above": false}, {"endpoint": 100, "start": 190, "slope": 3.459213, "above": false}, {"endpoint": 100, "start": 200, "slope": 3.59426, "above": false}], "row_scores": [0.0, 0.0, 0.0, 0.0, 0.0, 0.0, 0.0, 0.0, 0.0, 0.0], "sci": 0.0, "threshold": 0.01}, "latest_price": 361.83, "_meta": {"updated_at": "2026-03-29 test"}}